<profile>

<ReportVersion>
<Version>2023.1</Version>
</ReportVersion>

<UserAssignments>
<unit>ns</unit>
<ProductFamily>zynquplus</ProductFamily>
<Part>xczu7ev-ffvc1156-2-e</Part>
<TopModelName>network_top_Pipeline_load_weight1_matrix_inner_loop30</TopModelName>
<TargetClockPeriod>350.00</TargetClockPeriod>
<ClockUncertainty>94.50</ClockUncertainty>
<FlowTarget>vivado</FlowTarget>
</UserAssignments>

<PerformanceEstimates>
<PipelineType>no</PipelineType>
<SummaryOfTimingAnalysis>
<unit>ns</unit>
<EstimatedClockPeriod>255.500</EstimatedClockPeriod>
</SummaryOfTimingAnalysis>
<SummaryOfOverallLatency>
<unit>clock cycles</unit>
<Best-caseLatency>90</Best-caseLatency>
<Average-caseLatency>90</Average-caseLatency>
<Worst-caseLatency>90</Worst-caseLatency>
<Best-caseRealTimeLatency>31.500 us</Best-caseRealTimeLatency>
<Average-caseRealTimeLatency>31.500 us</Average-caseRealTimeLatency>
<Worst-caseRealTimeLatency>31.500 us</Worst-caseRealTimeLatency>
<Interval-min>90</Interval-min>
<Interval-max>90</Interval-max>
</SummaryOfOverallLatency>
<SummaryOfLoopLatency>
<load_weight1_matrix_inner_loop>
<Slack>255.50</Slack>
<TripCount>80</TripCount>
<Latency>88</Latency>
<AbsoluteTimeLatency>30800</AbsoluteTimeLatency>
<PipelineII>1</PipelineII>
<PipelineDepth>10</PipelineDepth>
<InstanceList>
</InstanceList>
</load_weight1_matrix_inner_loop>
</SummaryOfLoopLatency>
</PerformanceEstimates>

<AreaEstimates>
<Resources>
<DSP>0</DSP>
<FF>183</FF>
<LUT>323</LUT>
<BRAM_18K>0</BRAM_18K>
<URAM>0</URAM>
</Resources>
<AvailableResources>
<BRAM_18K>624</BRAM_18K>
<DSP>1728</DSP>
<FF>460800</FF>
<LUT>230400</LUT>
<URAM>96</URAM>
</AvailableResources>
</AreaEstimates>

<InterfaceSummary>
<RtlPorts>
<name>ap_clk</name>
<Object>network_top_Pipeline_load_weight1_matrix_inner_loop30</Object>
<Type>return value</Type>
<Scope></Scope>
<IOProtocol>ap_ctrl_hs</IOProtocol>
<IOConfig></IOConfig>
<Dir>in</Dir>
<Bits>1</Bits>
<Attribute>control</Attribute>
</RtlPorts>
<RtlPorts>
<name>ap_rst</name>
<Object>network_top_Pipeline_load_weight1_matrix_inner_loop30</Object>
<Type>return value</Type>
<Scope></Scope>
<IOProtocol>ap_ctrl_hs</IOProtocol>
<IOConfig></IOConfig>
<Dir>in</Dir>
<Bits>1</Bits>
<Attribute>control</Attribute>
</RtlPorts>
<RtlPorts>
<name>ap_start</name>
<Object>network_top_Pipeline_load_weight1_matrix_inner_loop30</Object>
<Type>return value</Type>
<Scope></Scope>
<IOProtocol>ap_ctrl_hs</IOProtocol>
<IOConfig></IOConfig>
<Dir>in</Dir>
<Bits>1</Bits>
<Attribute>control</Attribute>
</RtlPorts>
<RtlPorts>
<name>ap_done</name>
<Object>network_top_Pipeline_load_weight1_matrix_inner_loop30</Object>
<Type>return value</Type>
<Scope></Scope>
<IOProtocol>ap_ctrl_hs</IOProtocol>
<IOConfig></IOConfig>
<Dir>out</Dir>
<Bits>1</Bits>
<Attribute>control</Attribute>
</RtlPorts>
<RtlPorts>
<name>ap_idle</name>
<Object>network_top_Pipeline_load_weight1_matrix_inner_loop30</Object>
<Type>return value</Type>
<Scope></Scope>
<IOProtocol>ap_ctrl_hs</IOProtocol>
<IOConfig></IOConfig>
<Dir>out</Dir>
<Bits>1</Bits>
<Attribute>control</Attribute>
</RtlPorts>
<RtlPorts>
<name>ap_ready</name>
<Object>network_top_Pipeline_load_weight1_matrix_inner_loop30</Object>
<Type>return value</Type>
<Scope></Scope>
<IOProtocol>ap_ctrl_hs</IOProtocol>
<IOConfig></IOConfig>
<Dir>out</Dir>
<Bits>1</Bits>
<Attribute>control</Attribute>
</RtlPorts>
<RtlPorts>
<name>m_axi_gmem_AWVALID</name>
<Object>gmem</Object>
<Type>pointer</Type>
<Scope></Scope>
<IOProtocol>m_axi</IOProtocol>
<IOConfig></IOConfig>
<Dir>out</Dir>
<Bits>1</Bits>
<Attribute>unknown</Attribute>
</RtlPorts>
<RtlPorts>
<name>m_axi_gmem_AWREADY</name>
<Object>gmem</Object>
<Type>pointer</Type>
<Scope></Scope>
<IOProtocol>m_axi</IOProtocol>
<IOConfig></IOConfig>
<Dir>in</Dir>
<Bits>1</Bits>
<Attribute>unknown</Attribute>
</RtlPorts>
<RtlPorts>
<name>m_axi_gmem_AWADDR</name>
<Object>gmem</Object>
<Type>pointer</Type>
<Scope></Scope>
<IOProtocol>m_axi</IOProtocol>
<IOConfig></IOConfig>
<Dir>out</Dir>
<Bits>64</Bits>
<Attribute>unknown</Attribute>
</RtlPorts>
<RtlPorts>
<name>m_axi_gmem_AWID</name>
<Object>gmem</Object>
<Type>pointer</Type>
<Scope></Scope>
<IOProtocol>m_axi</IOProtocol>
<IOConfig></IOConfig>
<Dir>out</Dir>
<Bits>1</Bits>
<Attribute>unknown</Attribute>
</RtlPorts>
<RtlPorts>
<name>m_axi_gmem_AWLEN</name>
<Object>gmem</Object>
<Type>pointer</Type>
<Scope></Scope>
<IOProtocol>m_axi</IOProtocol>
<IOConfig></IOConfig>
<Dir>out</Dir>
<Bits>32</Bits>
<Attribute>unknown</Attribute>
</RtlPorts>
<RtlPorts>
<name>m_axi_gmem_AWSIZE</name>
<Object>gmem</Object>
<Type>pointer</Type>
<Scope></Scope>
<IOProtocol>m_axi</IOProtocol>
<IOConfig></IOConfig>
<Dir>out</Dir>
<Bits>3</Bits>
<Attribute>unknown</Attribute>
</RtlPorts>
<RtlPorts>
<name>m_axi_gmem_AWBURST</name>
<Object>gmem</Object>
<Type>pointer</Type>
<Scope></Scope>
<IOProtocol>m_axi</IOProtocol>
<IOConfig></IOConfig>
<Dir>out</Dir>
<Bits>2</Bits>
<Attribute>unknown</Attribute>
</RtlPorts>
<RtlPorts>
<name>m_axi_gmem_AWLOCK</name>
<Object>gmem</Object>
<Type>pointer</Type>
<Scope></Scope>
<IOProtocol>m_axi</IOProtocol>
<IOConfig></IOConfig>
<Dir>out</Dir>
<Bits>2</Bits>
<Attribute>unknown</Attribute>
</RtlPorts>
<RtlPorts>
<name>m_axi_gmem_AWCACHE</name>
<Object>gmem</Object>
<Type>pointer</Type>
<Scope></Scope>
<IOProtocol>m_axi</IOProtocol>
<IOConfig></IOConfig>
<Dir>out</Dir>
<Bits>4</Bits>
<Attribute>unknown</Attribute>
</RtlPorts>
<RtlPorts>
<name>m_axi_gmem_AWPROT</name>
<Object>gmem</Object>
<Type>pointer</Type>
<Scope></Scope>
<IOProtocol>m_axi</IOProtocol>
<IOConfig></IOConfig>
<Dir>out</Dir>
<Bits>3</Bits>
<Attribute>unknown</Attribute>
</RtlPorts>
<RtlPorts>
<name>m_axi_gmem_AWQOS</name>
<Object>gmem</Object>
<Type>pointer</Type>
<Scope></Scope>
<IOProtocol>m_axi</IOProtocol>
<IOConfig></IOConfig>
<Dir>out</Dir>
<Bits>4</Bits>
<Attribute>unknown</Attribute>
</RtlPorts>
<RtlPorts>
<name>m_axi_gmem_AWREGION</name>
<Object>gmem</Object>
<Type>pointer</Type>
<Scope></Scope>
<IOProtocol>m_axi</IOProtocol>
<IOConfig></IOConfig>
<Dir>out</Dir>
<Bits>4</Bits>
<Attribute>unknown</Attribute>
</RtlPorts>
<RtlPorts>
<name>m_axi_gmem_AWUSER</name>
<Object>gmem</Object>
<Type>pointer</Type>
<Scope></Scope>
<IOProtocol>m_axi</IOProtocol>
<IOConfig></IOConfig>
<Dir>out</Dir>
<Bits>1</Bits>
<Attribute>unknown</Attribute>
</RtlPorts>
<RtlPorts>
<name>m_axi_gmem_WVALID</name>
<Object>gmem</Object>
<Type>pointer</Type>
<Scope></Scope>
<IOProtocol>m_axi</IOProtocol>
<IOConfig></IOConfig>
<Dir>out</Dir>
<Bits>1</Bits>
<Attribute>unknown</Attribute>
</RtlPorts>
<RtlPorts>
<name>m_axi_gmem_WREADY</name>
<Object>gmem</Object>
<Type>pointer</Type>
<Scope></Scope>
<IOProtocol>m_axi</IOProtocol>
<IOConfig></IOConfig>
<Dir>in</Dir>
<Bits>1</Bits>
<Attribute>unknown</Attribute>
</RtlPorts>
<RtlPorts>
<name>m_axi_gmem_WDATA</name>
<Object>gmem</Object>
<Type>pointer</Type>
<Scope></Scope>
<IOProtocol>m_axi</IOProtocol>
<IOConfig></IOConfig>
<Dir>out</Dir>
<Bits>32</Bits>
<Attribute>unknown</Attribute>
</RtlPorts>
<RtlPorts>
<name>m_axi_gmem_WSTRB</name>
<Object>gmem</Object>
<Type>pointer</Type>
<Scope></Scope>
<IOProtocol>m_axi</IOProtocol>
<IOConfig></IOConfig>
<Dir>out</Dir>
<Bits>4</Bits>
<Attribute>unknown</Attribute>
</RtlPorts>
<RtlPorts>
<name>m_axi_gmem_WLAST</name>
<Object>gmem</Object>
<Type>pointer</Type>
<Scope></Scope>
<IOProtocol>m_axi</IOProtocol>
<IOConfig></IOConfig>
<Dir>out</Dir>
<Bits>1</Bits>
<Attribute>unknown</Attribute>
</RtlPorts>
<RtlPorts>
<name>m_axi_gmem_WID</name>
<Object>gmem</Object>
<Type>pointer</Type>
<Scope></Scope>
<IOProtocol>m_axi</IOProtocol>
<IOConfig></IOConfig>
<Dir>out</Dir>
<Bits>1</Bits>
<Attribute>unknown</Attribute>
</RtlPorts>
<RtlPorts>
<name>m_axi_gmem_WUSER</name>
<Object>gmem</Object>
<Type>pointer</Type>
<Scope></Scope>
<IOProtocol>m_axi</IOProtocol>
<IOConfig></IOConfig>
<Dir>out</Dir>
<Bits>1</Bits>
<Attribute>unknown</Attribute>
</RtlPorts>
<RtlPorts>
<name>m_axi_gmem_ARVALID</name>
<Object>gmem</Object>
<Type>pointer</Type>
<Scope></Scope>
<IOProtocol>m_axi</IOProtocol>
<IOConfig></IOConfig>
<Dir>out</Dir>
<Bits>1</Bits>
<Attribute>unknown</Attribute>
</RtlPorts>
<RtlPorts>
<name>m_axi_gmem_ARREADY</name>
<Object>gmem</Object>
<Type>pointer</Type>
<Scope></Scope>
<IOProtocol>m_axi</IOProtocol>
<IOConfig></IOConfig>
<Dir>in</Dir>
<Bits>1</Bits>
<Attribute>unknown</Attribute>
</RtlPorts>
<RtlPorts>
<name>m_axi_gmem_ARADDR</name>
<Object>gmem</Object>
<Type>pointer</Type>
<Scope></Scope>
<IOProtocol>m_axi</IOProtocol>
<IOConfig></IOConfig>
<Dir>out</Dir>
<Bits>64</Bits>
<Attribute>unknown</Attribute>
</RtlPorts>
<RtlPorts>
<name>m_axi_gmem_ARID</name>
<Object>gmem</Object>
<Type>pointer</Type>
<Scope></Scope>
<IOProtocol>m_axi</IOProtocol>
<IOConfig></IOConfig>
<Dir>out</Dir>
<Bits>1</Bits>
<Attribute>unknown</Attribute>
</RtlPorts>
<RtlPorts>
<name>m_axi_gmem_ARLEN</name>
<Object>gmem</Object>
<Type>pointer</Type>
<Scope></Scope>
<IOProtocol>m_axi</IOProtocol>
<IOConfig></IOConfig>
<Dir>out</Dir>
<Bits>32</Bits>
<Attribute>unknown</Attribute>
</RtlPorts>
<RtlPorts>
<name>m_axi_gmem_ARSIZE</name>
<Object>gmem</Object>
<Type>pointer</Type>
<Scope></Scope>
<IOProtocol>m_axi</IOProtocol>
<IOConfig></IOConfig>
<Dir>out</Dir>
<Bits>3</Bits>
<Attribute>unknown</Attribute>
</RtlPorts>
<RtlPorts>
<name>m_axi_gmem_ARBURST</name>
<Object>gmem</Object>
<Type>pointer</Type>
<Scope></Scope>
<IOProtocol>m_axi</IOProtocol>
<IOConfig></IOConfig>
<Dir>out</Dir>
<Bits>2</Bits>
<Attribute>unknown</Attribute>
</RtlPorts>
<RtlPorts>
<name>m_axi_gmem_ARLOCK</name>
<Object>gmem</Object>
<Type>pointer</Type>
<Scope></Scope>
<IOProtocol>m_axi</IOProtocol>
<IOConfig></IOConfig>
<Dir>out</Dir>
<Bits>2</Bits>
<Attribute>unknown</Attribute>
</RtlPorts>
<RtlPorts>
<name>m_axi_gmem_ARCACHE</name>
<Object>gmem</Object>
<Type>pointer</Type>
<Scope></Scope>
<IOProtocol>m_axi</IOProtocol>
<IOConfig></IOConfig>
<Dir>out</Dir>
<Bits>4</Bits>
<Attribute>unknown</Attribute>
</RtlPorts>
<RtlPorts>
<name>m_axi_gmem_ARPROT</name>
<Object>gmem</Object>
<Type>pointer</Type>
<Scope></Scope>
<IOProtocol>m_axi</IOProtocol>
<IOConfig></IOConfig>
<Dir>out</Dir>
<Bits>3</Bits>
<Attribute>unknown</Attribute>
</RtlPorts>
<RtlPorts>
<name>m_axi_gmem_ARQOS</name>
<Object>gmem</Object>
<Type>pointer</Type>
<Scope></Scope>
<IOProtocol>m_axi</IOProtocol>
<IOConfig></IOConfig>
<Dir>out</Dir>
<Bits>4</Bits>
<Attribute>unknown</Attribute>
</RtlPorts>
<RtlPorts>
<name>m_axi_gmem_ARREGION</name>
<Object>gmem</Object>
<Type>pointer</Type>
<Scope></Scope>
<IOProtocol>m_axi</IOProtocol>
<IOConfig></IOConfig>
<Dir>out</Dir>
<Bits>4</Bits>
<Attribute>unknown</Attribute>
</RtlPorts>
<RtlPorts>
<name>m_axi_gmem_ARUSER</name>
<Object>gmem</Object>
<Type>pointer</Type>
<Scope></Scope>
<IOProtocol>m_axi</IOProtocol>
<IOConfig></IOConfig>
<Dir>out</Dir>
<Bits>1</Bits>
<Attribute>unknown</Attribute>
</RtlPorts>
<RtlPorts>
<name>m_axi_gmem_RVALID</name>
<Object>gmem</Object>
<Type>pointer</Type>
<Scope></Scope>
<IOProtocol>m_axi</IOProtocol>
<IOConfig></IOConfig>
<Dir>in</Dir>
<Bits>1</Bits>
<Attribute>unknown</Attribute>
</RtlPorts>
<RtlPorts>
<name>m_axi_gmem_RREADY</name>
<Object>gmem</Object>
<Type>pointer</Type>
<Scope></Scope>
<IOProtocol>m_axi</IOProtocol>
<IOConfig></IOConfig>
<Dir>out</Dir>
<Bits>1</Bits>
<Attribute>unknown</Attribute>
</RtlPorts>
<RtlPorts>
<name>m_axi_gmem_RDATA</name>
<Object>gmem</Object>
<Type>pointer</Type>
<Scope></Scope>
<IOProtocol>m_axi</IOProtocol>
<IOConfig></IOConfig>
<Dir>in</Dir>
<Bits>32</Bits>
<Attribute>unknown</Attribute>
</RtlPorts>
<RtlPorts>
<name>m_axi_gmem_RLAST</name>
<Object>gmem</Object>
<Type>pointer</Type>
<Scope></Scope>
<IOProtocol>m_axi</IOProtocol>
<IOConfig></IOConfig>
<Dir>in</Dir>
<Bits>1</Bits>
<Attribute>unknown</Attribute>
</RtlPorts>
<RtlPorts>
<name>m_axi_gmem_RID</name>
<Object>gmem</Object>
<Type>pointer</Type>
<Scope></Scope>
<IOProtocol>m_axi</IOProtocol>
<IOConfig></IOConfig>
<Dir>in</Dir>
<Bits>1</Bits>
<Attribute>unknown</Attribute>
</RtlPorts>
<RtlPorts>
<name>m_axi_gmem_RFIFONUM</name>
<Object>gmem</Object>
<Type>pointer</Type>
<Scope></Scope>
<IOProtocol>m_axi</IOProtocol>
<IOConfig></IOConfig>
<Dir>in</Dir>
<Bits>9</Bits>
<Attribute>unknown</Attribute>
</RtlPorts>
<RtlPorts>
<name>m_axi_gmem_RUSER</name>
<Object>gmem</Object>
<Type>pointer</Type>
<Scope></Scope>
<IOProtocol>m_axi</IOProtocol>
<IOConfig></IOConfig>
<Dir>in</Dir>
<Bits>1</Bits>
<Attribute>unknown</Attribute>
</RtlPorts>
<RtlPorts>
<name>m_axi_gmem_RRESP</name>
<Object>gmem</Object>
<Type>pointer</Type>
<Scope></Scope>
<IOProtocol>m_axi</IOProtocol>
<IOConfig></IOConfig>
<Dir>in</Dir>
<Bits>2</Bits>
<Attribute>unknown</Attribute>
</RtlPorts>
<RtlPorts>
<name>m_axi_gmem_BVALID</name>
<Object>gmem</Object>
<Type>pointer</Type>
<Scope></Scope>
<IOProtocol>m_axi</IOProtocol>
<IOConfig></IOConfig>
<Dir>in</Dir>
<Bits>1</Bits>
<Attribute>unknown</Attribute>
</RtlPorts>
<RtlPorts>
<name>m_axi_gmem_BREADY</name>
<Object>gmem</Object>
<Type>pointer</Type>
<Scope></Scope>
<IOProtocol>m_axi</IOProtocol>
<IOConfig></IOConfig>
<Dir>out</Dir>
<Bits>1</Bits>
<Attribute>unknown</Attribute>
</RtlPorts>
<RtlPorts>
<name>m_axi_gmem_BRESP</name>
<Object>gmem</Object>
<Type>pointer</Type>
<Scope></Scope>
<IOProtocol>m_axi</IOProtocol>
<IOConfig></IOConfig>
<Dir>in</Dir>
<Bits>2</Bits>
<Attribute>unknown</Attribute>
</RtlPorts>
<RtlPorts>
<name>m_axi_gmem_BID</name>
<Object>gmem</Object>
<Type>pointer</Type>
<Scope></Scope>
<IOProtocol>m_axi</IOProtocol>
<IOConfig></IOConfig>
<Dir>in</Dir>
<Bits>1</Bits>
<Attribute>unknown</Attribute>
</RtlPorts>
<RtlPorts>
<name>m_axi_gmem_BUSER</name>
<Object>gmem</Object>
<Type>pointer</Type>
<Scope></Scope>
<IOProtocol>m_axi</IOProtocol>
<IOConfig></IOConfig>
<Dir>in</Dir>
<Bits>1</Bits>
<Attribute>unknown</Attribute>
</RtlPorts>
<RtlPorts>
<name>myparams</name>
<Object>myparams</Object>
<Type>scalar</Type>
<Scope></Scope>
<IOProtocol>ap_none</IOProtocol>
<IOConfig></IOConfig>
<Dir>in</Dir>
<Bits>64</Bits>
<Attribute>data</Attribute>
</RtlPorts>
<RtlPorts>
<name>p_ZZ11network_topP13params_structP8ap_fixedILi22ELi17EL9ap_q_mode0EL9ap_o_mode0EL_11855</name>
<Object>p_ZZ11network_topP13params_structP8ap_fixedILi22ELi17EL9ap_q_mode0EL9ap_o_mode0EL_11855</Object>
<Type>pointer</Type>
<Scope>global</Scope>
<IOProtocol>ap_vld</IOProtocol>
<IOConfig></IOConfig>
<Dir>out</Dir>
<Bits>22</Bits>
<Attribute>data</Attribute>
</RtlPorts>
<RtlPorts>
<name>p_ZZ11network_topP13params_structP8ap_fixedILi22ELi17EL9ap_q_mode0EL9ap_o_mode0EL_11855_ap_vld</name>
<Object>p_ZZ11network_topP13params_structP8ap_fixedILi22ELi17EL9ap_q_mode0EL9ap_o_mode0EL_11855</Object>
<Type>pointer</Type>
<Scope>global</Scope>
<IOProtocol>ap_vld</IOProtocol>
<IOConfig></IOConfig>
<Dir>out</Dir>
<Bits>1</Bits>
<Attribute>control</Attribute>
</RtlPorts>
<RtlPorts>
<name>p_ZZ11network_topP13params_structP8ap_fixedILi22ELi17EL9ap_q_mode0EL9ap_o_mode0EL_11856</name>
<Object>p_ZZ11network_topP13params_structP8ap_fixedILi22ELi17EL9ap_q_mode0EL9ap_o_mode0EL_11856</Object>
<Type>pointer</Type>
<Scope>global</Scope>
<IOProtocol>ap_vld</IOProtocol>
<IOConfig></IOConfig>
<Dir>out</Dir>
<Bits>22</Bits>
<Attribute>data</Attribute>
</RtlPorts>
<RtlPorts>
<name>p_ZZ11network_topP13params_structP8ap_fixedILi22ELi17EL9ap_q_mode0EL9ap_o_mode0EL_11856_ap_vld</name>
<Object>p_ZZ11network_topP13params_structP8ap_fixedILi22ELi17EL9ap_q_mode0EL9ap_o_mode0EL_11856</Object>
<Type>pointer</Type>
<Scope>global</Scope>
<IOProtocol>ap_vld</IOProtocol>
<IOConfig></IOConfig>
<Dir>out</Dir>
<Bits>1</Bits>
<Attribute>control</Attribute>
</RtlPorts>
<RtlPorts>
<name>p_ZZ11network_topP13params_structP8ap_fixedILi22ELi17EL9ap_q_mode0EL9ap_o_mode0EL_11868</name>
<Object>p_ZZ11network_topP13params_structP8ap_fixedILi22ELi17EL9ap_q_mode0EL9ap_o_mode0EL_11868</Object>
<Type>pointer</Type>
<Scope>global</Scope>
<IOProtocol>ap_vld</IOProtocol>
<IOConfig></IOConfig>
<Dir>out</Dir>
<Bits>22</Bits>
<Attribute>data</Attribute>
</RtlPorts>
<RtlPorts>
<name>p_ZZ11network_topP13params_structP8ap_fixedILi22ELi17EL9ap_q_mode0EL9ap_o_mode0EL_11868_ap_vld</name>
<Object>p_ZZ11network_topP13params_structP8ap_fixedILi22ELi17EL9ap_q_mode0EL9ap_o_mode0EL_11868</Object>
<Type>pointer</Type>
<Scope>global</Scope>
<IOProtocol>ap_vld</IOProtocol>
<IOConfig></IOConfig>
<Dir>out</Dir>
<Bits>1</Bits>
<Attribute>control</Attribute>
</RtlPorts>
<RtlPorts>
<name>p_ZZ11network_topP13params_structP8ap_fixedILi22ELi17EL9ap_q_mode0EL9ap_o_mode0EL_11880</name>
<Object>p_ZZ11network_topP13params_structP8ap_fixedILi22ELi17EL9ap_q_mode0EL9ap_o_mode0EL_11880</Object>
<Type>pointer</Type>
<Scope>global</Scope>
<IOProtocol>ap_vld</IOProtocol>
<IOConfig></IOConfig>
<Dir>out</Dir>
<Bits>22</Bits>
<Attribute>data</Attribute>
</RtlPorts>
<RtlPorts>
<name>p_ZZ11network_topP13params_structP8ap_fixedILi22ELi17EL9ap_q_mode0EL9ap_o_mode0EL_11880_ap_vld</name>
<Object>p_ZZ11network_topP13params_structP8ap_fixedILi22ELi17EL9ap_q_mode0EL9ap_o_mode0EL_11880</Object>
<Type>pointer</Type>
<Scope>global</Scope>
<IOProtocol>ap_vld</IOProtocol>
<IOConfig></IOConfig>
<Dir>out</Dir>
<Bits>1</Bits>
<Attribute>control</Attribute>
</RtlPorts>
<RtlPorts>
<name>p_ZZ11network_topP13params_structP8ap_fixedILi22ELi17EL9ap_q_mode0EL9ap_o_mode0EL_11892</name>
<Object>p_ZZ11network_topP13params_structP8ap_fixedILi22ELi17EL9ap_q_mode0EL9ap_o_mode0EL_11892</Object>
<Type>pointer</Type>
<Scope>global</Scope>
<IOProtocol>ap_vld</IOProtocol>
<IOConfig></IOConfig>
<Dir>out</Dir>
<Bits>22</Bits>
<Attribute>data</Attribute>
</RtlPorts>
<RtlPorts>
<name>p_ZZ11network_topP13params_structP8ap_fixedILi22ELi17EL9ap_q_mode0EL9ap_o_mode0EL_11892_ap_vld</name>
<Object>p_ZZ11network_topP13params_structP8ap_fixedILi22ELi17EL9ap_q_mode0EL9ap_o_mode0EL_11892</Object>
<Type>pointer</Type>
<Scope>global</Scope>
<IOProtocol>ap_vld</IOProtocol>
<IOConfig></IOConfig>
<Dir>out</Dir>
<Bits>1</Bits>
<Attribute>control</Attribute>
</RtlPorts>
<RtlPorts>
<name>p_ZZ11network_topP13params_structP8ap_fixedILi22ELi17EL9ap_q_mode0EL9ap_o_mode0EL_11904</name>
<Object>p_ZZ11network_topP13params_structP8ap_fixedILi22ELi17EL9ap_q_mode0EL9ap_o_mode0EL_11904</Object>
<Type>pointer</Type>
<Scope>global</Scope>
<IOProtocol>ap_vld</IOProtocol>
<IOConfig></IOConfig>
<Dir>out</Dir>
<Bits>22</Bits>
<Attribute>data</Attribute>
</RtlPorts>
<RtlPorts>
<name>p_ZZ11network_topP13params_structP8ap_fixedILi22ELi17EL9ap_q_mode0EL9ap_o_mode0EL_11904_ap_vld</name>
<Object>p_ZZ11network_topP13params_structP8ap_fixedILi22ELi17EL9ap_q_mode0EL9ap_o_mode0EL_11904</Object>
<Type>pointer</Type>
<Scope>global</Scope>
<IOProtocol>ap_vld</IOProtocol>
<IOConfig></IOConfig>
<Dir>out</Dir>
<Bits>1</Bits>
<Attribute>control</Attribute>
</RtlPorts>
<RtlPorts>
<name>p_ZZ11network_topP13params_structP8ap_fixedILi22ELi17EL9ap_q_mode0EL9ap_o_mode0EL_11916</name>
<Object>p_ZZ11network_topP13params_structP8ap_fixedILi22ELi17EL9ap_q_mode0EL9ap_o_mode0EL_11916</Object>
<Type>pointer</Type>
<Scope>global</Scope>
<IOProtocol>ap_vld</IOProtocol>
<IOConfig></IOConfig>
<Dir>out</Dir>
<Bits>22</Bits>
<Attribute>data</Attribute>
</RtlPorts>
<RtlPorts>
<name>p_ZZ11network_topP13params_structP8ap_fixedILi22ELi17EL9ap_q_mode0EL9ap_o_mode0EL_11916_ap_vld</name>
<Object>p_ZZ11network_topP13params_structP8ap_fixedILi22ELi17EL9ap_q_mode0EL9ap_o_mode0EL_11916</Object>
<Type>pointer</Type>
<Scope>global</Scope>
<IOProtocol>ap_vld</IOProtocol>
<IOConfig></IOConfig>
<Dir>out</Dir>
<Bits>1</Bits>
<Attribute>control</Attribute>
</RtlPorts>
<RtlPorts>
<name>p_ZZ11network_topP13params_structP8ap_fixedILi22ELi17EL9ap_q_mode0EL9ap_o_mode0EL_11928</name>
<Object>p_ZZ11network_topP13params_structP8ap_fixedILi22ELi17EL9ap_q_mode0EL9ap_o_mode0EL_11928</Object>
<Type>pointer</Type>
<Scope>global</Scope>
<IOProtocol>ap_vld</IOProtocol>
<IOConfig></IOConfig>
<Dir>out</Dir>
<Bits>22</Bits>
<Attribute>data</Attribute>
</RtlPorts>
<RtlPorts>
<name>p_ZZ11network_topP13params_structP8ap_fixedILi22ELi17EL9ap_q_mode0EL9ap_o_mode0EL_11928_ap_vld</name>
<Object>p_ZZ11network_topP13params_structP8ap_fixedILi22ELi17EL9ap_q_mode0EL9ap_o_mode0EL_11928</Object>
<Type>pointer</Type>
<Scope>global</Scope>
<IOProtocol>ap_vld</IOProtocol>
<IOConfig></IOConfig>
<Dir>out</Dir>
<Bits>1</Bits>
<Attribute>control</Attribute>
</RtlPorts>
<RtlPorts>
<name>p_ZZ11network_topP13params_structP8ap_fixedILi22ELi17EL9ap_q_mode0EL9ap_o_mode0EL_11940</name>
<Object>p_ZZ11network_topP13params_structP8ap_fixedILi22ELi17EL9ap_q_mode0EL9ap_o_mode0EL_11940</Object>
<Type>pointer</Type>
<Scope>global</Scope>
<IOProtocol>ap_vld</IOProtocol>
<IOConfig></IOConfig>
<Dir>out</Dir>
<Bits>22</Bits>
<Attribute>data</Attribute>
</RtlPorts>
<RtlPorts>
<name>p_ZZ11network_topP13params_structP8ap_fixedILi22ELi17EL9ap_q_mode0EL9ap_o_mode0EL_11940_ap_vld</name>
<Object>p_ZZ11network_topP13params_structP8ap_fixedILi22ELi17EL9ap_q_mode0EL9ap_o_mode0EL_11940</Object>
<Type>pointer</Type>
<Scope>global</Scope>
<IOProtocol>ap_vld</IOProtocol>
<IOConfig></IOConfig>
<Dir>out</Dir>
<Bits>1</Bits>
<Attribute>control</Attribute>
</RtlPorts>
<RtlPorts>
<name>p_ZZ11network_topP13params_structP8ap_fixedILi22ELi17EL9ap_q_mode0EL9ap_o_mode0EL_11941</name>
<Object>p_ZZ11network_topP13params_structP8ap_fixedILi22ELi17EL9ap_q_mode0EL9ap_o_mode0EL_11941</Object>
<Type>pointer</Type>
<Scope>global</Scope>
<IOProtocol>ap_vld</IOProtocol>
<IOConfig></IOConfig>
<Dir>out</Dir>
<Bits>22</Bits>
<Attribute>data</Attribute>
</RtlPorts>
<RtlPorts>
<name>p_ZZ11network_topP13params_structP8ap_fixedILi22ELi17EL9ap_q_mode0EL9ap_o_mode0EL_11941_ap_vld</name>
<Object>p_ZZ11network_topP13params_structP8ap_fixedILi22ELi17EL9ap_q_mode0EL9ap_o_mode0EL_11941</Object>
<Type>pointer</Type>
<Scope>global</Scope>
<IOProtocol>ap_vld</IOProtocol>
<IOConfig></IOConfig>
<Dir>out</Dir>
<Bits>1</Bits>
<Attribute>control</Attribute>
</RtlPorts>
<RtlPorts>
<name>p_ZZ11network_topP13params_structP8ap_fixedILi22ELi17EL9ap_q_mode0EL9ap_o_mode0EL_11857</name>
<Object>p_ZZ11network_topP13params_structP8ap_fixedILi22ELi17EL9ap_q_mode0EL9ap_o_mode0EL_11857</Object>
<Type>pointer</Type>
<Scope>global</Scope>
<IOProtocol>ap_vld</IOProtocol>
<IOConfig></IOConfig>
<Dir>out</Dir>
<Bits>22</Bits>
<Attribute>data</Attribute>
</RtlPorts>
<RtlPorts>
<name>p_ZZ11network_topP13params_structP8ap_fixedILi22ELi17EL9ap_q_mode0EL9ap_o_mode0EL_11857_ap_vld</name>
<Object>p_ZZ11network_topP13params_structP8ap_fixedILi22ELi17EL9ap_q_mode0EL9ap_o_mode0EL_11857</Object>
<Type>pointer</Type>
<Scope>global</Scope>
<IOProtocol>ap_vld</IOProtocol>
<IOConfig></IOConfig>
<Dir>out</Dir>
<Bits>1</Bits>
<Attribute>control</Attribute>
</RtlPorts>
<RtlPorts>
<name>p_ZZ11network_topP13params_structP8ap_fixedILi22ELi17EL9ap_q_mode0EL9ap_o_mode0EL_11858</name>
<Object>p_ZZ11network_topP13params_structP8ap_fixedILi22ELi17EL9ap_q_mode0EL9ap_o_mode0EL_11858</Object>
<Type>pointer</Type>
<Scope>global</Scope>
<IOProtocol>ap_vld</IOProtocol>
<IOConfig></IOConfig>
<Dir>out</Dir>
<Bits>22</Bits>
<Attribute>data</Attribute>
</RtlPorts>
<RtlPorts>
<name>p_ZZ11network_topP13params_structP8ap_fixedILi22ELi17EL9ap_q_mode0EL9ap_o_mode0EL_11858_ap_vld</name>
<Object>p_ZZ11network_topP13params_structP8ap_fixedILi22ELi17EL9ap_q_mode0EL9ap_o_mode0EL_11858</Object>
<Type>pointer</Type>
<Scope>global</Scope>
<IOProtocol>ap_vld</IOProtocol>
<IOConfig></IOConfig>
<Dir>out</Dir>
<Bits>1</Bits>
<Attribute>control</Attribute>
</RtlPorts>
<RtlPorts>
<name>p_ZZ11network_topP13params_structP8ap_fixedILi22ELi17EL9ap_q_mode0EL9ap_o_mode0EL_11859</name>
<Object>p_ZZ11network_topP13params_structP8ap_fixedILi22ELi17EL9ap_q_mode0EL9ap_o_mode0EL_11859</Object>
<Type>pointer</Type>
<Scope>global</Scope>
<IOProtocol>ap_vld</IOProtocol>
<IOConfig></IOConfig>
<Dir>out</Dir>
<Bits>22</Bits>
<Attribute>data</Attribute>
</RtlPorts>
<RtlPorts>
<name>p_ZZ11network_topP13params_structP8ap_fixedILi22ELi17EL9ap_q_mode0EL9ap_o_mode0EL_11859_ap_vld</name>
<Object>p_ZZ11network_topP13params_structP8ap_fixedILi22ELi17EL9ap_q_mode0EL9ap_o_mode0EL_11859</Object>
<Type>pointer</Type>
<Scope>global</Scope>
<IOProtocol>ap_vld</IOProtocol>
<IOConfig></IOConfig>
<Dir>out</Dir>
<Bits>1</Bits>
<Attribute>control</Attribute>
</RtlPorts>
<RtlPorts>
<name>p_ZZ11network_topP13params_structP8ap_fixedILi22ELi17EL9ap_q_mode0EL9ap_o_mode0EL_11860</name>
<Object>p_ZZ11network_topP13params_structP8ap_fixedILi22ELi17EL9ap_q_mode0EL9ap_o_mode0EL_11860</Object>
<Type>pointer</Type>
<Scope>global</Scope>
<IOProtocol>ap_vld</IOProtocol>
<IOConfig></IOConfig>
<Dir>out</Dir>
<Bits>22</Bits>
<Attribute>data</Attribute>
</RtlPorts>
<RtlPorts>
<name>p_ZZ11network_topP13params_structP8ap_fixedILi22ELi17EL9ap_q_mode0EL9ap_o_mode0EL_11860_ap_vld</name>
<Object>p_ZZ11network_topP13params_structP8ap_fixedILi22ELi17EL9ap_q_mode0EL9ap_o_mode0EL_11860</Object>
<Type>pointer</Type>
<Scope>global</Scope>
<IOProtocol>ap_vld</IOProtocol>
<IOConfig></IOConfig>
<Dir>out</Dir>
<Bits>1</Bits>
<Attribute>control</Attribute>
</RtlPorts>
<RtlPorts>
<name>p_ZZ11network_topP13params_structP8ap_fixedILi22ELi17EL9ap_q_mode0EL9ap_o_mode0EL_11861</name>
<Object>p_ZZ11network_topP13params_structP8ap_fixedILi22ELi17EL9ap_q_mode0EL9ap_o_mode0EL_11861</Object>
<Type>pointer</Type>
<Scope>global</Scope>
<IOProtocol>ap_vld</IOProtocol>
<IOConfig></IOConfig>
<Dir>out</Dir>
<Bits>22</Bits>
<Attribute>data</Attribute>
</RtlPorts>
<RtlPorts>
<name>p_ZZ11network_topP13params_structP8ap_fixedILi22ELi17EL9ap_q_mode0EL9ap_o_mode0EL_11861_ap_vld</name>
<Object>p_ZZ11network_topP13params_structP8ap_fixedILi22ELi17EL9ap_q_mode0EL9ap_o_mode0EL_11861</Object>
<Type>pointer</Type>
<Scope>global</Scope>
<IOProtocol>ap_vld</IOProtocol>
<IOConfig></IOConfig>
<Dir>out</Dir>
<Bits>1</Bits>
<Attribute>control</Attribute>
</RtlPorts>
<RtlPorts>
<name>p_ZZ11network_topP13params_structP8ap_fixedILi22ELi17EL9ap_q_mode0EL9ap_o_mode0EL_11862</name>
<Object>p_ZZ11network_topP13params_structP8ap_fixedILi22ELi17EL9ap_q_mode0EL9ap_o_mode0EL_11862</Object>
<Type>pointer</Type>
<Scope>global</Scope>
<IOProtocol>ap_vld</IOProtocol>
<IOConfig></IOConfig>
<Dir>out</Dir>
<Bits>22</Bits>
<Attribute>data</Attribute>
</RtlPorts>
<RtlPorts>
<name>p_ZZ11network_topP13params_structP8ap_fixedILi22ELi17EL9ap_q_mode0EL9ap_o_mode0EL_11862_ap_vld</name>
<Object>p_ZZ11network_topP13params_structP8ap_fixedILi22ELi17EL9ap_q_mode0EL9ap_o_mode0EL_11862</Object>
<Type>pointer</Type>
<Scope>global</Scope>
<IOProtocol>ap_vld</IOProtocol>
<IOConfig></IOConfig>
<Dir>out</Dir>
<Bits>1</Bits>
<Attribute>control</Attribute>
</RtlPorts>
<RtlPorts>
<name>p_ZZ11network_topP13params_structP8ap_fixedILi22ELi17EL9ap_q_mode0EL9ap_o_mode0EL_11863</name>
<Object>p_ZZ11network_topP13params_structP8ap_fixedILi22ELi17EL9ap_q_mode0EL9ap_o_mode0EL_11863</Object>
<Type>pointer</Type>
<Scope>global</Scope>
<IOProtocol>ap_vld</IOProtocol>
<IOConfig></IOConfig>
<Dir>out</Dir>
<Bits>22</Bits>
<Attribute>data</Attribute>
</RtlPorts>
<RtlPorts>
<name>p_ZZ11network_topP13params_structP8ap_fixedILi22ELi17EL9ap_q_mode0EL9ap_o_mode0EL_11863_ap_vld</name>
<Object>p_ZZ11network_topP13params_structP8ap_fixedILi22ELi17EL9ap_q_mode0EL9ap_o_mode0EL_11863</Object>
<Type>pointer</Type>
<Scope>global</Scope>
<IOProtocol>ap_vld</IOProtocol>
<IOConfig></IOConfig>
<Dir>out</Dir>
<Bits>1</Bits>
<Attribute>control</Attribute>
</RtlPorts>
<RtlPorts>
<name>p_ZZ11network_topP13params_structP8ap_fixedILi22ELi17EL9ap_q_mode0EL9ap_o_mode0EL_11864</name>
<Object>p_ZZ11network_topP13params_structP8ap_fixedILi22ELi17EL9ap_q_mode0EL9ap_o_mode0EL_11864</Object>
<Type>pointer</Type>
<Scope>global</Scope>
<IOProtocol>ap_vld</IOProtocol>
<IOConfig></IOConfig>
<Dir>out</Dir>
<Bits>22</Bits>
<Attribute>data</Attribute>
</RtlPorts>
<RtlPorts>
<name>p_ZZ11network_topP13params_structP8ap_fixedILi22ELi17EL9ap_q_mode0EL9ap_o_mode0EL_11864_ap_vld</name>
<Object>p_ZZ11network_topP13params_structP8ap_fixedILi22ELi17EL9ap_q_mode0EL9ap_o_mode0EL_11864</Object>
<Type>pointer</Type>
<Scope>global</Scope>
<IOProtocol>ap_vld</IOProtocol>
<IOConfig></IOConfig>
<Dir>out</Dir>
<Bits>1</Bits>
<Attribute>control</Attribute>
</RtlPorts>
<RtlPorts>
<name>p_ZZ11network_topP13params_structP8ap_fixedILi22ELi17EL9ap_q_mode0EL9ap_o_mode0EL_11866</name>
<Object>p_ZZ11network_topP13params_structP8ap_fixedILi22ELi17EL9ap_q_mode0EL9ap_o_mode0EL_11866</Object>
<Type>pointer</Type>
<Scope>global</Scope>
<IOProtocol>ap_vld</IOProtocol>
<IOConfig></IOConfig>
<Dir>out</Dir>
<Bits>22</Bits>
<Attribute>data</Attribute>
</RtlPorts>
<RtlPorts>
<name>p_ZZ11network_topP13params_structP8ap_fixedILi22ELi17EL9ap_q_mode0EL9ap_o_mode0EL_11866_ap_vld</name>
<Object>p_ZZ11network_topP13params_structP8ap_fixedILi22ELi17EL9ap_q_mode0EL9ap_o_mode0EL_11866</Object>
<Type>pointer</Type>
<Scope>global</Scope>
<IOProtocol>ap_vld</IOProtocol>
<IOConfig></IOConfig>
<Dir>out</Dir>
<Bits>1</Bits>
<Attribute>control</Attribute>
</RtlPorts>
<RtlPorts>
<name>p_ZZ11network_topP13params_structP8ap_fixedILi22ELi17EL9ap_q_mode0EL9ap_o_mode0EL_11867</name>
<Object>p_ZZ11network_topP13params_structP8ap_fixedILi22ELi17EL9ap_q_mode0EL9ap_o_mode0EL_11867</Object>
<Type>pointer</Type>
<Scope>global</Scope>
<IOProtocol>ap_vld</IOProtocol>
<IOConfig></IOConfig>
<Dir>out</Dir>
<Bits>22</Bits>
<Attribute>data</Attribute>
</RtlPorts>
<RtlPorts>
<name>p_ZZ11network_topP13params_structP8ap_fixedILi22ELi17EL9ap_q_mode0EL9ap_o_mode0EL_11867_ap_vld</name>
<Object>p_ZZ11network_topP13params_structP8ap_fixedILi22ELi17EL9ap_q_mode0EL9ap_o_mode0EL_11867</Object>
<Type>pointer</Type>
<Scope>global</Scope>
<IOProtocol>ap_vld</IOProtocol>
<IOConfig></IOConfig>
<Dir>out</Dir>
<Bits>1</Bits>
<Attribute>control</Attribute>
</RtlPorts>
<RtlPorts>
<name>p_ZZ11network_topP13params_structP8ap_fixedILi22ELi17EL9ap_q_mode0EL9ap_o_mode0EL_11869</name>
<Object>p_ZZ11network_topP13params_structP8ap_fixedILi22ELi17EL9ap_q_mode0EL9ap_o_mode0EL_11869</Object>
<Type>pointer</Type>
<Scope>global</Scope>
<IOProtocol>ap_vld</IOProtocol>
<IOConfig></IOConfig>
<Dir>out</Dir>
<Bits>22</Bits>
<Attribute>data</Attribute>
</RtlPorts>
<RtlPorts>
<name>p_ZZ11network_topP13params_structP8ap_fixedILi22ELi17EL9ap_q_mode0EL9ap_o_mode0EL_11869_ap_vld</name>
<Object>p_ZZ11network_topP13params_structP8ap_fixedILi22ELi17EL9ap_q_mode0EL9ap_o_mode0EL_11869</Object>
<Type>pointer</Type>
<Scope>global</Scope>
<IOProtocol>ap_vld</IOProtocol>
<IOConfig></IOConfig>
<Dir>out</Dir>
<Bits>1</Bits>
<Attribute>control</Attribute>
</RtlPorts>
<RtlPorts>
<name>p_ZZ11network_topP13params_structP8ap_fixedILi22ELi17EL9ap_q_mode0EL9ap_o_mode0EL_11870</name>
<Object>p_ZZ11network_topP13params_structP8ap_fixedILi22ELi17EL9ap_q_mode0EL9ap_o_mode0EL_11870</Object>
<Type>pointer</Type>
<Scope>global</Scope>
<IOProtocol>ap_vld</IOProtocol>
<IOConfig></IOConfig>
<Dir>out</Dir>
<Bits>22</Bits>
<Attribute>data</Attribute>
</RtlPorts>
<RtlPorts>
<name>p_ZZ11network_topP13params_structP8ap_fixedILi22ELi17EL9ap_q_mode0EL9ap_o_mode0EL_11870_ap_vld</name>
<Object>p_ZZ11network_topP13params_structP8ap_fixedILi22ELi17EL9ap_q_mode0EL9ap_o_mode0EL_11870</Object>
<Type>pointer</Type>
<Scope>global</Scope>
<IOProtocol>ap_vld</IOProtocol>
<IOConfig></IOConfig>
<Dir>out</Dir>
<Bits>1</Bits>
<Attribute>control</Attribute>
</RtlPorts>
<RtlPorts>
<name>p_ZZ11network_topP13params_structP8ap_fixedILi22ELi17EL9ap_q_mode0EL9ap_o_mode0EL_11871</name>
<Object>p_ZZ11network_topP13params_structP8ap_fixedILi22ELi17EL9ap_q_mode0EL9ap_o_mode0EL_11871</Object>
<Type>pointer</Type>
<Scope>global</Scope>
<IOProtocol>ap_vld</IOProtocol>
<IOConfig></IOConfig>
<Dir>out</Dir>
<Bits>22</Bits>
<Attribute>data</Attribute>
</RtlPorts>
<RtlPorts>
<name>p_ZZ11network_topP13params_structP8ap_fixedILi22ELi17EL9ap_q_mode0EL9ap_o_mode0EL_11871_ap_vld</name>
<Object>p_ZZ11network_topP13params_structP8ap_fixedILi22ELi17EL9ap_q_mode0EL9ap_o_mode0EL_11871</Object>
<Type>pointer</Type>
<Scope>global</Scope>
<IOProtocol>ap_vld</IOProtocol>
<IOConfig></IOConfig>
<Dir>out</Dir>
<Bits>1</Bits>
<Attribute>control</Attribute>
</RtlPorts>
<RtlPorts>
<name>p_ZZ11network_topP13params_structP8ap_fixedILi22ELi17EL9ap_q_mode0EL9ap_o_mode0EL_11872</name>
<Object>p_ZZ11network_topP13params_structP8ap_fixedILi22ELi17EL9ap_q_mode0EL9ap_o_mode0EL_11872</Object>
<Type>pointer</Type>
<Scope>global</Scope>
<IOProtocol>ap_vld</IOProtocol>
<IOConfig></IOConfig>
<Dir>out</Dir>
<Bits>22</Bits>
<Attribute>data</Attribute>
</RtlPorts>
<RtlPorts>
<name>p_ZZ11network_topP13params_structP8ap_fixedILi22ELi17EL9ap_q_mode0EL9ap_o_mode0EL_11872_ap_vld</name>
<Object>p_ZZ11network_topP13params_structP8ap_fixedILi22ELi17EL9ap_q_mode0EL9ap_o_mode0EL_11872</Object>
<Type>pointer</Type>
<Scope>global</Scope>
<IOProtocol>ap_vld</IOProtocol>
<IOConfig></IOConfig>
<Dir>out</Dir>
<Bits>1</Bits>
<Attribute>control</Attribute>
</RtlPorts>
<RtlPorts>
<name>p_ZZ11network_topP13params_structP8ap_fixedILi22ELi17EL9ap_q_mode0EL9ap_o_mode0EL_11873</name>
<Object>p_ZZ11network_topP13params_structP8ap_fixedILi22ELi17EL9ap_q_mode0EL9ap_o_mode0EL_11873</Object>
<Type>pointer</Type>
<Scope>global</Scope>
<IOProtocol>ap_vld</IOProtocol>
<IOConfig></IOConfig>
<Dir>out</Dir>
<Bits>22</Bits>
<Attribute>data</Attribute>
</RtlPorts>
<RtlPorts>
<name>p_ZZ11network_topP13params_structP8ap_fixedILi22ELi17EL9ap_q_mode0EL9ap_o_mode0EL_11873_ap_vld</name>
<Object>p_ZZ11network_topP13params_structP8ap_fixedILi22ELi17EL9ap_q_mode0EL9ap_o_mode0EL_11873</Object>
<Type>pointer</Type>
<Scope>global</Scope>
<IOProtocol>ap_vld</IOProtocol>
<IOConfig></IOConfig>
<Dir>out</Dir>
<Bits>1</Bits>
<Attribute>control</Attribute>
</RtlPorts>
<RtlPorts>
<name>p_ZZ11network_topP13params_structP8ap_fixedILi22ELi17EL9ap_q_mode0EL9ap_o_mode0EL_11874</name>
<Object>p_ZZ11network_topP13params_structP8ap_fixedILi22ELi17EL9ap_q_mode0EL9ap_o_mode0EL_11874</Object>
<Type>pointer</Type>
<Scope>global</Scope>
<IOProtocol>ap_vld</IOProtocol>
<IOConfig></IOConfig>
<Dir>out</Dir>
<Bits>22</Bits>
<Attribute>data</Attribute>
</RtlPorts>
<RtlPorts>
<name>p_ZZ11network_topP13params_structP8ap_fixedILi22ELi17EL9ap_q_mode0EL9ap_o_mode0EL_11874_ap_vld</name>
<Object>p_ZZ11network_topP13params_structP8ap_fixedILi22ELi17EL9ap_q_mode0EL9ap_o_mode0EL_11874</Object>
<Type>pointer</Type>
<Scope>global</Scope>
<IOProtocol>ap_vld</IOProtocol>
<IOConfig></IOConfig>
<Dir>out</Dir>
<Bits>1</Bits>
<Attribute>control</Attribute>
</RtlPorts>
<RtlPorts>
<name>p_ZZ11network_topP13params_structP8ap_fixedILi22ELi17EL9ap_q_mode0EL9ap_o_mode0EL_11875</name>
<Object>p_ZZ11network_topP13params_structP8ap_fixedILi22ELi17EL9ap_q_mode0EL9ap_o_mode0EL_11875</Object>
<Type>pointer</Type>
<Scope>global</Scope>
<IOProtocol>ap_vld</IOProtocol>
<IOConfig></IOConfig>
<Dir>out</Dir>
<Bits>22</Bits>
<Attribute>data</Attribute>
</RtlPorts>
<RtlPorts>
<name>p_ZZ11network_topP13params_structP8ap_fixedILi22ELi17EL9ap_q_mode0EL9ap_o_mode0EL_11875_ap_vld</name>
<Object>p_ZZ11network_topP13params_structP8ap_fixedILi22ELi17EL9ap_q_mode0EL9ap_o_mode0EL_11875</Object>
<Type>pointer</Type>
<Scope>global</Scope>
<IOProtocol>ap_vld</IOProtocol>
<IOConfig></IOConfig>
<Dir>out</Dir>
<Bits>1</Bits>
<Attribute>control</Attribute>
</RtlPorts>
<RtlPorts>
<name>p_ZZ11network_topP13params_structP8ap_fixedILi22ELi17EL9ap_q_mode0EL9ap_o_mode0EL_11877</name>
<Object>p_ZZ11network_topP13params_structP8ap_fixedILi22ELi17EL9ap_q_mode0EL9ap_o_mode0EL_11877</Object>
<Type>pointer</Type>
<Scope>global</Scope>
<IOProtocol>ap_vld</IOProtocol>
<IOConfig></IOConfig>
<Dir>out</Dir>
<Bits>22</Bits>
<Attribute>data</Attribute>
</RtlPorts>
<RtlPorts>
<name>p_ZZ11network_topP13params_structP8ap_fixedILi22ELi17EL9ap_q_mode0EL9ap_o_mode0EL_11877_ap_vld</name>
<Object>p_ZZ11network_topP13params_structP8ap_fixedILi22ELi17EL9ap_q_mode0EL9ap_o_mode0EL_11877</Object>
<Type>pointer</Type>
<Scope>global</Scope>
<IOProtocol>ap_vld</IOProtocol>
<IOConfig></IOConfig>
<Dir>out</Dir>
<Bits>1</Bits>
<Attribute>control</Attribute>
</RtlPorts>
<RtlPorts>
<name>p_ZZ11network_topP13params_structP8ap_fixedILi22ELi17EL9ap_q_mode0EL9ap_o_mode0EL_11878</name>
<Object>p_ZZ11network_topP13params_structP8ap_fixedILi22ELi17EL9ap_q_mode0EL9ap_o_mode0EL_11878</Object>
<Type>pointer</Type>
<Scope>global</Scope>
<IOProtocol>ap_vld</IOProtocol>
<IOConfig></IOConfig>
<Dir>out</Dir>
<Bits>22</Bits>
<Attribute>data</Attribute>
</RtlPorts>
<RtlPorts>
<name>p_ZZ11network_topP13params_structP8ap_fixedILi22ELi17EL9ap_q_mode0EL9ap_o_mode0EL_11878_ap_vld</name>
<Object>p_ZZ11network_topP13params_structP8ap_fixedILi22ELi17EL9ap_q_mode0EL9ap_o_mode0EL_11878</Object>
<Type>pointer</Type>
<Scope>global</Scope>
<IOProtocol>ap_vld</IOProtocol>
<IOConfig></IOConfig>
<Dir>out</Dir>
<Bits>1</Bits>
<Attribute>control</Attribute>
</RtlPorts>
<RtlPorts>
<name>p_ZZ11network_topP13params_structP8ap_fixedILi22ELi17EL9ap_q_mode0EL9ap_o_mode0EL_11879</name>
<Object>p_ZZ11network_topP13params_structP8ap_fixedILi22ELi17EL9ap_q_mode0EL9ap_o_mode0EL_11879</Object>
<Type>pointer</Type>
<Scope>global</Scope>
<IOProtocol>ap_vld</IOProtocol>
<IOConfig></IOConfig>
<Dir>out</Dir>
<Bits>22</Bits>
<Attribute>data</Attribute>
</RtlPorts>
<RtlPorts>
<name>p_ZZ11network_topP13params_structP8ap_fixedILi22ELi17EL9ap_q_mode0EL9ap_o_mode0EL_11879_ap_vld</name>
<Object>p_ZZ11network_topP13params_structP8ap_fixedILi22ELi17EL9ap_q_mode0EL9ap_o_mode0EL_11879</Object>
<Type>pointer</Type>
<Scope>global</Scope>
<IOProtocol>ap_vld</IOProtocol>
<IOConfig></IOConfig>
<Dir>out</Dir>
<Bits>1</Bits>
<Attribute>control</Attribute>
</RtlPorts>
<RtlPorts>
<name>p_ZZ11network_topP13params_structP8ap_fixedILi22ELi17EL9ap_q_mode0EL9ap_o_mode0EL_11881</name>
<Object>p_ZZ11network_topP13params_structP8ap_fixedILi22ELi17EL9ap_q_mode0EL9ap_o_mode0EL_11881</Object>
<Type>pointer</Type>
<Scope>global</Scope>
<IOProtocol>ap_vld</IOProtocol>
<IOConfig></IOConfig>
<Dir>out</Dir>
<Bits>22</Bits>
<Attribute>data</Attribute>
</RtlPorts>
<RtlPorts>
<name>p_ZZ11network_topP13params_structP8ap_fixedILi22ELi17EL9ap_q_mode0EL9ap_o_mode0EL_11881_ap_vld</name>
<Object>p_ZZ11network_topP13params_structP8ap_fixedILi22ELi17EL9ap_q_mode0EL9ap_o_mode0EL_11881</Object>
<Type>pointer</Type>
<Scope>global</Scope>
<IOProtocol>ap_vld</IOProtocol>
<IOConfig></IOConfig>
<Dir>out</Dir>
<Bits>1</Bits>
<Attribute>control</Attribute>
</RtlPorts>
<RtlPorts>
<name>p_ZZ11network_topP13params_structP8ap_fixedILi22ELi17EL9ap_q_mode0EL9ap_o_mode0EL_11882</name>
<Object>p_ZZ11network_topP13params_structP8ap_fixedILi22ELi17EL9ap_q_mode0EL9ap_o_mode0EL_11882</Object>
<Type>pointer</Type>
<Scope>global</Scope>
<IOProtocol>ap_vld</IOProtocol>
<IOConfig></IOConfig>
<Dir>out</Dir>
<Bits>22</Bits>
<Attribute>data</Attribute>
</RtlPorts>
<RtlPorts>
<name>p_ZZ11network_topP13params_structP8ap_fixedILi22ELi17EL9ap_q_mode0EL9ap_o_mode0EL_11882_ap_vld</name>
<Object>p_ZZ11network_topP13params_structP8ap_fixedILi22ELi17EL9ap_q_mode0EL9ap_o_mode0EL_11882</Object>
<Type>pointer</Type>
<Scope>global</Scope>
<IOProtocol>ap_vld</IOProtocol>
<IOConfig></IOConfig>
<Dir>out</Dir>
<Bits>1</Bits>
<Attribute>control</Attribute>
</RtlPorts>
<RtlPorts>
<name>p_ZZ11network_topP13params_structP8ap_fixedILi22ELi17EL9ap_q_mode0EL9ap_o_mode0EL_11883</name>
<Object>p_ZZ11network_topP13params_structP8ap_fixedILi22ELi17EL9ap_q_mode0EL9ap_o_mode0EL_11883</Object>
<Type>pointer</Type>
<Scope>global</Scope>
<IOProtocol>ap_vld</IOProtocol>
<IOConfig></IOConfig>
<Dir>out</Dir>
<Bits>22</Bits>
<Attribute>data</Attribute>
</RtlPorts>
<RtlPorts>
<name>p_ZZ11network_topP13params_structP8ap_fixedILi22ELi17EL9ap_q_mode0EL9ap_o_mode0EL_11883_ap_vld</name>
<Object>p_ZZ11network_topP13params_structP8ap_fixedILi22ELi17EL9ap_q_mode0EL9ap_o_mode0EL_11883</Object>
<Type>pointer</Type>
<Scope>global</Scope>
<IOProtocol>ap_vld</IOProtocol>
<IOConfig></IOConfig>
<Dir>out</Dir>
<Bits>1</Bits>
<Attribute>control</Attribute>
</RtlPorts>
<RtlPorts>
<name>p_ZZ11network_topP13params_structP8ap_fixedILi22ELi17EL9ap_q_mode0EL9ap_o_mode0EL_11884</name>
<Object>p_ZZ11network_topP13params_structP8ap_fixedILi22ELi17EL9ap_q_mode0EL9ap_o_mode0EL_11884</Object>
<Type>pointer</Type>
<Scope>global</Scope>
<IOProtocol>ap_vld</IOProtocol>
<IOConfig></IOConfig>
<Dir>out</Dir>
<Bits>22</Bits>
<Attribute>data</Attribute>
</RtlPorts>
<RtlPorts>
<name>p_ZZ11network_topP13params_structP8ap_fixedILi22ELi17EL9ap_q_mode0EL9ap_o_mode0EL_11884_ap_vld</name>
<Object>p_ZZ11network_topP13params_structP8ap_fixedILi22ELi17EL9ap_q_mode0EL9ap_o_mode0EL_11884</Object>
<Type>pointer</Type>
<Scope>global</Scope>
<IOProtocol>ap_vld</IOProtocol>
<IOConfig></IOConfig>
<Dir>out</Dir>
<Bits>1</Bits>
<Attribute>control</Attribute>
</RtlPorts>
<RtlPorts>
<name>p_ZZ11network_topP13params_structP8ap_fixedILi22ELi17EL9ap_q_mode0EL9ap_o_mode0EL_11885</name>
<Object>p_ZZ11network_topP13params_structP8ap_fixedILi22ELi17EL9ap_q_mode0EL9ap_o_mode0EL_11885</Object>
<Type>pointer</Type>
<Scope>global</Scope>
<IOProtocol>ap_vld</IOProtocol>
<IOConfig></IOConfig>
<Dir>out</Dir>
<Bits>22</Bits>
<Attribute>data</Attribute>
</RtlPorts>
<RtlPorts>
<name>p_ZZ11network_topP13params_structP8ap_fixedILi22ELi17EL9ap_q_mode0EL9ap_o_mode0EL_11885_ap_vld</name>
<Object>p_ZZ11network_topP13params_structP8ap_fixedILi22ELi17EL9ap_q_mode0EL9ap_o_mode0EL_11885</Object>
<Type>pointer</Type>
<Scope>global</Scope>
<IOProtocol>ap_vld</IOProtocol>
<IOConfig></IOConfig>
<Dir>out</Dir>
<Bits>1</Bits>
<Attribute>control</Attribute>
</RtlPorts>
<RtlPorts>
<name>p_ZZ11network_topP13params_structP8ap_fixedILi22ELi17EL9ap_q_mode0EL9ap_o_mode0EL_11886</name>
<Object>p_ZZ11network_topP13params_structP8ap_fixedILi22ELi17EL9ap_q_mode0EL9ap_o_mode0EL_11886</Object>
<Type>pointer</Type>
<Scope>global</Scope>
<IOProtocol>ap_vld</IOProtocol>
<IOConfig></IOConfig>
<Dir>out</Dir>
<Bits>22</Bits>
<Attribute>data</Attribute>
</RtlPorts>
<RtlPorts>
<name>p_ZZ11network_topP13params_structP8ap_fixedILi22ELi17EL9ap_q_mode0EL9ap_o_mode0EL_11886_ap_vld</name>
<Object>p_ZZ11network_topP13params_structP8ap_fixedILi22ELi17EL9ap_q_mode0EL9ap_o_mode0EL_11886</Object>
<Type>pointer</Type>
<Scope>global</Scope>
<IOProtocol>ap_vld</IOProtocol>
<IOConfig></IOConfig>
<Dir>out</Dir>
<Bits>1</Bits>
<Attribute>control</Attribute>
</RtlPorts>
<RtlPorts>
<name>p_ZZ11network_topP13params_structP8ap_fixedILi22ELi17EL9ap_q_mode0EL9ap_o_mode0EL_11888</name>
<Object>p_ZZ11network_topP13params_structP8ap_fixedILi22ELi17EL9ap_q_mode0EL9ap_o_mode0EL_11888</Object>
<Type>pointer</Type>
<Scope>global</Scope>
<IOProtocol>ap_vld</IOProtocol>
<IOConfig></IOConfig>
<Dir>out</Dir>
<Bits>22</Bits>
<Attribute>data</Attribute>
</RtlPorts>
<RtlPorts>
<name>p_ZZ11network_topP13params_structP8ap_fixedILi22ELi17EL9ap_q_mode0EL9ap_o_mode0EL_11888_ap_vld</name>
<Object>p_ZZ11network_topP13params_structP8ap_fixedILi22ELi17EL9ap_q_mode0EL9ap_o_mode0EL_11888</Object>
<Type>pointer</Type>
<Scope>global</Scope>
<IOProtocol>ap_vld</IOProtocol>
<IOConfig></IOConfig>
<Dir>out</Dir>
<Bits>1</Bits>
<Attribute>control</Attribute>
</RtlPorts>
<RtlPorts>
<name>p_ZZ11network_topP13params_structP8ap_fixedILi22ELi17EL9ap_q_mode0EL9ap_o_mode0EL_11889</name>
<Object>p_ZZ11network_topP13params_structP8ap_fixedILi22ELi17EL9ap_q_mode0EL9ap_o_mode0EL_11889</Object>
<Type>pointer</Type>
<Scope>global</Scope>
<IOProtocol>ap_vld</IOProtocol>
<IOConfig></IOConfig>
<Dir>out</Dir>
<Bits>22</Bits>
<Attribute>data</Attribute>
</RtlPorts>
<RtlPorts>
<name>p_ZZ11network_topP13params_structP8ap_fixedILi22ELi17EL9ap_q_mode0EL9ap_o_mode0EL_11889_ap_vld</name>
<Object>p_ZZ11network_topP13params_structP8ap_fixedILi22ELi17EL9ap_q_mode0EL9ap_o_mode0EL_11889</Object>
<Type>pointer</Type>
<Scope>global</Scope>
<IOProtocol>ap_vld</IOProtocol>
<IOConfig></IOConfig>
<Dir>out</Dir>
<Bits>1</Bits>
<Attribute>control</Attribute>
</RtlPorts>
<RtlPorts>
<name>p_ZZ11network_topP13params_structP8ap_fixedILi22ELi17EL9ap_q_mode0EL9ap_o_mode0EL_11890</name>
<Object>p_ZZ11network_topP13params_structP8ap_fixedILi22ELi17EL9ap_q_mode0EL9ap_o_mode0EL_11890</Object>
<Type>pointer</Type>
<Scope>global</Scope>
<IOProtocol>ap_vld</IOProtocol>
<IOConfig></IOConfig>
<Dir>out</Dir>
<Bits>22</Bits>
<Attribute>data</Attribute>
</RtlPorts>
<RtlPorts>
<name>p_ZZ11network_topP13params_structP8ap_fixedILi22ELi17EL9ap_q_mode0EL9ap_o_mode0EL_11890_ap_vld</name>
<Object>p_ZZ11network_topP13params_structP8ap_fixedILi22ELi17EL9ap_q_mode0EL9ap_o_mode0EL_11890</Object>
<Type>pointer</Type>
<Scope>global</Scope>
<IOProtocol>ap_vld</IOProtocol>
<IOConfig></IOConfig>
<Dir>out</Dir>
<Bits>1</Bits>
<Attribute>control</Attribute>
</RtlPorts>
<RtlPorts>
<name>p_ZZ11network_topP13params_structP8ap_fixedILi22ELi17EL9ap_q_mode0EL9ap_o_mode0EL_11891</name>
<Object>p_ZZ11network_topP13params_structP8ap_fixedILi22ELi17EL9ap_q_mode0EL9ap_o_mode0EL_11891</Object>
<Type>pointer</Type>
<Scope>global</Scope>
<IOProtocol>ap_vld</IOProtocol>
<IOConfig></IOConfig>
<Dir>out</Dir>
<Bits>22</Bits>
<Attribute>data</Attribute>
</RtlPorts>
<RtlPorts>
<name>p_ZZ11network_topP13params_structP8ap_fixedILi22ELi17EL9ap_q_mode0EL9ap_o_mode0EL_11891_ap_vld</name>
<Object>p_ZZ11network_topP13params_structP8ap_fixedILi22ELi17EL9ap_q_mode0EL9ap_o_mode0EL_11891</Object>
<Type>pointer</Type>
<Scope>global</Scope>
<IOProtocol>ap_vld</IOProtocol>
<IOConfig></IOConfig>
<Dir>out</Dir>
<Bits>1</Bits>
<Attribute>control</Attribute>
</RtlPorts>
<RtlPorts>
<name>p_ZZ11network_topP13params_structP8ap_fixedILi22ELi17EL9ap_q_mode0EL9ap_o_mode0EL_11893</name>
<Object>p_ZZ11network_topP13params_structP8ap_fixedILi22ELi17EL9ap_q_mode0EL9ap_o_mode0EL_11893</Object>
<Type>pointer</Type>
<Scope>global</Scope>
<IOProtocol>ap_vld</IOProtocol>
<IOConfig></IOConfig>
<Dir>out</Dir>
<Bits>22</Bits>
<Attribute>data</Attribute>
</RtlPorts>
<RtlPorts>
<name>p_ZZ11network_topP13params_structP8ap_fixedILi22ELi17EL9ap_q_mode0EL9ap_o_mode0EL_11893_ap_vld</name>
<Object>p_ZZ11network_topP13params_structP8ap_fixedILi22ELi17EL9ap_q_mode0EL9ap_o_mode0EL_11893</Object>
<Type>pointer</Type>
<Scope>global</Scope>
<IOProtocol>ap_vld</IOProtocol>
<IOConfig></IOConfig>
<Dir>out</Dir>
<Bits>1</Bits>
<Attribute>control</Attribute>
</RtlPorts>
<RtlPorts>
<name>p_ZZ11network_topP13params_structP8ap_fixedILi22ELi17EL9ap_q_mode0EL9ap_o_mode0EL_11894</name>
<Object>p_ZZ11network_topP13params_structP8ap_fixedILi22ELi17EL9ap_q_mode0EL9ap_o_mode0EL_11894</Object>
<Type>pointer</Type>
<Scope>global</Scope>
<IOProtocol>ap_vld</IOProtocol>
<IOConfig></IOConfig>
<Dir>out</Dir>
<Bits>22</Bits>
<Attribute>data</Attribute>
</RtlPorts>
<RtlPorts>
<name>p_ZZ11network_topP13params_structP8ap_fixedILi22ELi17EL9ap_q_mode0EL9ap_o_mode0EL_11894_ap_vld</name>
<Object>p_ZZ11network_topP13params_structP8ap_fixedILi22ELi17EL9ap_q_mode0EL9ap_o_mode0EL_11894</Object>
<Type>pointer</Type>
<Scope>global</Scope>
<IOProtocol>ap_vld</IOProtocol>
<IOConfig></IOConfig>
<Dir>out</Dir>
<Bits>1</Bits>
<Attribute>control</Attribute>
</RtlPorts>
<RtlPorts>
<name>p_ZZ11network_topP13params_structP8ap_fixedILi22ELi17EL9ap_q_mode0EL9ap_o_mode0EL_11895</name>
<Object>p_ZZ11network_topP13params_structP8ap_fixedILi22ELi17EL9ap_q_mode0EL9ap_o_mode0EL_11895</Object>
<Type>pointer</Type>
<Scope>global</Scope>
<IOProtocol>ap_vld</IOProtocol>
<IOConfig></IOConfig>
<Dir>out</Dir>
<Bits>22</Bits>
<Attribute>data</Attribute>
</RtlPorts>
<RtlPorts>
<name>p_ZZ11network_topP13params_structP8ap_fixedILi22ELi17EL9ap_q_mode0EL9ap_o_mode0EL_11895_ap_vld</name>
<Object>p_ZZ11network_topP13params_structP8ap_fixedILi22ELi17EL9ap_q_mode0EL9ap_o_mode0EL_11895</Object>
<Type>pointer</Type>
<Scope>global</Scope>
<IOProtocol>ap_vld</IOProtocol>
<IOConfig></IOConfig>
<Dir>out</Dir>
<Bits>1</Bits>
<Attribute>control</Attribute>
</RtlPorts>
<RtlPorts>
<name>p_ZZ11network_topP13params_structP8ap_fixedILi22ELi17EL9ap_q_mode0EL9ap_o_mode0EL_11896</name>
<Object>p_ZZ11network_topP13params_structP8ap_fixedILi22ELi17EL9ap_q_mode0EL9ap_o_mode0EL_11896</Object>
<Type>pointer</Type>
<Scope>global</Scope>
<IOProtocol>ap_vld</IOProtocol>
<IOConfig></IOConfig>
<Dir>out</Dir>
<Bits>22</Bits>
<Attribute>data</Attribute>
</RtlPorts>
<RtlPorts>
<name>p_ZZ11network_topP13params_structP8ap_fixedILi22ELi17EL9ap_q_mode0EL9ap_o_mode0EL_11896_ap_vld</name>
<Object>p_ZZ11network_topP13params_structP8ap_fixedILi22ELi17EL9ap_q_mode0EL9ap_o_mode0EL_11896</Object>
<Type>pointer</Type>
<Scope>global</Scope>
<IOProtocol>ap_vld</IOProtocol>
<IOConfig></IOConfig>
<Dir>out</Dir>
<Bits>1</Bits>
<Attribute>control</Attribute>
</RtlPorts>
<RtlPorts>
<name>p_ZZ11network_topP13params_structP8ap_fixedILi22ELi17EL9ap_q_mode0EL9ap_o_mode0EL_11897</name>
<Object>p_ZZ11network_topP13params_structP8ap_fixedILi22ELi17EL9ap_q_mode0EL9ap_o_mode0EL_11897</Object>
<Type>pointer</Type>
<Scope>global</Scope>
<IOProtocol>ap_vld</IOProtocol>
<IOConfig></IOConfig>
<Dir>out</Dir>
<Bits>22</Bits>
<Attribute>data</Attribute>
</RtlPorts>
<RtlPorts>
<name>p_ZZ11network_topP13params_structP8ap_fixedILi22ELi17EL9ap_q_mode0EL9ap_o_mode0EL_11897_ap_vld</name>
<Object>p_ZZ11network_topP13params_structP8ap_fixedILi22ELi17EL9ap_q_mode0EL9ap_o_mode0EL_11897</Object>
<Type>pointer</Type>
<Scope>global</Scope>
<IOProtocol>ap_vld</IOProtocol>
<IOConfig></IOConfig>
<Dir>out</Dir>
<Bits>1</Bits>
<Attribute>control</Attribute>
</RtlPorts>
<RtlPorts>
<name>p_ZZ11network_topP13params_structP8ap_fixedILi22ELi17EL9ap_q_mode0EL9ap_o_mode0EL_11899</name>
<Object>p_ZZ11network_topP13params_structP8ap_fixedILi22ELi17EL9ap_q_mode0EL9ap_o_mode0EL_11899</Object>
<Type>pointer</Type>
<Scope>global</Scope>
<IOProtocol>ap_vld</IOProtocol>
<IOConfig></IOConfig>
<Dir>out</Dir>
<Bits>22</Bits>
<Attribute>data</Attribute>
</RtlPorts>
<RtlPorts>
<name>p_ZZ11network_topP13params_structP8ap_fixedILi22ELi17EL9ap_q_mode0EL9ap_o_mode0EL_11899_ap_vld</name>
<Object>p_ZZ11network_topP13params_structP8ap_fixedILi22ELi17EL9ap_q_mode0EL9ap_o_mode0EL_11899</Object>
<Type>pointer</Type>
<Scope>global</Scope>
<IOProtocol>ap_vld</IOProtocol>
<IOConfig></IOConfig>
<Dir>out</Dir>
<Bits>1</Bits>
<Attribute>control</Attribute>
</RtlPorts>
<RtlPorts>
<name>p_ZZ11network_topP13params_structP8ap_fixedILi22ELi17EL9ap_q_mode0EL9ap_o_mode0EL_11900</name>
<Object>p_ZZ11network_topP13params_structP8ap_fixedILi22ELi17EL9ap_q_mode0EL9ap_o_mode0EL_11900</Object>
<Type>pointer</Type>
<Scope>global</Scope>
<IOProtocol>ap_vld</IOProtocol>
<IOConfig></IOConfig>
<Dir>out</Dir>
<Bits>22</Bits>
<Attribute>data</Attribute>
</RtlPorts>
<RtlPorts>
<name>p_ZZ11network_topP13params_structP8ap_fixedILi22ELi17EL9ap_q_mode0EL9ap_o_mode0EL_11900_ap_vld</name>
<Object>p_ZZ11network_topP13params_structP8ap_fixedILi22ELi17EL9ap_q_mode0EL9ap_o_mode0EL_11900</Object>
<Type>pointer</Type>
<Scope>global</Scope>
<IOProtocol>ap_vld</IOProtocol>
<IOConfig></IOConfig>
<Dir>out</Dir>
<Bits>1</Bits>
<Attribute>control</Attribute>
</RtlPorts>
<RtlPorts>
<name>p_ZZ11network_topP13params_structP8ap_fixedILi22ELi17EL9ap_q_mode0EL9ap_o_mode0EL_11901</name>
<Object>p_ZZ11network_topP13params_structP8ap_fixedILi22ELi17EL9ap_q_mode0EL9ap_o_mode0EL_11901</Object>
<Type>pointer</Type>
<Scope>global</Scope>
<IOProtocol>ap_vld</IOProtocol>
<IOConfig></IOConfig>
<Dir>out</Dir>
<Bits>22</Bits>
<Attribute>data</Attribute>
</RtlPorts>
<RtlPorts>
<name>p_ZZ11network_topP13params_structP8ap_fixedILi22ELi17EL9ap_q_mode0EL9ap_o_mode0EL_11901_ap_vld</name>
<Object>p_ZZ11network_topP13params_structP8ap_fixedILi22ELi17EL9ap_q_mode0EL9ap_o_mode0EL_11901</Object>
<Type>pointer</Type>
<Scope>global</Scope>
<IOProtocol>ap_vld</IOProtocol>
<IOConfig></IOConfig>
<Dir>out</Dir>
<Bits>1</Bits>
<Attribute>control</Attribute>
</RtlPorts>
<RtlPorts>
<name>p_ZZ11network_topP13params_structP8ap_fixedILi22ELi17EL9ap_q_mode0EL9ap_o_mode0EL_11902</name>
<Object>p_ZZ11network_topP13params_structP8ap_fixedILi22ELi17EL9ap_q_mode0EL9ap_o_mode0EL_11902</Object>
<Type>pointer</Type>
<Scope>global</Scope>
<IOProtocol>ap_vld</IOProtocol>
<IOConfig></IOConfig>
<Dir>out</Dir>
<Bits>22</Bits>
<Attribute>data</Attribute>
</RtlPorts>
<RtlPorts>
<name>p_ZZ11network_topP13params_structP8ap_fixedILi22ELi17EL9ap_q_mode0EL9ap_o_mode0EL_11902_ap_vld</name>
<Object>p_ZZ11network_topP13params_structP8ap_fixedILi22ELi17EL9ap_q_mode0EL9ap_o_mode0EL_11902</Object>
<Type>pointer</Type>
<Scope>global</Scope>
<IOProtocol>ap_vld</IOProtocol>
<IOConfig></IOConfig>
<Dir>out</Dir>
<Bits>1</Bits>
<Attribute>control</Attribute>
</RtlPorts>
<RtlPorts>
<name>p_ZZ11network_topP13params_structP8ap_fixedILi22ELi17EL9ap_q_mode0EL9ap_o_mode0EL_11903</name>
<Object>p_ZZ11network_topP13params_structP8ap_fixedILi22ELi17EL9ap_q_mode0EL9ap_o_mode0EL_11903</Object>
<Type>pointer</Type>
<Scope>global</Scope>
<IOProtocol>ap_vld</IOProtocol>
<IOConfig></IOConfig>
<Dir>out</Dir>
<Bits>22</Bits>
<Attribute>data</Attribute>
</RtlPorts>
<RtlPorts>
<name>p_ZZ11network_topP13params_structP8ap_fixedILi22ELi17EL9ap_q_mode0EL9ap_o_mode0EL_11903_ap_vld</name>
<Object>p_ZZ11network_topP13params_structP8ap_fixedILi22ELi17EL9ap_q_mode0EL9ap_o_mode0EL_11903</Object>
<Type>pointer</Type>
<Scope>global</Scope>
<IOProtocol>ap_vld</IOProtocol>
<IOConfig></IOConfig>
<Dir>out</Dir>
<Bits>1</Bits>
<Attribute>control</Attribute>
</RtlPorts>
<RtlPorts>
<name>p_ZZ11network_topP13params_structP8ap_fixedILi22ELi17EL9ap_q_mode0EL9ap_o_mode0EL_11905</name>
<Object>p_ZZ11network_topP13params_structP8ap_fixedILi22ELi17EL9ap_q_mode0EL9ap_o_mode0EL_11905</Object>
<Type>pointer</Type>
<Scope>global</Scope>
<IOProtocol>ap_vld</IOProtocol>
<IOConfig></IOConfig>
<Dir>out</Dir>
<Bits>22</Bits>
<Attribute>data</Attribute>
</RtlPorts>
<RtlPorts>
<name>p_ZZ11network_topP13params_structP8ap_fixedILi22ELi17EL9ap_q_mode0EL9ap_o_mode0EL_11905_ap_vld</name>
<Object>p_ZZ11network_topP13params_structP8ap_fixedILi22ELi17EL9ap_q_mode0EL9ap_o_mode0EL_11905</Object>
<Type>pointer</Type>
<Scope>global</Scope>
<IOProtocol>ap_vld</IOProtocol>
<IOConfig></IOConfig>
<Dir>out</Dir>
<Bits>1</Bits>
<Attribute>control</Attribute>
</RtlPorts>
<RtlPorts>
<name>p_ZZ11network_topP13params_structP8ap_fixedILi22ELi17EL9ap_q_mode0EL9ap_o_mode0EL_11906</name>
<Object>p_ZZ11network_topP13params_structP8ap_fixedILi22ELi17EL9ap_q_mode0EL9ap_o_mode0EL_11906</Object>
<Type>pointer</Type>
<Scope>global</Scope>
<IOProtocol>ap_vld</IOProtocol>
<IOConfig></IOConfig>
<Dir>out</Dir>
<Bits>22</Bits>
<Attribute>data</Attribute>
</RtlPorts>
<RtlPorts>
<name>p_ZZ11network_topP13params_structP8ap_fixedILi22ELi17EL9ap_q_mode0EL9ap_o_mode0EL_11906_ap_vld</name>
<Object>p_ZZ11network_topP13params_structP8ap_fixedILi22ELi17EL9ap_q_mode0EL9ap_o_mode0EL_11906</Object>
<Type>pointer</Type>
<Scope>global</Scope>
<IOProtocol>ap_vld</IOProtocol>
<IOConfig></IOConfig>
<Dir>out</Dir>
<Bits>1</Bits>
<Attribute>control</Attribute>
</RtlPorts>
<RtlPorts>
<name>p_ZZ11network_topP13params_structP8ap_fixedILi22ELi17EL9ap_q_mode0EL9ap_o_mode0EL_11907</name>
<Object>p_ZZ11network_topP13params_structP8ap_fixedILi22ELi17EL9ap_q_mode0EL9ap_o_mode0EL_11907</Object>
<Type>pointer</Type>
<Scope>global</Scope>
<IOProtocol>ap_vld</IOProtocol>
<IOConfig></IOConfig>
<Dir>out</Dir>
<Bits>22</Bits>
<Attribute>data</Attribute>
</RtlPorts>
<RtlPorts>
<name>p_ZZ11network_topP13params_structP8ap_fixedILi22ELi17EL9ap_q_mode0EL9ap_o_mode0EL_11907_ap_vld</name>
<Object>p_ZZ11network_topP13params_structP8ap_fixedILi22ELi17EL9ap_q_mode0EL9ap_o_mode0EL_11907</Object>
<Type>pointer</Type>
<Scope>global</Scope>
<IOProtocol>ap_vld</IOProtocol>
<IOConfig></IOConfig>
<Dir>out</Dir>
<Bits>1</Bits>
<Attribute>control</Attribute>
</RtlPorts>
<RtlPorts>
<name>p_ZZ11network_topP13params_structP8ap_fixedILi22ELi17EL9ap_q_mode0EL9ap_o_mode0EL_11908</name>
<Object>p_ZZ11network_topP13params_structP8ap_fixedILi22ELi17EL9ap_q_mode0EL9ap_o_mode0EL_11908</Object>
<Type>pointer</Type>
<Scope>global</Scope>
<IOProtocol>ap_vld</IOProtocol>
<IOConfig></IOConfig>
<Dir>out</Dir>
<Bits>22</Bits>
<Attribute>data</Attribute>
</RtlPorts>
<RtlPorts>
<name>p_ZZ11network_topP13params_structP8ap_fixedILi22ELi17EL9ap_q_mode0EL9ap_o_mode0EL_11908_ap_vld</name>
<Object>p_ZZ11network_topP13params_structP8ap_fixedILi22ELi17EL9ap_q_mode0EL9ap_o_mode0EL_11908</Object>
<Type>pointer</Type>
<Scope>global</Scope>
<IOProtocol>ap_vld</IOProtocol>
<IOConfig></IOConfig>
<Dir>out</Dir>
<Bits>1</Bits>
<Attribute>control</Attribute>
</RtlPorts>
<RtlPorts>
<name>p_ZZ11network_topP13params_structP8ap_fixedILi22ELi17EL9ap_q_mode0EL9ap_o_mode0EL_11910</name>
<Object>p_ZZ11network_topP13params_structP8ap_fixedILi22ELi17EL9ap_q_mode0EL9ap_o_mode0EL_11910</Object>
<Type>pointer</Type>
<Scope>global</Scope>
<IOProtocol>ap_vld</IOProtocol>
<IOConfig></IOConfig>
<Dir>out</Dir>
<Bits>22</Bits>
<Attribute>data</Attribute>
</RtlPorts>
<RtlPorts>
<name>p_ZZ11network_topP13params_structP8ap_fixedILi22ELi17EL9ap_q_mode0EL9ap_o_mode0EL_11910_ap_vld</name>
<Object>p_ZZ11network_topP13params_structP8ap_fixedILi22ELi17EL9ap_q_mode0EL9ap_o_mode0EL_11910</Object>
<Type>pointer</Type>
<Scope>global</Scope>
<IOProtocol>ap_vld</IOProtocol>
<IOConfig></IOConfig>
<Dir>out</Dir>
<Bits>1</Bits>
<Attribute>control</Attribute>
</RtlPorts>
<RtlPorts>
<name>p_ZZ11network_topP13params_structP8ap_fixedILi22ELi17EL9ap_q_mode0EL9ap_o_mode0EL_11911</name>
<Object>p_ZZ11network_topP13params_structP8ap_fixedILi22ELi17EL9ap_q_mode0EL9ap_o_mode0EL_11911</Object>
<Type>pointer</Type>
<Scope>global</Scope>
<IOProtocol>ap_vld</IOProtocol>
<IOConfig></IOConfig>
<Dir>out</Dir>
<Bits>22</Bits>
<Attribute>data</Attribute>
</RtlPorts>
<RtlPorts>
<name>p_ZZ11network_topP13params_structP8ap_fixedILi22ELi17EL9ap_q_mode0EL9ap_o_mode0EL_11911_ap_vld</name>
<Object>p_ZZ11network_topP13params_structP8ap_fixedILi22ELi17EL9ap_q_mode0EL9ap_o_mode0EL_11911</Object>
<Type>pointer</Type>
<Scope>global</Scope>
<IOProtocol>ap_vld</IOProtocol>
<IOConfig></IOConfig>
<Dir>out</Dir>
<Bits>1</Bits>
<Attribute>control</Attribute>
</RtlPorts>
<RtlPorts>
<name>p_ZZ11network_topP13params_structP8ap_fixedILi22ELi17EL9ap_q_mode0EL9ap_o_mode0EL_11912</name>
<Object>p_ZZ11network_topP13params_structP8ap_fixedILi22ELi17EL9ap_q_mode0EL9ap_o_mode0EL_11912</Object>
<Type>pointer</Type>
<Scope>global</Scope>
<IOProtocol>ap_vld</IOProtocol>
<IOConfig></IOConfig>
<Dir>out</Dir>
<Bits>22</Bits>
<Attribute>data</Attribute>
</RtlPorts>
<RtlPorts>
<name>p_ZZ11network_topP13params_structP8ap_fixedILi22ELi17EL9ap_q_mode0EL9ap_o_mode0EL_11912_ap_vld</name>
<Object>p_ZZ11network_topP13params_structP8ap_fixedILi22ELi17EL9ap_q_mode0EL9ap_o_mode0EL_11912</Object>
<Type>pointer</Type>
<Scope>global</Scope>
<IOProtocol>ap_vld</IOProtocol>
<IOConfig></IOConfig>
<Dir>out</Dir>
<Bits>1</Bits>
<Attribute>control</Attribute>
</RtlPorts>
<RtlPorts>
<name>p_ZZ11network_topP13params_structP8ap_fixedILi22ELi17EL9ap_q_mode0EL9ap_o_mode0EL_11913</name>
<Object>p_ZZ11network_topP13params_structP8ap_fixedILi22ELi17EL9ap_q_mode0EL9ap_o_mode0EL_11913</Object>
<Type>pointer</Type>
<Scope>global</Scope>
<IOProtocol>ap_vld</IOProtocol>
<IOConfig></IOConfig>
<Dir>out</Dir>
<Bits>22</Bits>
<Attribute>data</Attribute>
</RtlPorts>
<RtlPorts>
<name>p_ZZ11network_topP13params_structP8ap_fixedILi22ELi17EL9ap_q_mode0EL9ap_o_mode0EL_11913_ap_vld</name>
<Object>p_ZZ11network_topP13params_structP8ap_fixedILi22ELi17EL9ap_q_mode0EL9ap_o_mode0EL_11913</Object>
<Type>pointer</Type>
<Scope>global</Scope>
<IOProtocol>ap_vld</IOProtocol>
<IOConfig></IOConfig>
<Dir>out</Dir>
<Bits>1</Bits>
<Attribute>control</Attribute>
</RtlPorts>
<RtlPorts>
<name>p_ZZ11network_topP13params_structP8ap_fixedILi22ELi17EL9ap_q_mode0EL9ap_o_mode0EL_11914</name>
<Object>p_ZZ11network_topP13params_structP8ap_fixedILi22ELi17EL9ap_q_mode0EL9ap_o_mode0EL_11914</Object>
<Type>pointer</Type>
<Scope>global</Scope>
<IOProtocol>ap_vld</IOProtocol>
<IOConfig></IOConfig>
<Dir>out</Dir>
<Bits>22</Bits>
<Attribute>data</Attribute>
</RtlPorts>
<RtlPorts>
<name>p_ZZ11network_topP13params_structP8ap_fixedILi22ELi17EL9ap_q_mode0EL9ap_o_mode0EL_11914_ap_vld</name>
<Object>p_ZZ11network_topP13params_structP8ap_fixedILi22ELi17EL9ap_q_mode0EL9ap_o_mode0EL_11914</Object>
<Type>pointer</Type>
<Scope>global</Scope>
<IOProtocol>ap_vld</IOProtocol>
<IOConfig></IOConfig>
<Dir>out</Dir>
<Bits>1</Bits>
<Attribute>control</Attribute>
</RtlPorts>
<RtlPorts>
<name>p_ZZ11network_topP13params_structP8ap_fixedILi22ELi17EL9ap_q_mode0EL9ap_o_mode0EL_11915</name>
<Object>p_ZZ11network_topP13params_structP8ap_fixedILi22ELi17EL9ap_q_mode0EL9ap_o_mode0EL_11915</Object>
<Type>pointer</Type>
<Scope>global</Scope>
<IOProtocol>ap_vld</IOProtocol>
<IOConfig></IOConfig>
<Dir>out</Dir>
<Bits>22</Bits>
<Attribute>data</Attribute>
</RtlPorts>
<RtlPorts>
<name>p_ZZ11network_topP13params_structP8ap_fixedILi22ELi17EL9ap_q_mode0EL9ap_o_mode0EL_11915_ap_vld</name>
<Object>p_ZZ11network_topP13params_structP8ap_fixedILi22ELi17EL9ap_q_mode0EL9ap_o_mode0EL_11915</Object>
<Type>pointer</Type>
<Scope>global</Scope>
<IOProtocol>ap_vld</IOProtocol>
<IOConfig></IOConfig>
<Dir>out</Dir>
<Bits>1</Bits>
<Attribute>control</Attribute>
</RtlPorts>
<RtlPorts>
<name>p_ZZ11network_topP13params_structP8ap_fixedILi22ELi17EL9ap_q_mode0EL9ap_o_mode0EL_11917</name>
<Object>p_ZZ11network_topP13params_structP8ap_fixedILi22ELi17EL9ap_q_mode0EL9ap_o_mode0EL_11917</Object>
<Type>pointer</Type>
<Scope>global</Scope>
<IOProtocol>ap_vld</IOProtocol>
<IOConfig></IOConfig>
<Dir>out</Dir>
<Bits>22</Bits>
<Attribute>data</Attribute>
</RtlPorts>
<RtlPorts>
<name>p_ZZ11network_topP13params_structP8ap_fixedILi22ELi17EL9ap_q_mode0EL9ap_o_mode0EL_11917_ap_vld</name>
<Object>p_ZZ11network_topP13params_structP8ap_fixedILi22ELi17EL9ap_q_mode0EL9ap_o_mode0EL_11917</Object>
<Type>pointer</Type>
<Scope>global</Scope>
<IOProtocol>ap_vld</IOProtocol>
<IOConfig></IOConfig>
<Dir>out</Dir>
<Bits>1</Bits>
<Attribute>control</Attribute>
</RtlPorts>
<RtlPorts>
<name>p_ZZ11network_topP13params_structP8ap_fixedILi22ELi17EL9ap_q_mode0EL9ap_o_mode0EL_11918</name>
<Object>p_ZZ11network_topP13params_structP8ap_fixedILi22ELi17EL9ap_q_mode0EL9ap_o_mode0EL_11918</Object>
<Type>pointer</Type>
<Scope>global</Scope>
<IOProtocol>ap_vld</IOProtocol>
<IOConfig></IOConfig>
<Dir>out</Dir>
<Bits>22</Bits>
<Attribute>data</Attribute>
</RtlPorts>
<RtlPorts>
<name>p_ZZ11network_topP13params_structP8ap_fixedILi22ELi17EL9ap_q_mode0EL9ap_o_mode0EL_11918_ap_vld</name>
<Object>p_ZZ11network_topP13params_structP8ap_fixedILi22ELi17EL9ap_q_mode0EL9ap_o_mode0EL_11918</Object>
<Type>pointer</Type>
<Scope>global</Scope>
<IOProtocol>ap_vld</IOProtocol>
<IOConfig></IOConfig>
<Dir>out</Dir>
<Bits>1</Bits>
<Attribute>control</Attribute>
</RtlPorts>
<RtlPorts>
<name>p_ZZ11network_topP13params_structP8ap_fixedILi22ELi17EL9ap_q_mode0EL9ap_o_mode0EL_11919</name>
<Object>p_ZZ11network_topP13params_structP8ap_fixedILi22ELi17EL9ap_q_mode0EL9ap_o_mode0EL_11919</Object>
<Type>pointer</Type>
<Scope>global</Scope>
<IOProtocol>ap_vld</IOProtocol>
<IOConfig></IOConfig>
<Dir>out</Dir>
<Bits>22</Bits>
<Attribute>data</Attribute>
</RtlPorts>
<RtlPorts>
<name>p_ZZ11network_topP13params_structP8ap_fixedILi22ELi17EL9ap_q_mode0EL9ap_o_mode0EL_11919_ap_vld</name>
<Object>p_ZZ11network_topP13params_structP8ap_fixedILi22ELi17EL9ap_q_mode0EL9ap_o_mode0EL_11919</Object>
<Type>pointer</Type>
<Scope>global</Scope>
<IOProtocol>ap_vld</IOProtocol>
<IOConfig></IOConfig>
<Dir>out</Dir>
<Bits>1</Bits>
<Attribute>control</Attribute>
</RtlPorts>
<RtlPorts>
<name>p_ZZ11network_topP13params_structP8ap_fixedILi22ELi17EL9ap_q_mode0EL9ap_o_mode0EL_11921</name>
<Object>p_ZZ11network_topP13params_structP8ap_fixedILi22ELi17EL9ap_q_mode0EL9ap_o_mode0EL_11921</Object>
<Type>pointer</Type>
<Scope>global</Scope>
<IOProtocol>ap_vld</IOProtocol>
<IOConfig></IOConfig>
<Dir>out</Dir>
<Bits>22</Bits>
<Attribute>data</Attribute>
</RtlPorts>
<RtlPorts>
<name>p_ZZ11network_topP13params_structP8ap_fixedILi22ELi17EL9ap_q_mode0EL9ap_o_mode0EL_11921_ap_vld</name>
<Object>p_ZZ11network_topP13params_structP8ap_fixedILi22ELi17EL9ap_q_mode0EL9ap_o_mode0EL_11921</Object>
<Type>pointer</Type>
<Scope>global</Scope>
<IOProtocol>ap_vld</IOProtocol>
<IOConfig></IOConfig>
<Dir>out</Dir>
<Bits>1</Bits>
<Attribute>control</Attribute>
</RtlPorts>
<RtlPorts>
<name>p_ZZ11network_topP13params_structP8ap_fixedILi22ELi17EL9ap_q_mode0EL9ap_o_mode0EL_11922</name>
<Object>p_ZZ11network_topP13params_structP8ap_fixedILi22ELi17EL9ap_q_mode0EL9ap_o_mode0EL_11922</Object>
<Type>pointer</Type>
<Scope>global</Scope>
<IOProtocol>ap_vld</IOProtocol>
<IOConfig></IOConfig>
<Dir>out</Dir>
<Bits>22</Bits>
<Attribute>data</Attribute>
</RtlPorts>
<RtlPorts>
<name>p_ZZ11network_topP13params_structP8ap_fixedILi22ELi17EL9ap_q_mode0EL9ap_o_mode0EL_11922_ap_vld</name>
<Object>p_ZZ11network_topP13params_structP8ap_fixedILi22ELi17EL9ap_q_mode0EL9ap_o_mode0EL_11922</Object>
<Type>pointer</Type>
<Scope>global</Scope>
<IOProtocol>ap_vld</IOProtocol>
<IOConfig></IOConfig>
<Dir>out</Dir>
<Bits>1</Bits>
<Attribute>control</Attribute>
</RtlPorts>
<RtlPorts>
<name>p_ZZ11network_topP13params_structP8ap_fixedILi22ELi17EL9ap_q_mode0EL9ap_o_mode0EL_11923</name>
<Object>p_ZZ11network_topP13params_structP8ap_fixedILi22ELi17EL9ap_q_mode0EL9ap_o_mode0EL_11923</Object>
<Type>pointer</Type>
<Scope>global</Scope>
<IOProtocol>ap_vld</IOProtocol>
<IOConfig></IOConfig>
<Dir>out</Dir>
<Bits>22</Bits>
<Attribute>data</Attribute>
</RtlPorts>
<RtlPorts>
<name>p_ZZ11network_topP13params_structP8ap_fixedILi22ELi17EL9ap_q_mode0EL9ap_o_mode0EL_11923_ap_vld</name>
<Object>p_ZZ11network_topP13params_structP8ap_fixedILi22ELi17EL9ap_q_mode0EL9ap_o_mode0EL_11923</Object>
<Type>pointer</Type>
<Scope>global</Scope>
<IOProtocol>ap_vld</IOProtocol>
<IOConfig></IOConfig>
<Dir>out</Dir>
<Bits>1</Bits>
<Attribute>control</Attribute>
</RtlPorts>
<RtlPorts>
<name>p_ZZ11network_topP13params_structP8ap_fixedILi22ELi17EL9ap_q_mode0EL9ap_o_mode0EL_11924</name>
<Object>p_ZZ11network_topP13params_structP8ap_fixedILi22ELi17EL9ap_q_mode0EL9ap_o_mode0EL_11924</Object>
<Type>pointer</Type>
<Scope>global</Scope>
<IOProtocol>ap_vld</IOProtocol>
<IOConfig></IOConfig>
<Dir>out</Dir>
<Bits>22</Bits>
<Attribute>data</Attribute>
</RtlPorts>
<RtlPorts>
<name>p_ZZ11network_topP13params_structP8ap_fixedILi22ELi17EL9ap_q_mode0EL9ap_o_mode0EL_11924_ap_vld</name>
<Object>p_ZZ11network_topP13params_structP8ap_fixedILi22ELi17EL9ap_q_mode0EL9ap_o_mode0EL_11924</Object>
<Type>pointer</Type>
<Scope>global</Scope>
<IOProtocol>ap_vld</IOProtocol>
<IOConfig></IOConfig>
<Dir>out</Dir>
<Bits>1</Bits>
<Attribute>control</Attribute>
</RtlPorts>
<RtlPorts>
<name>p_ZZ11network_topP13params_structP8ap_fixedILi22ELi17EL9ap_q_mode0EL9ap_o_mode0EL_11925</name>
<Object>p_ZZ11network_topP13params_structP8ap_fixedILi22ELi17EL9ap_q_mode0EL9ap_o_mode0EL_11925</Object>
<Type>pointer</Type>
<Scope>global</Scope>
<IOProtocol>ap_vld</IOProtocol>
<IOConfig></IOConfig>
<Dir>out</Dir>
<Bits>22</Bits>
<Attribute>data</Attribute>
</RtlPorts>
<RtlPorts>
<name>p_ZZ11network_topP13params_structP8ap_fixedILi22ELi17EL9ap_q_mode0EL9ap_o_mode0EL_11925_ap_vld</name>
<Object>p_ZZ11network_topP13params_structP8ap_fixedILi22ELi17EL9ap_q_mode0EL9ap_o_mode0EL_11925</Object>
<Type>pointer</Type>
<Scope>global</Scope>
<IOProtocol>ap_vld</IOProtocol>
<IOConfig></IOConfig>
<Dir>out</Dir>
<Bits>1</Bits>
<Attribute>control</Attribute>
</RtlPorts>
<RtlPorts>
<name>p_ZZ11network_topP13params_structP8ap_fixedILi22ELi17EL9ap_q_mode0EL9ap_o_mode0EL_11926</name>
<Object>p_ZZ11network_topP13params_structP8ap_fixedILi22ELi17EL9ap_q_mode0EL9ap_o_mode0EL_11926</Object>
<Type>pointer</Type>
<Scope>global</Scope>
<IOProtocol>ap_vld</IOProtocol>
<IOConfig></IOConfig>
<Dir>out</Dir>
<Bits>22</Bits>
<Attribute>data</Attribute>
</RtlPorts>
<RtlPorts>
<name>p_ZZ11network_topP13params_structP8ap_fixedILi22ELi17EL9ap_q_mode0EL9ap_o_mode0EL_11926_ap_vld</name>
<Object>p_ZZ11network_topP13params_structP8ap_fixedILi22ELi17EL9ap_q_mode0EL9ap_o_mode0EL_11926</Object>
<Type>pointer</Type>
<Scope>global</Scope>
<IOProtocol>ap_vld</IOProtocol>
<IOConfig></IOConfig>
<Dir>out</Dir>
<Bits>1</Bits>
<Attribute>control</Attribute>
</RtlPorts>
<RtlPorts>
<name>p_ZZ11network_topP13params_structP8ap_fixedILi22ELi17EL9ap_q_mode0EL9ap_o_mode0EL_11927</name>
<Object>p_ZZ11network_topP13params_structP8ap_fixedILi22ELi17EL9ap_q_mode0EL9ap_o_mode0EL_11927</Object>
<Type>pointer</Type>
<Scope>global</Scope>
<IOProtocol>ap_vld</IOProtocol>
<IOConfig></IOConfig>
<Dir>out</Dir>
<Bits>22</Bits>
<Attribute>data</Attribute>
</RtlPorts>
<RtlPorts>
<name>p_ZZ11network_topP13params_structP8ap_fixedILi22ELi17EL9ap_q_mode0EL9ap_o_mode0EL_11927_ap_vld</name>
<Object>p_ZZ11network_topP13params_structP8ap_fixedILi22ELi17EL9ap_q_mode0EL9ap_o_mode0EL_11927</Object>
<Type>pointer</Type>
<Scope>global</Scope>
<IOProtocol>ap_vld</IOProtocol>
<IOConfig></IOConfig>
<Dir>out</Dir>
<Bits>1</Bits>
<Attribute>control</Attribute>
</RtlPorts>
<RtlPorts>
<name>p_ZZ11network_topP13params_structP8ap_fixedILi22ELi17EL9ap_q_mode0EL9ap_o_mode0EL_11929</name>
<Object>p_ZZ11network_topP13params_structP8ap_fixedILi22ELi17EL9ap_q_mode0EL9ap_o_mode0EL_11929</Object>
<Type>pointer</Type>
<Scope>global</Scope>
<IOProtocol>ap_vld</IOProtocol>
<IOConfig></IOConfig>
<Dir>out</Dir>
<Bits>22</Bits>
<Attribute>data</Attribute>
</RtlPorts>
<RtlPorts>
<name>p_ZZ11network_topP13params_structP8ap_fixedILi22ELi17EL9ap_q_mode0EL9ap_o_mode0EL_11929_ap_vld</name>
<Object>p_ZZ11network_topP13params_structP8ap_fixedILi22ELi17EL9ap_q_mode0EL9ap_o_mode0EL_11929</Object>
<Type>pointer</Type>
<Scope>global</Scope>
<IOProtocol>ap_vld</IOProtocol>
<IOConfig></IOConfig>
<Dir>out</Dir>
<Bits>1</Bits>
<Attribute>control</Attribute>
</RtlPorts>
<RtlPorts>
<name>p_ZZ11network_topP13params_structP8ap_fixedILi22ELi17EL9ap_q_mode0EL9ap_o_mode0EL_11930</name>
<Object>p_ZZ11network_topP13params_structP8ap_fixedILi22ELi17EL9ap_q_mode0EL9ap_o_mode0EL_11930</Object>
<Type>pointer</Type>
<Scope>global</Scope>
<IOProtocol>ap_vld</IOProtocol>
<IOConfig></IOConfig>
<Dir>out</Dir>
<Bits>22</Bits>
<Attribute>data</Attribute>
</RtlPorts>
<RtlPorts>
<name>p_ZZ11network_topP13params_structP8ap_fixedILi22ELi17EL9ap_q_mode0EL9ap_o_mode0EL_11930_ap_vld</name>
<Object>p_ZZ11network_topP13params_structP8ap_fixedILi22ELi17EL9ap_q_mode0EL9ap_o_mode0EL_11930</Object>
<Type>pointer</Type>
<Scope>global</Scope>
<IOProtocol>ap_vld</IOProtocol>
<IOConfig></IOConfig>
<Dir>out</Dir>
<Bits>1</Bits>
<Attribute>control</Attribute>
</RtlPorts>
<RtlPorts>
<name>p_ZZ11network_topP13params_structP8ap_fixedILi22ELi17EL9ap_q_mode0EL9ap_o_mode0EL_11932</name>
<Object>p_ZZ11network_topP13params_structP8ap_fixedILi22ELi17EL9ap_q_mode0EL9ap_o_mode0EL_11932</Object>
<Type>pointer</Type>
<Scope>global</Scope>
<IOProtocol>ap_vld</IOProtocol>
<IOConfig></IOConfig>
<Dir>out</Dir>
<Bits>22</Bits>
<Attribute>data</Attribute>
</RtlPorts>
<RtlPorts>
<name>p_ZZ11network_topP13params_structP8ap_fixedILi22ELi17EL9ap_q_mode0EL9ap_o_mode0EL_11932_ap_vld</name>
<Object>p_ZZ11network_topP13params_structP8ap_fixedILi22ELi17EL9ap_q_mode0EL9ap_o_mode0EL_11932</Object>
<Type>pointer</Type>
<Scope>global</Scope>
<IOProtocol>ap_vld</IOProtocol>
<IOConfig></IOConfig>
<Dir>out</Dir>
<Bits>1</Bits>
<Attribute>control</Attribute>
</RtlPorts>
<RtlPorts>
<name>p_ZZ11network_topP13params_structP8ap_fixedILi22ELi17EL9ap_q_mode0EL9ap_o_mode0EL_11933</name>
<Object>p_ZZ11network_topP13params_structP8ap_fixedILi22ELi17EL9ap_q_mode0EL9ap_o_mode0EL_11933</Object>
<Type>pointer</Type>
<Scope>global</Scope>
<IOProtocol>ap_vld</IOProtocol>
<IOConfig></IOConfig>
<Dir>out</Dir>
<Bits>22</Bits>
<Attribute>data</Attribute>
</RtlPorts>
<RtlPorts>
<name>p_ZZ11network_topP13params_structP8ap_fixedILi22ELi17EL9ap_q_mode0EL9ap_o_mode0EL_11933_ap_vld</name>
<Object>p_ZZ11network_topP13params_structP8ap_fixedILi22ELi17EL9ap_q_mode0EL9ap_o_mode0EL_11933</Object>
<Type>pointer</Type>
<Scope>global</Scope>
<IOProtocol>ap_vld</IOProtocol>
<IOConfig></IOConfig>
<Dir>out</Dir>
<Bits>1</Bits>
<Attribute>control</Attribute>
</RtlPorts>
<RtlPorts>
<name>p_ZZ11network_topP13params_structP8ap_fixedILi22ELi17EL9ap_q_mode0EL9ap_o_mode0EL_11934</name>
<Object>p_ZZ11network_topP13params_structP8ap_fixedILi22ELi17EL9ap_q_mode0EL9ap_o_mode0EL_11934</Object>
<Type>pointer</Type>
<Scope>global</Scope>
<IOProtocol>ap_vld</IOProtocol>
<IOConfig></IOConfig>
<Dir>out</Dir>
<Bits>22</Bits>
<Attribute>data</Attribute>
</RtlPorts>
<RtlPorts>
<name>p_ZZ11network_topP13params_structP8ap_fixedILi22ELi17EL9ap_q_mode0EL9ap_o_mode0EL_11934_ap_vld</name>
<Object>p_ZZ11network_topP13params_structP8ap_fixedILi22ELi17EL9ap_q_mode0EL9ap_o_mode0EL_11934</Object>
<Type>pointer</Type>
<Scope>global</Scope>
<IOProtocol>ap_vld</IOProtocol>
<IOConfig></IOConfig>
<Dir>out</Dir>
<Bits>1</Bits>
<Attribute>control</Attribute>
</RtlPorts>
<RtlPorts>
<name>p_ZZ11network_topP13params_structP8ap_fixedILi22ELi17EL9ap_q_mode0EL9ap_o_mode0EL_11935</name>
<Object>p_ZZ11network_topP13params_structP8ap_fixedILi22ELi17EL9ap_q_mode0EL9ap_o_mode0EL_11935</Object>
<Type>pointer</Type>
<Scope>global</Scope>
<IOProtocol>ap_vld</IOProtocol>
<IOConfig></IOConfig>
<Dir>out</Dir>
<Bits>22</Bits>
<Attribute>data</Attribute>
</RtlPorts>
<RtlPorts>
<name>p_ZZ11network_topP13params_structP8ap_fixedILi22ELi17EL9ap_q_mode0EL9ap_o_mode0EL_11935_ap_vld</name>
<Object>p_ZZ11network_topP13params_structP8ap_fixedILi22ELi17EL9ap_q_mode0EL9ap_o_mode0EL_11935</Object>
<Type>pointer</Type>
<Scope>global</Scope>
<IOProtocol>ap_vld</IOProtocol>
<IOConfig></IOConfig>
<Dir>out</Dir>
<Bits>1</Bits>
<Attribute>control</Attribute>
</RtlPorts>
<RtlPorts>
<name>p_ZZ11network_topP13params_structP8ap_fixedILi22ELi17EL9ap_q_mode0EL9ap_o_mode0EL_11936</name>
<Object>p_ZZ11network_topP13params_structP8ap_fixedILi22ELi17EL9ap_q_mode0EL9ap_o_mode0EL_11936</Object>
<Type>pointer</Type>
<Scope>global</Scope>
<IOProtocol>ap_vld</IOProtocol>
<IOConfig></IOConfig>
<Dir>out</Dir>
<Bits>22</Bits>
<Attribute>data</Attribute>
</RtlPorts>
<RtlPorts>
<name>p_ZZ11network_topP13params_structP8ap_fixedILi22ELi17EL9ap_q_mode0EL9ap_o_mode0EL_11936_ap_vld</name>
<Object>p_ZZ11network_topP13params_structP8ap_fixedILi22ELi17EL9ap_q_mode0EL9ap_o_mode0EL_11936</Object>
<Type>pointer</Type>
<Scope>global</Scope>
<IOProtocol>ap_vld</IOProtocol>
<IOConfig></IOConfig>
<Dir>out</Dir>
<Bits>1</Bits>
<Attribute>control</Attribute>
</RtlPorts>
<RtlPorts>
<name>p_ZZ11network_topP13params_structP8ap_fixedILi22ELi17EL9ap_q_mode0EL9ap_o_mode0EL_11937</name>
<Object>p_ZZ11network_topP13params_structP8ap_fixedILi22ELi17EL9ap_q_mode0EL9ap_o_mode0EL_11937</Object>
<Type>pointer</Type>
<Scope>global</Scope>
<IOProtocol>ap_vld</IOProtocol>
<IOConfig></IOConfig>
<Dir>out</Dir>
<Bits>22</Bits>
<Attribute>data</Attribute>
</RtlPorts>
<RtlPorts>
<name>p_ZZ11network_topP13params_structP8ap_fixedILi22ELi17EL9ap_q_mode0EL9ap_o_mode0EL_11937_ap_vld</name>
<Object>p_ZZ11network_topP13params_structP8ap_fixedILi22ELi17EL9ap_q_mode0EL9ap_o_mode0EL_11937</Object>
<Type>pointer</Type>
<Scope>global</Scope>
<IOProtocol>ap_vld</IOProtocol>
<IOConfig></IOConfig>
<Dir>out</Dir>
<Bits>1</Bits>
<Attribute>control</Attribute>
</RtlPorts>
<RtlPorts>
<name>p_ZZ11network_topP13params_structP8ap_fixedILi22ELi17EL9ap_q_mode0EL9ap_o_mode0EL_11938</name>
<Object>p_ZZ11network_topP13params_structP8ap_fixedILi22ELi17EL9ap_q_mode0EL9ap_o_mode0EL_11938</Object>
<Type>pointer</Type>
<Scope>global</Scope>
<IOProtocol>ap_vld</IOProtocol>
<IOConfig></IOConfig>
<Dir>out</Dir>
<Bits>22</Bits>
<Attribute>data</Attribute>
</RtlPorts>
<RtlPorts>
<name>p_ZZ11network_topP13params_structP8ap_fixedILi22ELi17EL9ap_q_mode0EL9ap_o_mode0EL_11938_ap_vld</name>
<Object>p_ZZ11network_topP13params_structP8ap_fixedILi22ELi17EL9ap_q_mode0EL9ap_o_mode0EL_11938</Object>
<Type>pointer</Type>
<Scope>global</Scope>
<IOProtocol>ap_vld</IOProtocol>
<IOConfig></IOConfig>
<Dir>out</Dir>
<Bits>1</Bits>
<Attribute>control</Attribute>
</RtlPorts>
<RtlPorts>
<name>p_ZZ11network_topP13params_structP8ap_fixedILi22ELi17EL9ap_q_mode0EL9ap_o_mode0EL_11939</name>
<Object>p_ZZ11network_topP13params_structP8ap_fixedILi22ELi17EL9ap_q_mode0EL9ap_o_mode0EL_11939</Object>
<Type>pointer</Type>
<Scope>global</Scope>
<IOProtocol>ap_vld</IOProtocol>
<IOConfig></IOConfig>
<Dir>out</Dir>
<Bits>22</Bits>
<Attribute>data</Attribute>
</RtlPorts>
<RtlPorts>
<name>p_ZZ11network_topP13params_structP8ap_fixedILi22ELi17EL9ap_q_mode0EL9ap_o_mode0EL_11939_ap_vld</name>
<Object>p_ZZ11network_topP13params_structP8ap_fixedILi22ELi17EL9ap_q_mode0EL9ap_o_mode0EL_11939</Object>
<Type>pointer</Type>
<Scope>global</Scope>
<IOProtocol>ap_vld</IOProtocol>
<IOConfig></IOConfig>
<Dir>out</Dir>
<Bits>1</Bits>
<Attribute>control</Attribute>
</RtlPorts>
</InterfaceSummary>

</profile>
