<profile>

<ReportVersion>
<Version>2023.1</Version>
</ReportVersion>

<UserAssignments>
<unit>ns</unit>
<ProductFamily>zynquplus</ProductFamily>
<Part>xczu7ev-ffvc1156-2-e</Part>
<TopModelName>network_top_Pipeline_load_weight3_matrix_inner_loop99</TopModelName>
<TargetClockPeriod>350.00</TargetClockPeriod>
<ClockUncertainty>94.50</ClockUncertainty>
<FlowTarget>vivado</FlowTarget>
</UserAssignments>

<PerformanceEstimates>
<PipelineType>no</PipelineType>
<SummaryOfTimingAnalysis>
<unit>ns</unit>
<EstimatedClockPeriod>255.500</EstimatedClockPeriod>
</SummaryOfTimingAnalysis>
<SummaryOfOverallLatency>
<unit>clock cycles</unit>
<Best-caseLatency>90</Best-caseLatency>
<Average-caseLatency>90</Average-caseLatency>
<Worst-caseLatency>90</Worst-caseLatency>
<Best-caseRealTimeLatency>31.500 us</Best-caseRealTimeLatency>
<Average-caseRealTimeLatency>31.500 us</Average-caseRealTimeLatency>
<Worst-caseRealTimeLatency>31.500 us</Worst-caseRealTimeLatency>
<Interval-min>90</Interval-min>
<Interval-max>90</Interval-max>
</SummaryOfOverallLatency>
<SummaryOfLoopLatency>
<load_weight3_matrix_inner_loop>
<Slack>255.50</Slack>
<TripCount>80</TripCount>
<Latency>88</Latency>
<AbsoluteTimeLatency>30800</AbsoluteTimeLatency>
<PipelineII>1</PipelineII>
<PipelineDepth>10</PipelineDepth>
<InstanceList>
</InstanceList>
</load_weight3_matrix_inner_loop>
</SummaryOfLoopLatency>
</PerformanceEstimates>

<AreaEstimates>
<Resources>
<DSP>0</DSP>
<FF>183</FF>
<LUT>323</LUT>
<BRAM_18K>0</BRAM_18K>
<URAM>0</URAM>
</Resources>
<AvailableResources>
<BRAM_18K>624</BRAM_18K>
<DSP>1728</DSP>
<FF>460800</FF>
<LUT>230400</LUT>
<URAM>96</URAM>
</AvailableResources>
</AreaEstimates>

<InterfaceSummary>
<RtlPorts>
<name>ap_clk</name>
<Object>network_top_Pipeline_load_weight3_matrix_inner_loop99</Object>
<Type>return value</Type>
<Scope></Scope>
<IOProtocol>ap_ctrl_hs</IOProtocol>
<IOConfig></IOConfig>
<Dir>in</Dir>
<Bits>1</Bits>
<Attribute>control</Attribute>
</RtlPorts>
<RtlPorts>
<name>ap_rst</name>
<Object>network_top_Pipeline_load_weight3_matrix_inner_loop99</Object>
<Type>return value</Type>
<Scope></Scope>
<IOProtocol>ap_ctrl_hs</IOProtocol>
<IOConfig></IOConfig>
<Dir>in</Dir>
<Bits>1</Bits>
<Attribute>control</Attribute>
</RtlPorts>
<RtlPorts>
<name>ap_start</name>
<Object>network_top_Pipeline_load_weight3_matrix_inner_loop99</Object>
<Type>return value</Type>
<Scope></Scope>
<IOProtocol>ap_ctrl_hs</IOProtocol>
<IOConfig></IOConfig>
<Dir>in</Dir>
<Bits>1</Bits>
<Attribute>control</Attribute>
</RtlPorts>
<RtlPorts>
<name>ap_done</name>
<Object>network_top_Pipeline_load_weight3_matrix_inner_loop99</Object>
<Type>return value</Type>
<Scope></Scope>
<IOProtocol>ap_ctrl_hs</IOProtocol>
<IOConfig></IOConfig>
<Dir>out</Dir>
<Bits>1</Bits>
<Attribute>control</Attribute>
</RtlPorts>
<RtlPorts>
<name>ap_idle</name>
<Object>network_top_Pipeline_load_weight3_matrix_inner_loop99</Object>
<Type>return value</Type>
<Scope></Scope>
<IOProtocol>ap_ctrl_hs</IOProtocol>
<IOConfig></IOConfig>
<Dir>out</Dir>
<Bits>1</Bits>
<Attribute>control</Attribute>
</RtlPorts>
<RtlPorts>
<name>ap_ready</name>
<Object>network_top_Pipeline_load_weight3_matrix_inner_loop99</Object>
<Type>return value</Type>
<Scope></Scope>
<IOProtocol>ap_ctrl_hs</IOProtocol>
<IOConfig></IOConfig>
<Dir>out</Dir>
<Bits>1</Bits>
<Attribute>control</Attribute>
</RtlPorts>
<RtlPorts>
<name>m_axi_gmem_AWVALID</name>
<Object>gmem</Object>
<Type>pointer</Type>
<Scope></Scope>
<IOProtocol>m_axi</IOProtocol>
<IOConfig></IOConfig>
<Dir>out</Dir>
<Bits>1</Bits>
<Attribute>unknown</Attribute>
</RtlPorts>
<RtlPorts>
<name>m_axi_gmem_AWREADY</name>
<Object>gmem</Object>
<Type>pointer</Type>
<Scope></Scope>
<IOProtocol>m_axi</IOProtocol>
<IOConfig></IOConfig>
<Dir>in</Dir>
<Bits>1</Bits>
<Attribute>unknown</Attribute>
</RtlPorts>
<RtlPorts>
<name>m_axi_gmem_AWADDR</name>
<Object>gmem</Object>
<Type>pointer</Type>
<Scope></Scope>
<IOProtocol>m_axi</IOProtocol>
<IOConfig></IOConfig>
<Dir>out</Dir>
<Bits>64</Bits>
<Attribute>unknown</Attribute>
</RtlPorts>
<RtlPorts>
<name>m_axi_gmem_AWID</name>
<Object>gmem</Object>
<Type>pointer</Type>
<Scope></Scope>
<IOProtocol>m_axi</IOProtocol>
<IOConfig></IOConfig>
<Dir>out</Dir>
<Bits>1</Bits>
<Attribute>unknown</Attribute>
</RtlPorts>
<RtlPorts>
<name>m_axi_gmem_AWLEN</name>
<Object>gmem</Object>
<Type>pointer</Type>
<Scope></Scope>
<IOProtocol>m_axi</IOProtocol>
<IOConfig></IOConfig>
<Dir>out</Dir>
<Bits>32</Bits>
<Attribute>unknown</Attribute>
</RtlPorts>
<RtlPorts>
<name>m_axi_gmem_AWSIZE</name>
<Object>gmem</Object>
<Type>pointer</Type>
<Scope></Scope>
<IOProtocol>m_axi</IOProtocol>
<IOConfig></IOConfig>
<Dir>out</Dir>
<Bits>3</Bits>
<Attribute>unknown</Attribute>
</RtlPorts>
<RtlPorts>
<name>m_axi_gmem_AWBURST</name>
<Object>gmem</Object>
<Type>pointer</Type>
<Scope></Scope>
<IOProtocol>m_axi</IOProtocol>
<IOConfig></IOConfig>
<Dir>out</Dir>
<Bits>2</Bits>
<Attribute>unknown</Attribute>
</RtlPorts>
<RtlPorts>
<name>m_axi_gmem_AWLOCK</name>
<Object>gmem</Object>
<Type>pointer</Type>
<Scope></Scope>
<IOProtocol>m_axi</IOProtocol>
<IOConfig></IOConfig>
<Dir>out</Dir>
<Bits>2</Bits>
<Attribute>unknown</Attribute>
</RtlPorts>
<RtlPorts>
<name>m_axi_gmem_AWCACHE</name>
<Object>gmem</Object>
<Type>pointer</Type>
<Scope></Scope>
<IOProtocol>m_axi</IOProtocol>
<IOConfig></IOConfig>
<Dir>out</Dir>
<Bits>4</Bits>
<Attribute>unknown</Attribute>
</RtlPorts>
<RtlPorts>
<name>m_axi_gmem_AWPROT</name>
<Object>gmem</Object>
<Type>pointer</Type>
<Scope></Scope>
<IOProtocol>m_axi</IOProtocol>
<IOConfig></IOConfig>
<Dir>out</Dir>
<Bits>3</Bits>
<Attribute>unknown</Attribute>
</RtlPorts>
<RtlPorts>
<name>m_axi_gmem_AWQOS</name>
<Object>gmem</Object>
<Type>pointer</Type>
<Scope></Scope>
<IOProtocol>m_axi</IOProtocol>
<IOConfig></IOConfig>
<Dir>out</Dir>
<Bits>4</Bits>
<Attribute>unknown</Attribute>
</RtlPorts>
<RtlPorts>
<name>m_axi_gmem_AWREGION</name>
<Object>gmem</Object>
<Type>pointer</Type>
<Scope></Scope>
<IOProtocol>m_axi</IOProtocol>
<IOConfig></IOConfig>
<Dir>out</Dir>
<Bits>4</Bits>
<Attribute>unknown</Attribute>
</RtlPorts>
<RtlPorts>
<name>m_axi_gmem_AWUSER</name>
<Object>gmem</Object>
<Type>pointer</Type>
<Scope></Scope>
<IOProtocol>m_axi</IOProtocol>
<IOConfig></IOConfig>
<Dir>out</Dir>
<Bits>1</Bits>
<Attribute>unknown</Attribute>
</RtlPorts>
<RtlPorts>
<name>m_axi_gmem_WVALID</name>
<Object>gmem</Object>
<Type>pointer</Type>
<Scope></Scope>
<IOProtocol>m_axi</IOProtocol>
<IOConfig></IOConfig>
<Dir>out</Dir>
<Bits>1</Bits>
<Attribute>unknown</Attribute>
</RtlPorts>
<RtlPorts>
<name>m_axi_gmem_WREADY</name>
<Object>gmem</Object>
<Type>pointer</Type>
<Scope></Scope>
<IOProtocol>m_axi</IOProtocol>
<IOConfig></IOConfig>
<Dir>in</Dir>
<Bits>1</Bits>
<Attribute>unknown</Attribute>
</RtlPorts>
<RtlPorts>
<name>m_axi_gmem_WDATA</name>
<Object>gmem</Object>
<Type>pointer</Type>
<Scope></Scope>
<IOProtocol>m_axi</IOProtocol>
<IOConfig></IOConfig>
<Dir>out</Dir>
<Bits>32</Bits>
<Attribute>unknown</Attribute>
</RtlPorts>
<RtlPorts>
<name>m_axi_gmem_WSTRB</name>
<Object>gmem</Object>
<Type>pointer</Type>
<Scope></Scope>
<IOProtocol>m_axi</IOProtocol>
<IOConfig></IOConfig>
<Dir>out</Dir>
<Bits>4</Bits>
<Attribute>unknown</Attribute>
</RtlPorts>
<RtlPorts>
<name>m_axi_gmem_WLAST</name>
<Object>gmem</Object>
<Type>pointer</Type>
<Scope></Scope>
<IOProtocol>m_axi</IOProtocol>
<IOConfig></IOConfig>
<Dir>out</Dir>
<Bits>1</Bits>
<Attribute>unknown</Attribute>
</RtlPorts>
<RtlPorts>
<name>m_axi_gmem_WID</name>
<Object>gmem</Object>
<Type>pointer</Type>
<Scope></Scope>
<IOProtocol>m_axi</IOProtocol>
<IOConfig></IOConfig>
<Dir>out</Dir>
<Bits>1</Bits>
<Attribute>unknown</Attribute>
</RtlPorts>
<RtlPorts>
<name>m_axi_gmem_WUSER</name>
<Object>gmem</Object>
<Type>pointer</Type>
<Scope></Scope>
<IOProtocol>m_axi</IOProtocol>
<IOConfig></IOConfig>
<Dir>out</Dir>
<Bits>1</Bits>
<Attribute>unknown</Attribute>
</RtlPorts>
<RtlPorts>
<name>m_axi_gmem_ARVALID</name>
<Object>gmem</Object>
<Type>pointer</Type>
<Scope></Scope>
<IOProtocol>m_axi</IOProtocol>
<IOConfig></IOConfig>
<Dir>out</Dir>
<Bits>1</Bits>
<Attribute>unknown</Attribute>
</RtlPorts>
<RtlPorts>
<name>m_axi_gmem_ARREADY</name>
<Object>gmem</Object>
<Type>pointer</Type>
<Scope></Scope>
<IOProtocol>m_axi</IOProtocol>
<IOConfig></IOConfig>
<Dir>in</Dir>
<Bits>1</Bits>
<Attribute>unknown</Attribute>
</RtlPorts>
<RtlPorts>
<name>m_axi_gmem_ARADDR</name>
<Object>gmem</Object>
<Type>pointer</Type>
<Scope></Scope>
<IOProtocol>m_axi</IOProtocol>
<IOConfig></IOConfig>
<Dir>out</Dir>
<Bits>64</Bits>
<Attribute>unknown</Attribute>
</RtlPorts>
<RtlPorts>
<name>m_axi_gmem_ARID</name>
<Object>gmem</Object>
<Type>pointer</Type>
<Scope></Scope>
<IOProtocol>m_axi</IOProtocol>
<IOConfig></IOConfig>
<Dir>out</Dir>
<Bits>1</Bits>
<Attribute>unknown</Attribute>
</RtlPorts>
<RtlPorts>
<name>m_axi_gmem_ARLEN</name>
<Object>gmem</Object>
<Type>pointer</Type>
<Scope></Scope>
<IOProtocol>m_axi</IOProtocol>
<IOConfig></IOConfig>
<Dir>out</Dir>
<Bits>32</Bits>
<Attribute>unknown</Attribute>
</RtlPorts>
<RtlPorts>
<name>m_axi_gmem_ARSIZE</name>
<Object>gmem</Object>
<Type>pointer</Type>
<Scope></Scope>
<IOProtocol>m_axi</IOProtocol>
<IOConfig></IOConfig>
<Dir>out</Dir>
<Bits>3</Bits>
<Attribute>unknown</Attribute>
</RtlPorts>
<RtlPorts>
<name>m_axi_gmem_ARBURST</name>
<Object>gmem</Object>
<Type>pointer</Type>
<Scope></Scope>
<IOProtocol>m_axi</IOProtocol>
<IOConfig></IOConfig>
<Dir>out</Dir>
<Bits>2</Bits>
<Attribute>unknown</Attribute>
</RtlPorts>
<RtlPorts>
<name>m_axi_gmem_ARLOCK</name>
<Object>gmem</Object>
<Type>pointer</Type>
<Scope></Scope>
<IOProtocol>m_axi</IOProtocol>
<IOConfig></IOConfig>
<Dir>out</Dir>
<Bits>2</Bits>
<Attribute>unknown</Attribute>
</RtlPorts>
<RtlPorts>
<name>m_axi_gmem_ARCACHE</name>
<Object>gmem</Object>
<Type>pointer</Type>
<Scope></Scope>
<IOProtocol>m_axi</IOProtocol>
<IOConfig></IOConfig>
<Dir>out</Dir>
<Bits>4</Bits>
<Attribute>unknown</Attribute>
</RtlPorts>
<RtlPorts>
<name>m_axi_gmem_ARPROT</name>
<Object>gmem</Object>
<Type>pointer</Type>
<Scope></Scope>
<IOProtocol>m_axi</IOProtocol>
<IOConfig></IOConfig>
<Dir>out</Dir>
<Bits>3</Bits>
<Attribute>unknown</Attribute>
</RtlPorts>
<RtlPorts>
<name>m_axi_gmem_ARQOS</name>
<Object>gmem</Object>
<Type>pointer</Type>
<Scope></Scope>
<IOProtocol>m_axi</IOProtocol>
<IOConfig></IOConfig>
<Dir>out</Dir>
<Bits>4</Bits>
<Attribute>unknown</Attribute>
</RtlPorts>
<RtlPorts>
<name>m_axi_gmem_ARREGION</name>
<Object>gmem</Object>
<Type>pointer</Type>
<Scope></Scope>
<IOProtocol>m_axi</IOProtocol>
<IOConfig></IOConfig>
<Dir>out</Dir>
<Bits>4</Bits>
<Attribute>unknown</Attribute>
</RtlPorts>
<RtlPorts>
<name>m_axi_gmem_ARUSER</name>
<Object>gmem</Object>
<Type>pointer</Type>
<Scope></Scope>
<IOProtocol>m_axi</IOProtocol>
<IOConfig></IOConfig>
<Dir>out</Dir>
<Bits>1</Bits>
<Attribute>unknown</Attribute>
</RtlPorts>
<RtlPorts>
<name>m_axi_gmem_RVALID</name>
<Object>gmem</Object>
<Type>pointer</Type>
<Scope></Scope>
<IOProtocol>m_axi</IOProtocol>
<IOConfig></IOConfig>
<Dir>in</Dir>
<Bits>1</Bits>
<Attribute>unknown</Attribute>
</RtlPorts>
<RtlPorts>
<name>m_axi_gmem_RREADY</name>
<Object>gmem</Object>
<Type>pointer</Type>
<Scope></Scope>
<IOProtocol>m_axi</IOProtocol>
<IOConfig></IOConfig>
<Dir>out</Dir>
<Bits>1</Bits>
<Attribute>unknown</Attribute>
</RtlPorts>
<RtlPorts>
<name>m_axi_gmem_RDATA</name>
<Object>gmem</Object>
<Type>pointer</Type>
<Scope></Scope>
<IOProtocol>m_axi</IOProtocol>
<IOConfig></IOConfig>
<Dir>in</Dir>
<Bits>32</Bits>
<Attribute>unknown</Attribute>
</RtlPorts>
<RtlPorts>
<name>m_axi_gmem_RLAST</name>
<Object>gmem</Object>
<Type>pointer</Type>
<Scope></Scope>
<IOProtocol>m_axi</IOProtocol>
<IOConfig></IOConfig>
<Dir>in</Dir>
<Bits>1</Bits>
<Attribute>unknown</Attribute>
</RtlPorts>
<RtlPorts>
<name>m_axi_gmem_RID</name>
<Object>gmem</Object>
<Type>pointer</Type>
<Scope></Scope>
<IOProtocol>m_axi</IOProtocol>
<IOConfig></IOConfig>
<Dir>in</Dir>
<Bits>1</Bits>
<Attribute>unknown</Attribute>
</RtlPorts>
<RtlPorts>
<name>m_axi_gmem_RFIFONUM</name>
<Object>gmem</Object>
<Type>pointer</Type>
<Scope></Scope>
<IOProtocol>m_axi</IOProtocol>
<IOConfig></IOConfig>
<Dir>in</Dir>
<Bits>9</Bits>
<Attribute>unknown</Attribute>
</RtlPorts>
<RtlPorts>
<name>m_axi_gmem_RUSER</name>
<Object>gmem</Object>
<Type>pointer</Type>
<Scope></Scope>
<IOProtocol>m_axi</IOProtocol>
<IOConfig></IOConfig>
<Dir>in</Dir>
<Bits>1</Bits>
<Attribute>unknown</Attribute>
</RtlPorts>
<RtlPorts>
<name>m_axi_gmem_RRESP</name>
<Object>gmem</Object>
<Type>pointer</Type>
<Scope></Scope>
<IOProtocol>m_axi</IOProtocol>
<IOConfig></IOConfig>
<Dir>in</Dir>
<Bits>2</Bits>
<Attribute>unknown</Attribute>
</RtlPorts>
<RtlPorts>
<name>m_axi_gmem_BVALID</name>
<Object>gmem</Object>
<Type>pointer</Type>
<Scope></Scope>
<IOProtocol>m_axi</IOProtocol>
<IOConfig></IOConfig>
<Dir>in</Dir>
<Bits>1</Bits>
<Attribute>unknown</Attribute>
</RtlPorts>
<RtlPorts>
<name>m_axi_gmem_BREADY</name>
<Object>gmem</Object>
<Type>pointer</Type>
<Scope></Scope>
<IOProtocol>m_axi</IOProtocol>
<IOConfig></IOConfig>
<Dir>out</Dir>
<Bits>1</Bits>
<Attribute>unknown</Attribute>
</RtlPorts>
<RtlPorts>
<name>m_axi_gmem_BRESP</name>
<Object>gmem</Object>
<Type>pointer</Type>
<Scope></Scope>
<IOProtocol>m_axi</IOProtocol>
<IOConfig></IOConfig>
<Dir>in</Dir>
<Bits>2</Bits>
<Attribute>unknown</Attribute>
</RtlPorts>
<RtlPorts>
<name>m_axi_gmem_BID</name>
<Object>gmem</Object>
<Type>pointer</Type>
<Scope></Scope>
<IOProtocol>m_axi</IOProtocol>
<IOConfig></IOConfig>
<Dir>in</Dir>
<Bits>1</Bits>
<Attribute>unknown</Attribute>
</RtlPorts>
<RtlPorts>
<name>m_axi_gmem_BUSER</name>
<Object>gmem</Object>
<Type>pointer</Type>
<Scope></Scope>
<IOProtocol>m_axi</IOProtocol>
<IOConfig></IOConfig>
<Dir>in</Dir>
<Bits>1</Bits>
<Attribute>unknown</Attribute>
</RtlPorts>
<RtlPorts>
<name>add_ln225</name>
<Object>add_ln225</Object>
<Type>scalar</Type>
<Scope></Scope>
<IOProtocol>ap_none</IOProtocol>
<IOConfig></IOConfig>
<Dir>in</Dir>
<Bits>64</Bits>
<Attribute>data</Attribute>
</RtlPorts>
<RtlPorts>
<name>p_ZZ11network_topP13params_structP8ap_fixedILi22ELi17EL9ap_q_mode0EL9ap_o_mode0EL_17575</name>
<Object>p_ZZ11network_topP13params_structP8ap_fixedILi22ELi17EL9ap_q_mode0EL9ap_o_mode0EL_17575</Object>
<Type>pointer</Type>
<Scope>global</Scope>
<IOProtocol>ap_vld</IOProtocol>
<IOConfig></IOConfig>
<Dir>out</Dir>
<Bits>22</Bits>
<Attribute>data</Attribute>
</RtlPorts>
<RtlPorts>
<name>p_ZZ11network_topP13params_structP8ap_fixedILi22ELi17EL9ap_q_mode0EL9ap_o_mode0EL_17575_ap_vld</name>
<Object>p_ZZ11network_topP13params_structP8ap_fixedILi22ELi17EL9ap_q_mode0EL9ap_o_mode0EL_17575</Object>
<Type>pointer</Type>
<Scope>global</Scope>
<IOProtocol>ap_vld</IOProtocol>
<IOConfig></IOConfig>
<Dir>out</Dir>
<Bits>1</Bits>
<Attribute>control</Attribute>
</RtlPorts>
<RtlPorts>
<name>p_ZZ11network_topP13params_structP8ap_fixedILi22ELi17EL9ap_q_mode0EL9ap_o_mode0EL_17576</name>
<Object>p_ZZ11network_topP13params_structP8ap_fixedILi22ELi17EL9ap_q_mode0EL9ap_o_mode0EL_17576</Object>
<Type>pointer</Type>
<Scope>global</Scope>
<IOProtocol>ap_vld</IOProtocol>
<IOConfig></IOConfig>
<Dir>out</Dir>
<Bits>22</Bits>
<Attribute>data</Attribute>
</RtlPorts>
<RtlPorts>
<name>p_ZZ11network_topP13params_structP8ap_fixedILi22ELi17EL9ap_q_mode0EL9ap_o_mode0EL_17576_ap_vld</name>
<Object>p_ZZ11network_topP13params_structP8ap_fixedILi22ELi17EL9ap_q_mode0EL9ap_o_mode0EL_17576</Object>
<Type>pointer</Type>
<Scope>global</Scope>
<IOProtocol>ap_vld</IOProtocol>
<IOConfig></IOConfig>
<Dir>out</Dir>
<Bits>1</Bits>
<Attribute>control</Attribute>
</RtlPorts>
<RtlPorts>
<name>p_ZZ11network_topP13params_structP8ap_fixedILi22ELi17EL9ap_q_mode0EL9ap_o_mode0EL_17588</name>
<Object>p_ZZ11network_topP13params_structP8ap_fixedILi22ELi17EL9ap_q_mode0EL9ap_o_mode0EL_17588</Object>
<Type>pointer</Type>
<Scope>global</Scope>
<IOProtocol>ap_vld</IOProtocol>
<IOConfig></IOConfig>
<Dir>out</Dir>
<Bits>22</Bits>
<Attribute>data</Attribute>
</RtlPorts>
<RtlPorts>
<name>p_ZZ11network_topP13params_structP8ap_fixedILi22ELi17EL9ap_q_mode0EL9ap_o_mode0EL_17588_ap_vld</name>
<Object>p_ZZ11network_topP13params_structP8ap_fixedILi22ELi17EL9ap_q_mode0EL9ap_o_mode0EL_17588</Object>
<Type>pointer</Type>
<Scope>global</Scope>
<IOProtocol>ap_vld</IOProtocol>
<IOConfig></IOConfig>
<Dir>out</Dir>
<Bits>1</Bits>
<Attribute>control</Attribute>
</RtlPorts>
<RtlPorts>
<name>p_ZZ11network_topP13params_structP8ap_fixedILi22ELi17EL9ap_q_mode0EL9ap_o_mode0EL_17600</name>
<Object>p_ZZ11network_topP13params_structP8ap_fixedILi22ELi17EL9ap_q_mode0EL9ap_o_mode0EL_17600</Object>
<Type>pointer</Type>
<Scope>global</Scope>
<IOProtocol>ap_vld</IOProtocol>
<IOConfig></IOConfig>
<Dir>out</Dir>
<Bits>22</Bits>
<Attribute>data</Attribute>
</RtlPorts>
<RtlPorts>
<name>p_ZZ11network_topP13params_structP8ap_fixedILi22ELi17EL9ap_q_mode0EL9ap_o_mode0EL_17600_ap_vld</name>
<Object>p_ZZ11network_topP13params_structP8ap_fixedILi22ELi17EL9ap_q_mode0EL9ap_o_mode0EL_17600</Object>
<Type>pointer</Type>
<Scope>global</Scope>
<IOProtocol>ap_vld</IOProtocol>
<IOConfig></IOConfig>
<Dir>out</Dir>
<Bits>1</Bits>
<Attribute>control</Attribute>
</RtlPorts>
<RtlPorts>
<name>p_ZZ11network_topP13params_structP8ap_fixedILi22ELi17EL9ap_q_mode0EL9ap_o_mode0EL_17612</name>
<Object>p_ZZ11network_topP13params_structP8ap_fixedILi22ELi17EL9ap_q_mode0EL9ap_o_mode0EL_17612</Object>
<Type>pointer</Type>
<Scope>global</Scope>
<IOProtocol>ap_vld</IOProtocol>
<IOConfig></IOConfig>
<Dir>out</Dir>
<Bits>22</Bits>
<Attribute>data</Attribute>
</RtlPorts>
<RtlPorts>
<name>p_ZZ11network_topP13params_structP8ap_fixedILi22ELi17EL9ap_q_mode0EL9ap_o_mode0EL_17612_ap_vld</name>
<Object>p_ZZ11network_topP13params_structP8ap_fixedILi22ELi17EL9ap_q_mode0EL9ap_o_mode0EL_17612</Object>
<Type>pointer</Type>
<Scope>global</Scope>
<IOProtocol>ap_vld</IOProtocol>
<IOConfig></IOConfig>
<Dir>out</Dir>
<Bits>1</Bits>
<Attribute>control</Attribute>
</RtlPorts>
<RtlPorts>
<name>p_ZZ11network_topP13params_structP8ap_fixedILi22ELi17EL9ap_q_mode0EL9ap_o_mode0EL_17624</name>
<Object>p_ZZ11network_topP13params_structP8ap_fixedILi22ELi17EL9ap_q_mode0EL9ap_o_mode0EL_17624</Object>
<Type>pointer</Type>
<Scope>global</Scope>
<IOProtocol>ap_vld</IOProtocol>
<IOConfig></IOConfig>
<Dir>out</Dir>
<Bits>22</Bits>
<Attribute>data</Attribute>
</RtlPorts>
<RtlPorts>
<name>p_ZZ11network_topP13params_structP8ap_fixedILi22ELi17EL9ap_q_mode0EL9ap_o_mode0EL_17624_ap_vld</name>
<Object>p_ZZ11network_topP13params_structP8ap_fixedILi22ELi17EL9ap_q_mode0EL9ap_o_mode0EL_17624</Object>
<Type>pointer</Type>
<Scope>global</Scope>
<IOProtocol>ap_vld</IOProtocol>
<IOConfig></IOConfig>
<Dir>out</Dir>
<Bits>1</Bits>
<Attribute>control</Attribute>
</RtlPorts>
<RtlPorts>
<name>p_ZZ11network_topP13params_structP8ap_fixedILi22ELi17EL9ap_q_mode0EL9ap_o_mode0EL_17636</name>
<Object>p_ZZ11network_topP13params_structP8ap_fixedILi22ELi17EL9ap_q_mode0EL9ap_o_mode0EL_17636</Object>
<Type>pointer</Type>
<Scope>global</Scope>
<IOProtocol>ap_vld</IOProtocol>
<IOConfig></IOConfig>
<Dir>out</Dir>
<Bits>22</Bits>
<Attribute>data</Attribute>
</RtlPorts>
<RtlPorts>
<name>p_ZZ11network_topP13params_structP8ap_fixedILi22ELi17EL9ap_q_mode0EL9ap_o_mode0EL_17636_ap_vld</name>
<Object>p_ZZ11network_topP13params_structP8ap_fixedILi22ELi17EL9ap_q_mode0EL9ap_o_mode0EL_17636</Object>
<Type>pointer</Type>
<Scope>global</Scope>
<IOProtocol>ap_vld</IOProtocol>
<IOConfig></IOConfig>
<Dir>out</Dir>
<Bits>1</Bits>
<Attribute>control</Attribute>
</RtlPorts>
<RtlPorts>
<name>p_ZZ11network_topP13params_structP8ap_fixedILi22ELi17EL9ap_q_mode0EL9ap_o_mode0EL_17648</name>
<Object>p_ZZ11network_topP13params_structP8ap_fixedILi22ELi17EL9ap_q_mode0EL9ap_o_mode0EL_17648</Object>
<Type>pointer</Type>
<Scope>global</Scope>
<IOProtocol>ap_vld</IOProtocol>
<IOConfig></IOConfig>
<Dir>out</Dir>
<Bits>22</Bits>
<Attribute>data</Attribute>
</RtlPorts>
<RtlPorts>
<name>p_ZZ11network_topP13params_structP8ap_fixedILi22ELi17EL9ap_q_mode0EL9ap_o_mode0EL_17648_ap_vld</name>
<Object>p_ZZ11network_topP13params_structP8ap_fixedILi22ELi17EL9ap_q_mode0EL9ap_o_mode0EL_17648</Object>
<Type>pointer</Type>
<Scope>global</Scope>
<IOProtocol>ap_vld</IOProtocol>
<IOConfig></IOConfig>
<Dir>out</Dir>
<Bits>1</Bits>
<Attribute>control</Attribute>
</RtlPorts>
<RtlPorts>
<name>p_ZZ11network_topP13params_structP8ap_fixedILi22ELi17EL9ap_q_mode0EL9ap_o_mode0EL_17660</name>
<Object>p_ZZ11network_topP13params_structP8ap_fixedILi22ELi17EL9ap_q_mode0EL9ap_o_mode0EL_17660</Object>
<Type>pointer</Type>
<Scope>global</Scope>
<IOProtocol>ap_vld</IOProtocol>
<IOConfig></IOConfig>
<Dir>out</Dir>
<Bits>22</Bits>
<Attribute>data</Attribute>
</RtlPorts>
<RtlPorts>
<name>p_ZZ11network_topP13params_structP8ap_fixedILi22ELi17EL9ap_q_mode0EL9ap_o_mode0EL_17660_ap_vld</name>
<Object>p_ZZ11network_topP13params_structP8ap_fixedILi22ELi17EL9ap_q_mode0EL9ap_o_mode0EL_17660</Object>
<Type>pointer</Type>
<Scope>global</Scope>
<IOProtocol>ap_vld</IOProtocol>
<IOConfig></IOConfig>
<Dir>out</Dir>
<Bits>1</Bits>
<Attribute>control</Attribute>
</RtlPorts>
<RtlPorts>
<name>p_ZZ11network_topP13params_structP8ap_fixedILi22ELi17EL9ap_q_mode0EL9ap_o_mode0EL_17661</name>
<Object>p_ZZ11network_topP13params_structP8ap_fixedILi22ELi17EL9ap_q_mode0EL9ap_o_mode0EL_17661</Object>
<Type>pointer</Type>
<Scope>global</Scope>
<IOProtocol>ap_vld</IOProtocol>
<IOConfig></IOConfig>
<Dir>out</Dir>
<Bits>22</Bits>
<Attribute>data</Attribute>
</RtlPorts>
<RtlPorts>
<name>p_ZZ11network_topP13params_structP8ap_fixedILi22ELi17EL9ap_q_mode0EL9ap_o_mode0EL_17661_ap_vld</name>
<Object>p_ZZ11network_topP13params_structP8ap_fixedILi22ELi17EL9ap_q_mode0EL9ap_o_mode0EL_17661</Object>
<Type>pointer</Type>
<Scope>global</Scope>
<IOProtocol>ap_vld</IOProtocol>
<IOConfig></IOConfig>
<Dir>out</Dir>
<Bits>1</Bits>
<Attribute>control</Attribute>
</RtlPorts>
<RtlPorts>
<name>p_ZZ11network_topP13params_structP8ap_fixedILi22ELi17EL9ap_q_mode0EL9ap_o_mode0EL_17577</name>
<Object>p_ZZ11network_topP13params_structP8ap_fixedILi22ELi17EL9ap_q_mode0EL9ap_o_mode0EL_17577</Object>
<Type>pointer</Type>
<Scope>global</Scope>
<IOProtocol>ap_vld</IOProtocol>
<IOConfig></IOConfig>
<Dir>out</Dir>
<Bits>22</Bits>
<Attribute>data</Attribute>
</RtlPorts>
<RtlPorts>
<name>p_ZZ11network_topP13params_structP8ap_fixedILi22ELi17EL9ap_q_mode0EL9ap_o_mode0EL_17577_ap_vld</name>
<Object>p_ZZ11network_topP13params_structP8ap_fixedILi22ELi17EL9ap_q_mode0EL9ap_o_mode0EL_17577</Object>
<Type>pointer</Type>
<Scope>global</Scope>
<IOProtocol>ap_vld</IOProtocol>
<IOConfig></IOConfig>
<Dir>out</Dir>
<Bits>1</Bits>
<Attribute>control</Attribute>
</RtlPorts>
<RtlPorts>
<name>p_ZZ11network_topP13params_structP8ap_fixedILi22ELi17EL9ap_q_mode0EL9ap_o_mode0EL_17578</name>
<Object>p_ZZ11network_topP13params_structP8ap_fixedILi22ELi17EL9ap_q_mode0EL9ap_o_mode0EL_17578</Object>
<Type>pointer</Type>
<Scope>global</Scope>
<IOProtocol>ap_vld</IOProtocol>
<IOConfig></IOConfig>
<Dir>out</Dir>
<Bits>22</Bits>
<Attribute>data</Attribute>
</RtlPorts>
<RtlPorts>
<name>p_ZZ11network_topP13params_structP8ap_fixedILi22ELi17EL9ap_q_mode0EL9ap_o_mode0EL_17578_ap_vld</name>
<Object>p_ZZ11network_topP13params_structP8ap_fixedILi22ELi17EL9ap_q_mode0EL9ap_o_mode0EL_17578</Object>
<Type>pointer</Type>
<Scope>global</Scope>
<IOProtocol>ap_vld</IOProtocol>
<IOConfig></IOConfig>
<Dir>out</Dir>
<Bits>1</Bits>
<Attribute>control</Attribute>
</RtlPorts>
<RtlPorts>
<name>p_ZZ11network_topP13params_structP8ap_fixedILi22ELi17EL9ap_q_mode0EL9ap_o_mode0EL_17579</name>
<Object>p_ZZ11network_topP13params_structP8ap_fixedILi22ELi17EL9ap_q_mode0EL9ap_o_mode0EL_17579</Object>
<Type>pointer</Type>
<Scope>global</Scope>
<IOProtocol>ap_vld</IOProtocol>
<IOConfig></IOConfig>
<Dir>out</Dir>
<Bits>22</Bits>
<Attribute>data</Attribute>
</RtlPorts>
<RtlPorts>
<name>p_ZZ11network_topP13params_structP8ap_fixedILi22ELi17EL9ap_q_mode0EL9ap_o_mode0EL_17579_ap_vld</name>
<Object>p_ZZ11network_topP13params_structP8ap_fixedILi22ELi17EL9ap_q_mode0EL9ap_o_mode0EL_17579</Object>
<Type>pointer</Type>
<Scope>global</Scope>
<IOProtocol>ap_vld</IOProtocol>
<IOConfig></IOConfig>
<Dir>out</Dir>
<Bits>1</Bits>
<Attribute>control</Attribute>
</RtlPorts>
<RtlPorts>
<name>p_ZZ11network_topP13params_structP8ap_fixedILi22ELi17EL9ap_q_mode0EL9ap_o_mode0EL_17580</name>
<Object>p_ZZ11network_topP13params_structP8ap_fixedILi22ELi17EL9ap_q_mode0EL9ap_o_mode0EL_17580</Object>
<Type>pointer</Type>
<Scope>global</Scope>
<IOProtocol>ap_vld</IOProtocol>
<IOConfig></IOConfig>
<Dir>out</Dir>
<Bits>22</Bits>
<Attribute>data</Attribute>
</RtlPorts>
<RtlPorts>
<name>p_ZZ11network_topP13params_structP8ap_fixedILi22ELi17EL9ap_q_mode0EL9ap_o_mode0EL_17580_ap_vld</name>
<Object>p_ZZ11network_topP13params_structP8ap_fixedILi22ELi17EL9ap_q_mode0EL9ap_o_mode0EL_17580</Object>
<Type>pointer</Type>
<Scope>global</Scope>
<IOProtocol>ap_vld</IOProtocol>
<IOConfig></IOConfig>
<Dir>out</Dir>
<Bits>1</Bits>
<Attribute>control</Attribute>
</RtlPorts>
<RtlPorts>
<name>p_ZZ11network_topP13params_structP8ap_fixedILi22ELi17EL9ap_q_mode0EL9ap_o_mode0EL_17581</name>
<Object>p_ZZ11network_topP13params_structP8ap_fixedILi22ELi17EL9ap_q_mode0EL9ap_o_mode0EL_17581</Object>
<Type>pointer</Type>
<Scope>global</Scope>
<IOProtocol>ap_vld</IOProtocol>
<IOConfig></IOConfig>
<Dir>out</Dir>
<Bits>22</Bits>
<Attribute>data</Attribute>
</RtlPorts>
<RtlPorts>
<name>p_ZZ11network_topP13params_structP8ap_fixedILi22ELi17EL9ap_q_mode0EL9ap_o_mode0EL_17581_ap_vld</name>
<Object>p_ZZ11network_topP13params_structP8ap_fixedILi22ELi17EL9ap_q_mode0EL9ap_o_mode0EL_17581</Object>
<Type>pointer</Type>
<Scope>global</Scope>
<IOProtocol>ap_vld</IOProtocol>
<IOConfig></IOConfig>
<Dir>out</Dir>
<Bits>1</Bits>
<Attribute>control</Attribute>
</RtlPorts>
<RtlPorts>
<name>p_ZZ11network_topP13params_structP8ap_fixedILi22ELi17EL9ap_q_mode0EL9ap_o_mode0EL_17582</name>
<Object>p_ZZ11network_topP13params_structP8ap_fixedILi22ELi17EL9ap_q_mode0EL9ap_o_mode0EL_17582</Object>
<Type>pointer</Type>
<Scope>global</Scope>
<IOProtocol>ap_vld</IOProtocol>
<IOConfig></IOConfig>
<Dir>out</Dir>
<Bits>22</Bits>
<Attribute>data</Attribute>
</RtlPorts>
<RtlPorts>
<name>p_ZZ11network_topP13params_structP8ap_fixedILi22ELi17EL9ap_q_mode0EL9ap_o_mode0EL_17582_ap_vld</name>
<Object>p_ZZ11network_topP13params_structP8ap_fixedILi22ELi17EL9ap_q_mode0EL9ap_o_mode0EL_17582</Object>
<Type>pointer</Type>
<Scope>global</Scope>
<IOProtocol>ap_vld</IOProtocol>
<IOConfig></IOConfig>
<Dir>out</Dir>
<Bits>1</Bits>
<Attribute>control</Attribute>
</RtlPorts>
<RtlPorts>
<name>p_ZZ11network_topP13params_structP8ap_fixedILi22ELi17EL9ap_q_mode0EL9ap_o_mode0EL_17583</name>
<Object>p_ZZ11network_topP13params_structP8ap_fixedILi22ELi17EL9ap_q_mode0EL9ap_o_mode0EL_17583</Object>
<Type>pointer</Type>
<Scope>global</Scope>
<IOProtocol>ap_vld</IOProtocol>
<IOConfig></IOConfig>
<Dir>out</Dir>
<Bits>22</Bits>
<Attribute>data</Attribute>
</RtlPorts>
<RtlPorts>
<name>p_ZZ11network_topP13params_structP8ap_fixedILi22ELi17EL9ap_q_mode0EL9ap_o_mode0EL_17583_ap_vld</name>
<Object>p_ZZ11network_topP13params_structP8ap_fixedILi22ELi17EL9ap_q_mode0EL9ap_o_mode0EL_17583</Object>
<Type>pointer</Type>
<Scope>global</Scope>
<IOProtocol>ap_vld</IOProtocol>
<IOConfig></IOConfig>
<Dir>out</Dir>
<Bits>1</Bits>
<Attribute>control</Attribute>
</RtlPorts>
<RtlPorts>
<name>p_ZZ11network_topP13params_structP8ap_fixedILi22ELi17EL9ap_q_mode0EL9ap_o_mode0EL_17584</name>
<Object>p_ZZ11network_topP13params_structP8ap_fixedILi22ELi17EL9ap_q_mode0EL9ap_o_mode0EL_17584</Object>
<Type>pointer</Type>
<Scope>global</Scope>
<IOProtocol>ap_vld</IOProtocol>
<IOConfig></IOConfig>
<Dir>out</Dir>
<Bits>22</Bits>
<Attribute>data</Attribute>
</RtlPorts>
<RtlPorts>
<name>p_ZZ11network_topP13params_structP8ap_fixedILi22ELi17EL9ap_q_mode0EL9ap_o_mode0EL_17584_ap_vld</name>
<Object>p_ZZ11network_topP13params_structP8ap_fixedILi22ELi17EL9ap_q_mode0EL9ap_o_mode0EL_17584</Object>
<Type>pointer</Type>
<Scope>global</Scope>
<IOProtocol>ap_vld</IOProtocol>
<IOConfig></IOConfig>
<Dir>out</Dir>
<Bits>1</Bits>
<Attribute>control</Attribute>
</RtlPorts>
<RtlPorts>
<name>p_ZZ11network_topP13params_structP8ap_fixedILi22ELi17EL9ap_q_mode0EL9ap_o_mode0EL_17586</name>
<Object>p_ZZ11network_topP13params_structP8ap_fixedILi22ELi17EL9ap_q_mode0EL9ap_o_mode0EL_17586</Object>
<Type>pointer</Type>
<Scope>global</Scope>
<IOProtocol>ap_vld</IOProtocol>
<IOConfig></IOConfig>
<Dir>out</Dir>
<Bits>22</Bits>
<Attribute>data</Attribute>
</RtlPorts>
<RtlPorts>
<name>p_ZZ11network_topP13params_structP8ap_fixedILi22ELi17EL9ap_q_mode0EL9ap_o_mode0EL_17586_ap_vld</name>
<Object>p_ZZ11network_topP13params_structP8ap_fixedILi22ELi17EL9ap_q_mode0EL9ap_o_mode0EL_17586</Object>
<Type>pointer</Type>
<Scope>global</Scope>
<IOProtocol>ap_vld</IOProtocol>
<IOConfig></IOConfig>
<Dir>out</Dir>
<Bits>1</Bits>
<Attribute>control</Attribute>
</RtlPorts>
<RtlPorts>
<name>p_ZZ11network_topP13params_structP8ap_fixedILi22ELi17EL9ap_q_mode0EL9ap_o_mode0EL_17587</name>
<Object>p_ZZ11network_topP13params_structP8ap_fixedILi22ELi17EL9ap_q_mode0EL9ap_o_mode0EL_17587</Object>
<Type>pointer</Type>
<Scope>global</Scope>
<IOProtocol>ap_vld</IOProtocol>
<IOConfig></IOConfig>
<Dir>out</Dir>
<Bits>22</Bits>
<Attribute>data</Attribute>
</RtlPorts>
<RtlPorts>
<name>p_ZZ11network_topP13params_structP8ap_fixedILi22ELi17EL9ap_q_mode0EL9ap_o_mode0EL_17587_ap_vld</name>
<Object>p_ZZ11network_topP13params_structP8ap_fixedILi22ELi17EL9ap_q_mode0EL9ap_o_mode0EL_17587</Object>
<Type>pointer</Type>
<Scope>global</Scope>
<IOProtocol>ap_vld</IOProtocol>
<IOConfig></IOConfig>
<Dir>out</Dir>
<Bits>1</Bits>
<Attribute>control</Attribute>
</RtlPorts>
<RtlPorts>
<name>p_ZZ11network_topP13params_structP8ap_fixedILi22ELi17EL9ap_q_mode0EL9ap_o_mode0EL_17589</name>
<Object>p_ZZ11network_topP13params_structP8ap_fixedILi22ELi17EL9ap_q_mode0EL9ap_o_mode0EL_17589</Object>
<Type>pointer</Type>
<Scope>global</Scope>
<IOProtocol>ap_vld</IOProtocol>
<IOConfig></IOConfig>
<Dir>out</Dir>
<Bits>22</Bits>
<Attribute>data</Attribute>
</RtlPorts>
<RtlPorts>
<name>p_ZZ11network_topP13params_structP8ap_fixedILi22ELi17EL9ap_q_mode0EL9ap_o_mode0EL_17589_ap_vld</name>
<Object>p_ZZ11network_topP13params_structP8ap_fixedILi22ELi17EL9ap_q_mode0EL9ap_o_mode0EL_17589</Object>
<Type>pointer</Type>
<Scope>global</Scope>
<IOProtocol>ap_vld</IOProtocol>
<IOConfig></IOConfig>
<Dir>out</Dir>
<Bits>1</Bits>
<Attribute>control</Attribute>
</RtlPorts>
<RtlPorts>
<name>p_ZZ11network_topP13params_structP8ap_fixedILi22ELi17EL9ap_q_mode0EL9ap_o_mode0EL_17590</name>
<Object>p_ZZ11network_topP13params_structP8ap_fixedILi22ELi17EL9ap_q_mode0EL9ap_o_mode0EL_17590</Object>
<Type>pointer</Type>
<Scope>global</Scope>
<IOProtocol>ap_vld</IOProtocol>
<IOConfig></IOConfig>
<Dir>out</Dir>
<Bits>22</Bits>
<Attribute>data</Attribute>
</RtlPorts>
<RtlPorts>
<name>p_ZZ11network_topP13params_structP8ap_fixedILi22ELi17EL9ap_q_mode0EL9ap_o_mode0EL_17590_ap_vld</name>
<Object>p_ZZ11network_topP13params_structP8ap_fixedILi22ELi17EL9ap_q_mode0EL9ap_o_mode0EL_17590</Object>
<Type>pointer</Type>
<Scope>global</Scope>
<IOProtocol>ap_vld</IOProtocol>
<IOConfig></IOConfig>
<Dir>out</Dir>
<Bits>1</Bits>
<Attribute>control</Attribute>
</RtlPorts>
<RtlPorts>
<name>p_ZZ11network_topP13params_structP8ap_fixedILi22ELi17EL9ap_q_mode0EL9ap_o_mode0EL_17591</name>
<Object>p_ZZ11network_topP13params_structP8ap_fixedILi22ELi17EL9ap_q_mode0EL9ap_o_mode0EL_17591</Object>
<Type>pointer</Type>
<Scope>global</Scope>
<IOProtocol>ap_vld</IOProtocol>
<IOConfig></IOConfig>
<Dir>out</Dir>
<Bits>22</Bits>
<Attribute>data</Attribute>
</RtlPorts>
<RtlPorts>
<name>p_ZZ11network_topP13params_structP8ap_fixedILi22ELi17EL9ap_q_mode0EL9ap_o_mode0EL_17591_ap_vld</name>
<Object>p_ZZ11network_topP13params_structP8ap_fixedILi22ELi17EL9ap_q_mode0EL9ap_o_mode0EL_17591</Object>
<Type>pointer</Type>
<Scope>global</Scope>
<IOProtocol>ap_vld</IOProtocol>
<IOConfig></IOConfig>
<Dir>out</Dir>
<Bits>1</Bits>
<Attribute>control</Attribute>
</RtlPorts>
<RtlPorts>
<name>p_ZZ11network_topP13params_structP8ap_fixedILi22ELi17EL9ap_q_mode0EL9ap_o_mode0EL_17592</name>
<Object>p_ZZ11network_topP13params_structP8ap_fixedILi22ELi17EL9ap_q_mode0EL9ap_o_mode0EL_17592</Object>
<Type>pointer</Type>
<Scope>global</Scope>
<IOProtocol>ap_vld</IOProtocol>
<IOConfig></IOConfig>
<Dir>out</Dir>
<Bits>22</Bits>
<Attribute>data</Attribute>
</RtlPorts>
<RtlPorts>
<name>p_ZZ11network_topP13params_structP8ap_fixedILi22ELi17EL9ap_q_mode0EL9ap_o_mode0EL_17592_ap_vld</name>
<Object>p_ZZ11network_topP13params_structP8ap_fixedILi22ELi17EL9ap_q_mode0EL9ap_o_mode0EL_17592</Object>
<Type>pointer</Type>
<Scope>global</Scope>
<IOProtocol>ap_vld</IOProtocol>
<IOConfig></IOConfig>
<Dir>out</Dir>
<Bits>1</Bits>
<Attribute>control</Attribute>
</RtlPorts>
<RtlPorts>
<name>p_ZZ11network_topP13params_structP8ap_fixedILi22ELi17EL9ap_q_mode0EL9ap_o_mode0EL_17593</name>
<Object>p_ZZ11network_topP13params_structP8ap_fixedILi22ELi17EL9ap_q_mode0EL9ap_o_mode0EL_17593</Object>
<Type>pointer</Type>
<Scope>global</Scope>
<IOProtocol>ap_vld</IOProtocol>
<IOConfig></IOConfig>
<Dir>out</Dir>
<Bits>22</Bits>
<Attribute>data</Attribute>
</RtlPorts>
<RtlPorts>
<name>p_ZZ11network_topP13params_structP8ap_fixedILi22ELi17EL9ap_q_mode0EL9ap_o_mode0EL_17593_ap_vld</name>
<Object>p_ZZ11network_topP13params_structP8ap_fixedILi22ELi17EL9ap_q_mode0EL9ap_o_mode0EL_17593</Object>
<Type>pointer</Type>
<Scope>global</Scope>
<IOProtocol>ap_vld</IOProtocol>
<IOConfig></IOConfig>
<Dir>out</Dir>
<Bits>1</Bits>
<Attribute>control</Attribute>
</RtlPorts>
<RtlPorts>
<name>p_ZZ11network_topP13params_structP8ap_fixedILi22ELi17EL9ap_q_mode0EL9ap_o_mode0EL_17594</name>
<Object>p_ZZ11network_topP13params_structP8ap_fixedILi22ELi17EL9ap_q_mode0EL9ap_o_mode0EL_17594</Object>
<Type>pointer</Type>
<Scope>global</Scope>
<IOProtocol>ap_vld</IOProtocol>
<IOConfig></IOConfig>
<Dir>out</Dir>
<Bits>22</Bits>
<Attribute>data</Attribute>
</RtlPorts>
<RtlPorts>
<name>p_ZZ11network_topP13params_structP8ap_fixedILi22ELi17EL9ap_q_mode0EL9ap_o_mode0EL_17594_ap_vld</name>
<Object>p_ZZ11network_topP13params_structP8ap_fixedILi22ELi17EL9ap_q_mode0EL9ap_o_mode0EL_17594</Object>
<Type>pointer</Type>
<Scope>global</Scope>
<IOProtocol>ap_vld</IOProtocol>
<IOConfig></IOConfig>
<Dir>out</Dir>
<Bits>1</Bits>
<Attribute>control</Attribute>
</RtlPorts>
<RtlPorts>
<name>p_ZZ11network_topP13params_structP8ap_fixedILi22ELi17EL9ap_q_mode0EL9ap_o_mode0EL_17595</name>
<Object>p_ZZ11network_topP13params_structP8ap_fixedILi22ELi17EL9ap_q_mode0EL9ap_o_mode0EL_17595</Object>
<Type>pointer</Type>
<Scope>global</Scope>
<IOProtocol>ap_vld</IOProtocol>
<IOConfig></IOConfig>
<Dir>out</Dir>
<Bits>22</Bits>
<Attribute>data</Attribute>
</RtlPorts>
<RtlPorts>
<name>p_ZZ11network_topP13params_structP8ap_fixedILi22ELi17EL9ap_q_mode0EL9ap_o_mode0EL_17595_ap_vld</name>
<Object>p_ZZ11network_topP13params_structP8ap_fixedILi22ELi17EL9ap_q_mode0EL9ap_o_mode0EL_17595</Object>
<Type>pointer</Type>
<Scope>global</Scope>
<IOProtocol>ap_vld</IOProtocol>
<IOConfig></IOConfig>
<Dir>out</Dir>
<Bits>1</Bits>
<Attribute>control</Attribute>
</RtlPorts>
<RtlPorts>
<name>p_ZZ11network_topP13params_structP8ap_fixedILi22ELi17EL9ap_q_mode0EL9ap_o_mode0EL_17597</name>
<Object>p_ZZ11network_topP13params_structP8ap_fixedILi22ELi17EL9ap_q_mode0EL9ap_o_mode0EL_17597</Object>
<Type>pointer</Type>
<Scope>global</Scope>
<IOProtocol>ap_vld</IOProtocol>
<IOConfig></IOConfig>
<Dir>out</Dir>
<Bits>22</Bits>
<Attribute>data</Attribute>
</RtlPorts>
<RtlPorts>
<name>p_ZZ11network_topP13params_structP8ap_fixedILi22ELi17EL9ap_q_mode0EL9ap_o_mode0EL_17597_ap_vld</name>
<Object>p_ZZ11network_topP13params_structP8ap_fixedILi22ELi17EL9ap_q_mode0EL9ap_o_mode0EL_17597</Object>
<Type>pointer</Type>
<Scope>global</Scope>
<IOProtocol>ap_vld</IOProtocol>
<IOConfig></IOConfig>
<Dir>out</Dir>
<Bits>1</Bits>
<Attribute>control</Attribute>
</RtlPorts>
<RtlPorts>
<name>p_ZZ11network_topP13params_structP8ap_fixedILi22ELi17EL9ap_q_mode0EL9ap_o_mode0EL_17598</name>
<Object>p_ZZ11network_topP13params_structP8ap_fixedILi22ELi17EL9ap_q_mode0EL9ap_o_mode0EL_17598</Object>
<Type>pointer</Type>
<Scope>global</Scope>
<IOProtocol>ap_vld</IOProtocol>
<IOConfig></IOConfig>
<Dir>out</Dir>
<Bits>22</Bits>
<Attribute>data</Attribute>
</RtlPorts>
<RtlPorts>
<name>p_ZZ11network_topP13params_structP8ap_fixedILi22ELi17EL9ap_q_mode0EL9ap_o_mode0EL_17598_ap_vld</name>
<Object>p_ZZ11network_topP13params_structP8ap_fixedILi22ELi17EL9ap_q_mode0EL9ap_o_mode0EL_17598</Object>
<Type>pointer</Type>
<Scope>global</Scope>
<IOProtocol>ap_vld</IOProtocol>
<IOConfig></IOConfig>
<Dir>out</Dir>
<Bits>1</Bits>
<Attribute>control</Attribute>
</RtlPorts>
<RtlPorts>
<name>p_ZZ11network_topP13params_structP8ap_fixedILi22ELi17EL9ap_q_mode0EL9ap_o_mode0EL_17599</name>
<Object>p_ZZ11network_topP13params_structP8ap_fixedILi22ELi17EL9ap_q_mode0EL9ap_o_mode0EL_17599</Object>
<Type>pointer</Type>
<Scope>global</Scope>
<IOProtocol>ap_vld</IOProtocol>
<IOConfig></IOConfig>
<Dir>out</Dir>
<Bits>22</Bits>
<Attribute>data</Attribute>
</RtlPorts>
<RtlPorts>
<name>p_ZZ11network_topP13params_structP8ap_fixedILi22ELi17EL9ap_q_mode0EL9ap_o_mode0EL_17599_ap_vld</name>
<Object>p_ZZ11network_topP13params_structP8ap_fixedILi22ELi17EL9ap_q_mode0EL9ap_o_mode0EL_17599</Object>
<Type>pointer</Type>
<Scope>global</Scope>
<IOProtocol>ap_vld</IOProtocol>
<IOConfig></IOConfig>
<Dir>out</Dir>
<Bits>1</Bits>
<Attribute>control</Attribute>
</RtlPorts>
<RtlPorts>
<name>p_ZZ11network_topP13params_structP8ap_fixedILi22ELi17EL9ap_q_mode0EL9ap_o_mode0EL_17601</name>
<Object>p_ZZ11network_topP13params_structP8ap_fixedILi22ELi17EL9ap_q_mode0EL9ap_o_mode0EL_17601</Object>
<Type>pointer</Type>
<Scope>global</Scope>
<IOProtocol>ap_vld</IOProtocol>
<IOConfig></IOConfig>
<Dir>out</Dir>
<Bits>22</Bits>
<Attribute>data</Attribute>
</RtlPorts>
<RtlPorts>
<name>p_ZZ11network_topP13params_structP8ap_fixedILi22ELi17EL9ap_q_mode0EL9ap_o_mode0EL_17601_ap_vld</name>
<Object>p_ZZ11network_topP13params_structP8ap_fixedILi22ELi17EL9ap_q_mode0EL9ap_o_mode0EL_17601</Object>
<Type>pointer</Type>
<Scope>global</Scope>
<IOProtocol>ap_vld</IOProtocol>
<IOConfig></IOConfig>
<Dir>out</Dir>
<Bits>1</Bits>
<Attribute>control</Attribute>
</RtlPorts>
<RtlPorts>
<name>p_ZZ11network_topP13params_structP8ap_fixedILi22ELi17EL9ap_q_mode0EL9ap_o_mode0EL_17602</name>
<Object>p_ZZ11network_topP13params_structP8ap_fixedILi22ELi17EL9ap_q_mode0EL9ap_o_mode0EL_17602</Object>
<Type>pointer</Type>
<Scope>global</Scope>
<IOProtocol>ap_vld</IOProtocol>
<IOConfig></IOConfig>
<Dir>out</Dir>
<Bits>22</Bits>
<Attribute>data</Attribute>
</RtlPorts>
<RtlPorts>
<name>p_ZZ11network_topP13params_structP8ap_fixedILi22ELi17EL9ap_q_mode0EL9ap_o_mode0EL_17602_ap_vld</name>
<Object>p_ZZ11network_topP13params_structP8ap_fixedILi22ELi17EL9ap_q_mode0EL9ap_o_mode0EL_17602</Object>
<Type>pointer</Type>
<Scope>global</Scope>
<IOProtocol>ap_vld</IOProtocol>
<IOConfig></IOConfig>
<Dir>out</Dir>
<Bits>1</Bits>
<Attribute>control</Attribute>
</RtlPorts>
<RtlPorts>
<name>p_ZZ11network_topP13params_structP8ap_fixedILi22ELi17EL9ap_q_mode0EL9ap_o_mode0EL_17603</name>
<Object>p_ZZ11network_topP13params_structP8ap_fixedILi22ELi17EL9ap_q_mode0EL9ap_o_mode0EL_17603</Object>
<Type>pointer</Type>
<Scope>global</Scope>
<IOProtocol>ap_vld</IOProtocol>
<IOConfig></IOConfig>
<Dir>out</Dir>
<Bits>22</Bits>
<Attribute>data</Attribute>
</RtlPorts>
<RtlPorts>
<name>p_ZZ11network_topP13params_structP8ap_fixedILi22ELi17EL9ap_q_mode0EL9ap_o_mode0EL_17603_ap_vld</name>
<Object>p_ZZ11network_topP13params_structP8ap_fixedILi22ELi17EL9ap_q_mode0EL9ap_o_mode0EL_17603</Object>
<Type>pointer</Type>
<Scope>global</Scope>
<IOProtocol>ap_vld</IOProtocol>
<IOConfig></IOConfig>
<Dir>out</Dir>
<Bits>1</Bits>
<Attribute>control</Attribute>
</RtlPorts>
<RtlPorts>
<name>p_ZZ11network_topP13params_structP8ap_fixedILi22ELi17EL9ap_q_mode0EL9ap_o_mode0EL_17604</name>
<Object>p_ZZ11network_topP13params_structP8ap_fixedILi22ELi17EL9ap_q_mode0EL9ap_o_mode0EL_17604</Object>
<Type>pointer</Type>
<Scope>global</Scope>
<IOProtocol>ap_vld</IOProtocol>
<IOConfig></IOConfig>
<Dir>out</Dir>
<Bits>22</Bits>
<Attribute>data</Attribute>
</RtlPorts>
<RtlPorts>
<name>p_ZZ11network_topP13params_structP8ap_fixedILi22ELi17EL9ap_q_mode0EL9ap_o_mode0EL_17604_ap_vld</name>
<Object>p_ZZ11network_topP13params_structP8ap_fixedILi22ELi17EL9ap_q_mode0EL9ap_o_mode0EL_17604</Object>
<Type>pointer</Type>
<Scope>global</Scope>
<IOProtocol>ap_vld</IOProtocol>
<IOConfig></IOConfig>
<Dir>out</Dir>
<Bits>1</Bits>
<Attribute>control</Attribute>
</RtlPorts>
<RtlPorts>
<name>p_ZZ11network_topP13params_structP8ap_fixedILi22ELi17EL9ap_q_mode0EL9ap_o_mode0EL_17605</name>
<Object>p_ZZ11network_topP13params_structP8ap_fixedILi22ELi17EL9ap_q_mode0EL9ap_o_mode0EL_17605</Object>
<Type>pointer</Type>
<Scope>global</Scope>
<IOProtocol>ap_vld</IOProtocol>
<IOConfig></IOConfig>
<Dir>out</Dir>
<Bits>22</Bits>
<Attribute>data</Attribute>
</RtlPorts>
<RtlPorts>
<name>p_ZZ11network_topP13params_structP8ap_fixedILi22ELi17EL9ap_q_mode0EL9ap_o_mode0EL_17605_ap_vld</name>
<Object>p_ZZ11network_topP13params_structP8ap_fixedILi22ELi17EL9ap_q_mode0EL9ap_o_mode0EL_17605</Object>
<Type>pointer</Type>
<Scope>global</Scope>
<IOProtocol>ap_vld</IOProtocol>
<IOConfig></IOConfig>
<Dir>out</Dir>
<Bits>1</Bits>
<Attribute>control</Attribute>
</RtlPorts>
<RtlPorts>
<name>p_ZZ11network_topP13params_structP8ap_fixedILi22ELi17EL9ap_q_mode0EL9ap_o_mode0EL_17606</name>
<Object>p_ZZ11network_topP13params_structP8ap_fixedILi22ELi17EL9ap_q_mode0EL9ap_o_mode0EL_17606</Object>
<Type>pointer</Type>
<Scope>global</Scope>
<IOProtocol>ap_vld</IOProtocol>
<IOConfig></IOConfig>
<Dir>out</Dir>
<Bits>22</Bits>
<Attribute>data</Attribute>
</RtlPorts>
<RtlPorts>
<name>p_ZZ11network_topP13params_structP8ap_fixedILi22ELi17EL9ap_q_mode0EL9ap_o_mode0EL_17606_ap_vld</name>
<Object>p_ZZ11network_topP13params_structP8ap_fixedILi22ELi17EL9ap_q_mode0EL9ap_o_mode0EL_17606</Object>
<Type>pointer</Type>
<Scope>global</Scope>
<IOProtocol>ap_vld</IOProtocol>
<IOConfig></IOConfig>
<Dir>out</Dir>
<Bits>1</Bits>
<Attribute>control</Attribute>
</RtlPorts>
<RtlPorts>
<name>p_ZZ11network_topP13params_structP8ap_fixedILi22ELi17EL9ap_q_mode0EL9ap_o_mode0EL_17608</name>
<Object>p_ZZ11network_topP13params_structP8ap_fixedILi22ELi17EL9ap_q_mode0EL9ap_o_mode0EL_17608</Object>
<Type>pointer</Type>
<Scope>global</Scope>
<IOProtocol>ap_vld</IOProtocol>
<IOConfig></IOConfig>
<Dir>out</Dir>
<Bits>22</Bits>
<Attribute>data</Attribute>
</RtlPorts>
<RtlPorts>
<name>p_ZZ11network_topP13params_structP8ap_fixedILi22ELi17EL9ap_q_mode0EL9ap_o_mode0EL_17608_ap_vld</name>
<Object>p_ZZ11network_topP13params_structP8ap_fixedILi22ELi17EL9ap_q_mode0EL9ap_o_mode0EL_17608</Object>
<Type>pointer</Type>
<Scope>global</Scope>
<IOProtocol>ap_vld</IOProtocol>
<IOConfig></IOConfig>
<Dir>out</Dir>
<Bits>1</Bits>
<Attribute>control</Attribute>
</RtlPorts>
<RtlPorts>
<name>p_ZZ11network_topP13params_structP8ap_fixedILi22ELi17EL9ap_q_mode0EL9ap_o_mode0EL_17609</name>
<Object>p_ZZ11network_topP13params_structP8ap_fixedILi22ELi17EL9ap_q_mode0EL9ap_o_mode0EL_17609</Object>
<Type>pointer</Type>
<Scope>global</Scope>
<IOProtocol>ap_vld</IOProtocol>
<IOConfig></IOConfig>
<Dir>out</Dir>
<Bits>22</Bits>
<Attribute>data</Attribute>
</RtlPorts>
<RtlPorts>
<name>p_ZZ11network_topP13params_structP8ap_fixedILi22ELi17EL9ap_q_mode0EL9ap_o_mode0EL_17609_ap_vld</name>
<Object>p_ZZ11network_topP13params_structP8ap_fixedILi22ELi17EL9ap_q_mode0EL9ap_o_mode0EL_17609</Object>
<Type>pointer</Type>
<Scope>global</Scope>
<IOProtocol>ap_vld</IOProtocol>
<IOConfig></IOConfig>
<Dir>out</Dir>
<Bits>1</Bits>
<Attribute>control</Attribute>
</RtlPorts>
<RtlPorts>
<name>p_ZZ11network_topP13params_structP8ap_fixedILi22ELi17EL9ap_q_mode0EL9ap_o_mode0EL_17610</name>
<Object>p_ZZ11network_topP13params_structP8ap_fixedILi22ELi17EL9ap_q_mode0EL9ap_o_mode0EL_17610</Object>
<Type>pointer</Type>
<Scope>global</Scope>
<IOProtocol>ap_vld</IOProtocol>
<IOConfig></IOConfig>
<Dir>out</Dir>
<Bits>22</Bits>
<Attribute>data</Attribute>
</RtlPorts>
<RtlPorts>
<name>p_ZZ11network_topP13params_structP8ap_fixedILi22ELi17EL9ap_q_mode0EL9ap_o_mode0EL_17610_ap_vld</name>
<Object>p_ZZ11network_topP13params_structP8ap_fixedILi22ELi17EL9ap_q_mode0EL9ap_o_mode0EL_17610</Object>
<Type>pointer</Type>
<Scope>global</Scope>
<IOProtocol>ap_vld</IOProtocol>
<IOConfig></IOConfig>
<Dir>out</Dir>
<Bits>1</Bits>
<Attribute>control</Attribute>
</RtlPorts>
<RtlPorts>
<name>p_ZZ11network_topP13params_structP8ap_fixedILi22ELi17EL9ap_q_mode0EL9ap_o_mode0EL_17611</name>
<Object>p_ZZ11network_topP13params_structP8ap_fixedILi22ELi17EL9ap_q_mode0EL9ap_o_mode0EL_17611</Object>
<Type>pointer</Type>
<Scope>global</Scope>
<IOProtocol>ap_vld</IOProtocol>
<IOConfig></IOConfig>
<Dir>out</Dir>
<Bits>22</Bits>
<Attribute>data</Attribute>
</RtlPorts>
<RtlPorts>
<name>p_ZZ11network_topP13params_structP8ap_fixedILi22ELi17EL9ap_q_mode0EL9ap_o_mode0EL_17611_ap_vld</name>
<Object>p_ZZ11network_topP13params_structP8ap_fixedILi22ELi17EL9ap_q_mode0EL9ap_o_mode0EL_17611</Object>
<Type>pointer</Type>
<Scope>global</Scope>
<IOProtocol>ap_vld</IOProtocol>
<IOConfig></IOConfig>
<Dir>out</Dir>
<Bits>1</Bits>
<Attribute>control</Attribute>
</RtlPorts>
<RtlPorts>
<name>p_ZZ11network_topP13params_structP8ap_fixedILi22ELi17EL9ap_q_mode0EL9ap_o_mode0EL_17613</name>
<Object>p_ZZ11network_topP13params_structP8ap_fixedILi22ELi17EL9ap_q_mode0EL9ap_o_mode0EL_17613</Object>
<Type>pointer</Type>
<Scope>global</Scope>
<IOProtocol>ap_vld</IOProtocol>
<IOConfig></IOConfig>
<Dir>out</Dir>
<Bits>22</Bits>
<Attribute>data</Attribute>
</RtlPorts>
<RtlPorts>
<name>p_ZZ11network_topP13params_structP8ap_fixedILi22ELi17EL9ap_q_mode0EL9ap_o_mode0EL_17613_ap_vld</name>
<Object>p_ZZ11network_topP13params_structP8ap_fixedILi22ELi17EL9ap_q_mode0EL9ap_o_mode0EL_17613</Object>
<Type>pointer</Type>
<Scope>global</Scope>
<IOProtocol>ap_vld</IOProtocol>
<IOConfig></IOConfig>
<Dir>out</Dir>
<Bits>1</Bits>
<Attribute>control</Attribute>
</RtlPorts>
<RtlPorts>
<name>p_ZZ11network_topP13params_structP8ap_fixedILi22ELi17EL9ap_q_mode0EL9ap_o_mode0EL_17614</name>
<Object>p_ZZ11network_topP13params_structP8ap_fixedILi22ELi17EL9ap_q_mode0EL9ap_o_mode0EL_17614</Object>
<Type>pointer</Type>
<Scope>global</Scope>
<IOProtocol>ap_vld</IOProtocol>
<IOConfig></IOConfig>
<Dir>out</Dir>
<Bits>22</Bits>
<Attribute>data</Attribute>
</RtlPorts>
<RtlPorts>
<name>p_ZZ11network_topP13params_structP8ap_fixedILi22ELi17EL9ap_q_mode0EL9ap_o_mode0EL_17614_ap_vld</name>
<Object>p_ZZ11network_topP13params_structP8ap_fixedILi22ELi17EL9ap_q_mode0EL9ap_o_mode0EL_17614</Object>
<Type>pointer</Type>
<Scope>global</Scope>
<IOProtocol>ap_vld</IOProtocol>
<IOConfig></IOConfig>
<Dir>out</Dir>
<Bits>1</Bits>
<Attribute>control</Attribute>
</RtlPorts>
<RtlPorts>
<name>p_ZZ11network_topP13params_structP8ap_fixedILi22ELi17EL9ap_q_mode0EL9ap_o_mode0EL_17615</name>
<Object>p_ZZ11network_topP13params_structP8ap_fixedILi22ELi17EL9ap_q_mode0EL9ap_o_mode0EL_17615</Object>
<Type>pointer</Type>
<Scope>global</Scope>
<IOProtocol>ap_vld</IOProtocol>
<IOConfig></IOConfig>
<Dir>out</Dir>
<Bits>22</Bits>
<Attribute>data</Attribute>
</RtlPorts>
<RtlPorts>
<name>p_ZZ11network_topP13params_structP8ap_fixedILi22ELi17EL9ap_q_mode0EL9ap_o_mode0EL_17615_ap_vld</name>
<Object>p_ZZ11network_topP13params_structP8ap_fixedILi22ELi17EL9ap_q_mode0EL9ap_o_mode0EL_17615</Object>
<Type>pointer</Type>
<Scope>global</Scope>
<IOProtocol>ap_vld</IOProtocol>
<IOConfig></IOConfig>
<Dir>out</Dir>
<Bits>1</Bits>
<Attribute>control</Attribute>
</RtlPorts>
<RtlPorts>
<name>p_ZZ11network_topP13params_structP8ap_fixedILi22ELi17EL9ap_q_mode0EL9ap_o_mode0EL_17616</name>
<Object>p_ZZ11network_topP13params_structP8ap_fixedILi22ELi17EL9ap_q_mode0EL9ap_o_mode0EL_17616</Object>
<Type>pointer</Type>
<Scope>global</Scope>
<IOProtocol>ap_vld</IOProtocol>
<IOConfig></IOConfig>
<Dir>out</Dir>
<Bits>22</Bits>
<Attribute>data</Attribute>
</RtlPorts>
<RtlPorts>
<name>p_ZZ11network_topP13params_structP8ap_fixedILi22ELi17EL9ap_q_mode0EL9ap_o_mode0EL_17616_ap_vld</name>
<Object>p_ZZ11network_topP13params_structP8ap_fixedILi22ELi17EL9ap_q_mode0EL9ap_o_mode0EL_17616</Object>
<Type>pointer</Type>
<Scope>global</Scope>
<IOProtocol>ap_vld</IOProtocol>
<IOConfig></IOConfig>
<Dir>out</Dir>
<Bits>1</Bits>
<Attribute>control</Attribute>
</RtlPorts>
<RtlPorts>
<name>p_ZZ11network_topP13params_structP8ap_fixedILi22ELi17EL9ap_q_mode0EL9ap_o_mode0EL_17617</name>
<Object>p_ZZ11network_topP13params_structP8ap_fixedILi22ELi17EL9ap_q_mode0EL9ap_o_mode0EL_17617</Object>
<Type>pointer</Type>
<Scope>global</Scope>
<IOProtocol>ap_vld</IOProtocol>
<IOConfig></IOConfig>
<Dir>out</Dir>
<Bits>22</Bits>
<Attribute>data</Attribute>
</RtlPorts>
<RtlPorts>
<name>p_ZZ11network_topP13params_structP8ap_fixedILi22ELi17EL9ap_q_mode0EL9ap_o_mode0EL_17617_ap_vld</name>
<Object>p_ZZ11network_topP13params_structP8ap_fixedILi22ELi17EL9ap_q_mode0EL9ap_o_mode0EL_17617</Object>
<Type>pointer</Type>
<Scope>global</Scope>
<IOProtocol>ap_vld</IOProtocol>
<IOConfig></IOConfig>
<Dir>out</Dir>
<Bits>1</Bits>
<Attribute>control</Attribute>
</RtlPorts>
<RtlPorts>
<name>p_ZZ11network_topP13params_structP8ap_fixedILi22ELi17EL9ap_q_mode0EL9ap_o_mode0EL_17619</name>
<Object>p_ZZ11network_topP13params_structP8ap_fixedILi22ELi17EL9ap_q_mode0EL9ap_o_mode0EL_17619</Object>
<Type>pointer</Type>
<Scope>global</Scope>
<IOProtocol>ap_vld</IOProtocol>
<IOConfig></IOConfig>
<Dir>out</Dir>
<Bits>22</Bits>
<Attribute>data</Attribute>
</RtlPorts>
<RtlPorts>
<name>p_ZZ11network_topP13params_structP8ap_fixedILi22ELi17EL9ap_q_mode0EL9ap_o_mode0EL_17619_ap_vld</name>
<Object>p_ZZ11network_topP13params_structP8ap_fixedILi22ELi17EL9ap_q_mode0EL9ap_o_mode0EL_17619</Object>
<Type>pointer</Type>
<Scope>global</Scope>
<IOProtocol>ap_vld</IOProtocol>
<IOConfig></IOConfig>
<Dir>out</Dir>
<Bits>1</Bits>
<Attribute>control</Attribute>
</RtlPorts>
<RtlPorts>
<name>p_ZZ11network_topP13params_structP8ap_fixedILi22ELi17EL9ap_q_mode0EL9ap_o_mode0EL_17620</name>
<Object>p_ZZ11network_topP13params_structP8ap_fixedILi22ELi17EL9ap_q_mode0EL9ap_o_mode0EL_17620</Object>
<Type>pointer</Type>
<Scope>global</Scope>
<IOProtocol>ap_vld</IOProtocol>
<IOConfig></IOConfig>
<Dir>out</Dir>
<Bits>22</Bits>
<Attribute>data</Attribute>
</RtlPorts>
<RtlPorts>
<name>p_ZZ11network_topP13params_structP8ap_fixedILi22ELi17EL9ap_q_mode0EL9ap_o_mode0EL_17620_ap_vld</name>
<Object>p_ZZ11network_topP13params_structP8ap_fixedILi22ELi17EL9ap_q_mode0EL9ap_o_mode0EL_17620</Object>
<Type>pointer</Type>
<Scope>global</Scope>
<IOProtocol>ap_vld</IOProtocol>
<IOConfig></IOConfig>
<Dir>out</Dir>
<Bits>1</Bits>
<Attribute>control</Attribute>
</RtlPorts>
<RtlPorts>
<name>p_ZZ11network_topP13params_structP8ap_fixedILi22ELi17EL9ap_q_mode0EL9ap_o_mode0EL_17621</name>
<Object>p_ZZ11network_topP13params_structP8ap_fixedILi22ELi17EL9ap_q_mode0EL9ap_o_mode0EL_17621</Object>
<Type>pointer</Type>
<Scope>global</Scope>
<IOProtocol>ap_vld</IOProtocol>
<IOConfig></IOConfig>
<Dir>out</Dir>
<Bits>22</Bits>
<Attribute>data</Attribute>
</RtlPorts>
<RtlPorts>
<name>p_ZZ11network_topP13params_structP8ap_fixedILi22ELi17EL9ap_q_mode0EL9ap_o_mode0EL_17621_ap_vld</name>
<Object>p_ZZ11network_topP13params_structP8ap_fixedILi22ELi17EL9ap_q_mode0EL9ap_o_mode0EL_17621</Object>
<Type>pointer</Type>
<Scope>global</Scope>
<IOProtocol>ap_vld</IOProtocol>
<IOConfig></IOConfig>
<Dir>out</Dir>
<Bits>1</Bits>
<Attribute>control</Attribute>
</RtlPorts>
<RtlPorts>
<name>p_ZZ11network_topP13params_structP8ap_fixedILi22ELi17EL9ap_q_mode0EL9ap_o_mode0EL_17622</name>
<Object>p_ZZ11network_topP13params_structP8ap_fixedILi22ELi17EL9ap_q_mode0EL9ap_o_mode0EL_17622</Object>
<Type>pointer</Type>
<Scope>global</Scope>
<IOProtocol>ap_vld</IOProtocol>
<IOConfig></IOConfig>
<Dir>out</Dir>
<Bits>22</Bits>
<Attribute>data</Attribute>
</RtlPorts>
<RtlPorts>
<name>p_ZZ11network_topP13params_structP8ap_fixedILi22ELi17EL9ap_q_mode0EL9ap_o_mode0EL_17622_ap_vld</name>
<Object>p_ZZ11network_topP13params_structP8ap_fixedILi22ELi17EL9ap_q_mode0EL9ap_o_mode0EL_17622</Object>
<Type>pointer</Type>
<Scope>global</Scope>
<IOProtocol>ap_vld</IOProtocol>
<IOConfig></IOConfig>
<Dir>out</Dir>
<Bits>1</Bits>
<Attribute>control</Attribute>
</RtlPorts>
<RtlPorts>
<name>p_ZZ11network_topP13params_structP8ap_fixedILi22ELi17EL9ap_q_mode0EL9ap_o_mode0EL_17623</name>
<Object>p_ZZ11network_topP13params_structP8ap_fixedILi22ELi17EL9ap_q_mode0EL9ap_o_mode0EL_17623</Object>
<Type>pointer</Type>
<Scope>global</Scope>
<IOProtocol>ap_vld</IOProtocol>
<IOConfig></IOConfig>
<Dir>out</Dir>
<Bits>22</Bits>
<Attribute>data</Attribute>
</RtlPorts>
<RtlPorts>
<name>p_ZZ11network_topP13params_structP8ap_fixedILi22ELi17EL9ap_q_mode0EL9ap_o_mode0EL_17623_ap_vld</name>
<Object>p_ZZ11network_topP13params_structP8ap_fixedILi22ELi17EL9ap_q_mode0EL9ap_o_mode0EL_17623</Object>
<Type>pointer</Type>
<Scope>global</Scope>
<IOProtocol>ap_vld</IOProtocol>
<IOConfig></IOConfig>
<Dir>out</Dir>
<Bits>1</Bits>
<Attribute>control</Attribute>
</RtlPorts>
<RtlPorts>
<name>p_ZZ11network_topP13params_structP8ap_fixedILi22ELi17EL9ap_q_mode0EL9ap_o_mode0EL_17625</name>
<Object>p_ZZ11network_topP13params_structP8ap_fixedILi22ELi17EL9ap_q_mode0EL9ap_o_mode0EL_17625</Object>
<Type>pointer</Type>
<Scope>global</Scope>
<IOProtocol>ap_vld</IOProtocol>
<IOConfig></IOConfig>
<Dir>out</Dir>
<Bits>22</Bits>
<Attribute>data</Attribute>
</RtlPorts>
<RtlPorts>
<name>p_ZZ11network_topP13params_structP8ap_fixedILi22ELi17EL9ap_q_mode0EL9ap_o_mode0EL_17625_ap_vld</name>
<Object>p_ZZ11network_topP13params_structP8ap_fixedILi22ELi17EL9ap_q_mode0EL9ap_o_mode0EL_17625</Object>
<Type>pointer</Type>
<Scope>global</Scope>
<IOProtocol>ap_vld</IOProtocol>
<IOConfig></IOConfig>
<Dir>out</Dir>
<Bits>1</Bits>
<Attribute>control</Attribute>
</RtlPorts>
<RtlPorts>
<name>p_ZZ11network_topP13params_structP8ap_fixedILi22ELi17EL9ap_q_mode0EL9ap_o_mode0EL_17626</name>
<Object>p_ZZ11network_topP13params_structP8ap_fixedILi22ELi17EL9ap_q_mode0EL9ap_o_mode0EL_17626</Object>
<Type>pointer</Type>
<Scope>global</Scope>
<IOProtocol>ap_vld</IOProtocol>
<IOConfig></IOConfig>
<Dir>out</Dir>
<Bits>22</Bits>
<Attribute>data</Attribute>
</RtlPorts>
<RtlPorts>
<name>p_ZZ11network_topP13params_structP8ap_fixedILi22ELi17EL9ap_q_mode0EL9ap_o_mode0EL_17626_ap_vld</name>
<Object>p_ZZ11network_topP13params_structP8ap_fixedILi22ELi17EL9ap_q_mode0EL9ap_o_mode0EL_17626</Object>
<Type>pointer</Type>
<Scope>global</Scope>
<IOProtocol>ap_vld</IOProtocol>
<IOConfig></IOConfig>
<Dir>out</Dir>
<Bits>1</Bits>
<Attribute>control</Attribute>
</RtlPorts>
<RtlPorts>
<name>p_ZZ11network_topP13params_structP8ap_fixedILi22ELi17EL9ap_q_mode0EL9ap_o_mode0EL_17627</name>
<Object>p_ZZ11network_topP13params_structP8ap_fixedILi22ELi17EL9ap_q_mode0EL9ap_o_mode0EL_17627</Object>
<Type>pointer</Type>
<Scope>global</Scope>
<IOProtocol>ap_vld</IOProtocol>
<IOConfig></IOConfig>
<Dir>out</Dir>
<Bits>22</Bits>
<Attribute>data</Attribute>
</RtlPorts>
<RtlPorts>
<name>p_ZZ11network_topP13params_structP8ap_fixedILi22ELi17EL9ap_q_mode0EL9ap_o_mode0EL_17627_ap_vld</name>
<Object>p_ZZ11network_topP13params_structP8ap_fixedILi22ELi17EL9ap_q_mode0EL9ap_o_mode0EL_17627</Object>
<Type>pointer</Type>
<Scope>global</Scope>
<IOProtocol>ap_vld</IOProtocol>
<IOConfig></IOConfig>
<Dir>out</Dir>
<Bits>1</Bits>
<Attribute>control</Attribute>
</RtlPorts>
<RtlPorts>
<name>p_ZZ11network_topP13params_structP8ap_fixedILi22ELi17EL9ap_q_mode0EL9ap_o_mode0EL_17628</name>
<Object>p_ZZ11network_topP13params_structP8ap_fixedILi22ELi17EL9ap_q_mode0EL9ap_o_mode0EL_17628</Object>
<Type>pointer</Type>
<Scope>global</Scope>
<IOProtocol>ap_vld</IOProtocol>
<IOConfig></IOConfig>
<Dir>out</Dir>
<Bits>22</Bits>
<Attribute>data</Attribute>
</RtlPorts>
<RtlPorts>
<name>p_ZZ11network_topP13params_structP8ap_fixedILi22ELi17EL9ap_q_mode0EL9ap_o_mode0EL_17628_ap_vld</name>
<Object>p_ZZ11network_topP13params_structP8ap_fixedILi22ELi17EL9ap_q_mode0EL9ap_o_mode0EL_17628</Object>
<Type>pointer</Type>
<Scope>global</Scope>
<IOProtocol>ap_vld</IOProtocol>
<IOConfig></IOConfig>
<Dir>out</Dir>
<Bits>1</Bits>
<Attribute>control</Attribute>
</RtlPorts>
<RtlPorts>
<name>p_ZZ11network_topP13params_structP8ap_fixedILi22ELi17EL9ap_q_mode0EL9ap_o_mode0EL_17630</name>
<Object>p_ZZ11network_topP13params_structP8ap_fixedILi22ELi17EL9ap_q_mode0EL9ap_o_mode0EL_17630</Object>
<Type>pointer</Type>
<Scope>global</Scope>
<IOProtocol>ap_vld</IOProtocol>
<IOConfig></IOConfig>
<Dir>out</Dir>
<Bits>22</Bits>
<Attribute>data</Attribute>
</RtlPorts>
<RtlPorts>
<name>p_ZZ11network_topP13params_structP8ap_fixedILi22ELi17EL9ap_q_mode0EL9ap_o_mode0EL_17630_ap_vld</name>
<Object>p_ZZ11network_topP13params_structP8ap_fixedILi22ELi17EL9ap_q_mode0EL9ap_o_mode0EL_17630</Object>
<Type>pointer</Type>
<Scope>global</Scope>
<IOProtocol>ap_vld</IOProtocol>
<IOConfig></IOConfig>
<Dir>out</Dir>
<Bits>1</Bits>
<Attribute>control</Attribute>
</RtlPorts>
<RtlPorts>
<name>p_ZZ11network_topP13params_structP8ap_fixedILi22ELi17EL9ap_q_mode0EL9ap_o_mode0EL_17631</name>
<Object>p_ZZ11network_topP13params_structP8ap_fixedILi22ELi17EL9ap_q_mode0EL9ap_o_mode0EL_17631</Object>
<Type>pointer</Type>
<Scope>global</Scope>
<IOProtocol>ap_vld</IOProtocol>
<IOConfig></IOConfig>
<Dir>out</Dir>
<Bits>22</Bits>
<Attribute>data</Attribute>
</RtlPorts>
<RtlPorts>
<name>p_ZZ11network_topP13params_structP8ap_fixedILi22ELi17EL9ap_q_mode0EL9ap_o_mode0EL_17631_ap_vld</name>
<Object>p_ZZ11network_topP13params_structP8ap_fixedILi22ELi17EL9ap_q_mode0EL9ap_o_mode0EL_17631</Object>
<Type>pointer</Type>
<Scope>global</Scope>
<IOProtocol>ap_vld</IOProtocol>
<IOConfig></IOConfig>
<Dir>out</Dir>
<Bits>1</Bits>
<Attribute>control</Attribute>
</RtlPorts>
<RtlPorts>
<name>p_ZZ11network_topP13params_structP8ap_fixedILi22ELi17EL9ap_q_mode0EL9ap_o_mode0EL_17632</name>
<Object>p_ZZ11network_topP13params_structP8ap_fixedILi22ELi17EL9ap_q_mode0EL9ap_o_mode0EL_17632</Object>
<Type>pointer</Type>
<Scope>global</Scope>
<IOProtocol>ap_vld</IOProtocol>
<IOConfig></IOConfig>
<Dir>out</Dir>
<Bits>22</Bits>
<Attribute>data</Attribute>
</RtlPorts>
<RtlPorts>
<name>p_ZZ11network_topP13params_structP8ap_fixedILi22ELi17EL9ap_q_mode0EL9ap_o_mode0EL_17632_ap_vld</name>
<Object>p_ZZ11network_topP13params_structP8ap_fixedILi22ELi17EL9ap_q_mode0EL9ap_o_mode0EL_17632</Object>
<Type>pointer</Type>
<Scope>global</Scope>
<IOProtocol>ap_vld</IOProtocol>
<IOConfig></IOConfig>
<Dir>out</Dir>
<Bits>1</Bits>
<Attribute>control</Attribute>
</RtlPorts>
<RtlPorts>
<name>p_ZZ11network_topP13params_structP8ap_fixedILi22ELi17EL9ap_q_mode0EL9ap_o_mode0EL_17633</name>
<Object>p_ZZ11network_topP13params_structP8ap_fixedILi22ELi17EL9ap_q_mode0EL9ap_o_mode0EL_17633</Object>
<Type>pointer</Type>
<Scope>global</Scope>
<IOProtocol>ap_vld</IOProtocol>
<IOConfig></IOConfig>
<Dir>out</Dir>
<Bits>22</Bits>
<Attribute>data</Attribute>
</RtlPorts>
<RtlPorts>
<name>p_ZZ11network_topP13params_structP8ap_fixedILi22ELi17EL9ap_q_mode0EL9ap_o_mode0EL_17633_ap_vld</name>
<Object>p_ZZ11network_topP13params_structP8ap_fixedILi22ELi17EL9ap_q_mode0EL9ap_o_mode0EL_17633</Object>
<Type>pointer</Type>
<Scope>global</Scope>
<IOProtocol>ap_vld</IOProtocol>
<IOConfig></IOConfig>
<Dir>out</Dir>
<Bits>1</Bits>
<Attribute>control</Attribute>
</RtlPorts>
<RtlPorts>
<name>p_ZZ11network_topP13params_structP8ap_fixedILi22ELi17EL9ap_q_mode0EL9ap_o_mode0EL_17634</name>
<Object>p_ZZ11network_topP13params_structP8ap_fixedILi22ELi17EL9ap_q_mode0EL9ap_o_mode0EL_17634</Object>
<Type>pointer</Type>
<Scope>global</Scope>
<IOProtocol>ap_vld</IOProtocol>
<IOConfig></IOConfig>
<Dir>out</Dir>
<Bits>22</Bits>
<Attribute>data</Attribute>
</RtlPorts>
<RtlPorts>
<name>p_ZZ11network_topP13params_structP8ap_fixedILi22ELi17EL9ap_q_mode0EL9ap_o_mode0EL_17634_ap_vld</name>
<Object>p_ZZ11network_topP13params_structP8ap_fixedILi22ELi17EL9ap_q_mode0EL9ap_o_mode0EL_17634</Object>
<Type>pointer</Type>
<Scope>global</Scope>
<IOProtocol>ap_vld</IOProtocol>
<IOConfig></IOConfig>
<Dir>out</Dir>
<Bits>1</Bits>
<Attribute>control</Attribute>
</RtlPorts>
<RtlPorts>
<name>p_ZZ11network_topP13params_structP8ap_fixedILi22ELi17EL9ap_q_mode0EL9ap_o_mode0EL_17635</name>
<Object>p_ZZ11network_topP13params_structP8ap_fixedILi22ELi17EL9ap_q_mode0EL9ap_o_mode0EL_17635</Object>
<Type>pointer</Type>
<Scope>global</Scope>
<IOProtocol>ap_vld</IOProtocol>
<IOConfig></IOConfig>
<Dir>out</Dir>
<Bits>22</Bits>
<Attribute>data</Attribute>
</RtlPorts>
<RtlPorts>
<name>p_ZZ11network_topP13params_structP8ap_fixedILi22ELi17EL9ap_q_mode0EL9ap_o_mode0EL_17635_ap_vld</name>
<Object>p_ZZ11network_topP13params_structP8ap_fixedILi22ELi17EL9ap_q_mode0EL9ap_o_mode0EL_17635</Object>
<Type>pointer</Type>
<Scope>global</Scope>
<IOProtocol>ap_vld</IOProtocol>
<IOConfig></IOConfig>
<Dir>out</Dir>
<Bits>1</Bits>
<Attribute>control</Attribute>
</RtlPorts>
<RtlPorts>
<name>p_ZZ11network_topP13params_structP8ap_fixedILi22ELi17EL9ap_q_mode0EL9ap_o_mode0EL_17637</name>
<Object>p_ZZ11network_topP13params_structP8ap_fixedILi22ELi17EL9ap_q_mode0EL9ap_o_mode0EL_17637</Object>
<Type>pointer</Type>
<Scope>global</Scope>
<IOProtocol>ap_vld</IOProtocol>
<IOConfig></IOConfig>
<Dir>out</Dir>
<Bits>22</Bits>
<Attribute>data</Attribute>
</RtlPorts>
<RtlPorts>
<name>p_ZZ11network_topP13params_structP8ap_fixedILi22ELi17EL9ap_q_mode0EL9ap_o_mode0EL_17637_ap_vld</name>
<Object>p_ZZ11network_topP13params_structP8ap_fixedILi22ELi17EL9ap_q_mode0EL9ap_o_mode0EL_17637</Object>
<Type>pointer</Type>
<Scope>global</Scope>
<IOProtocol>ap_vld</IOProtocol>
<IOConfig></IOConfig>
<Dir>out</Dir>
<Bits>1</Bits>
<Attribute>control</Attribute>
</RtlPorts>
<RtlPorts>
<name>p_ZZ11network_topP13params_structP8ap_fixedILi22ELi17EL9ap_q_mode0EL9ap_o_mode0EL_17638</name>
<Object>p_ZZ11network_topP13params_structP8ap_fixedILi22ELi17EL9ap_q_mode0EL9ap_o_mode0EL_17638</Object>
<Type>pointer</Type>
<Scope>global</Scope>
<IOProtocol>ap_vld</IOProtocol>
<IOConfig></IOConfig>
<Dir>out</Dir>
<Bits>22</Bits>
<Attribute>data</Attribute>
</RtlPorts>
<RtlPorts>
<name>p_ZZ11network_topP13params_structP8ap_fixedILi22ELi17EL9ap_q_mode0EL9ap_o_mode0EL_17638_ap_vld</name>
<Object>p_ZZ11network_topP13params_structP8ap_fixedILi22ELi17EL9ap_q_mode0EL9ap_o_mode0EL_17638</Object>
<Type>pointer</Type>
<Scope>global</Scope>
<IOProtocol>ap_vld</IOProtocol>
<IOConfig></IOConfig>
<Dir>out</Dir>
<Bits>1</Bits>
<Attribute>control</Attribute>
</RtlPorts>
<RtlPorts>
<name>p_ZZ11network_topP13params_structP8ap_fixedILi22ELi17EL9ap_q_mode0EL9ap_o_mode0EL_17639</name>
<Object>p_ZZ11network_topP13params_structP8ap_fixedILi22ELi17EL9ap_q_mode0EL9ap_o_mode0EL_17639</Object>
<Type>pointer</Type>
<Scope>global</Scope>
<IOProtocol>ap_vld</IOProtocol>
<IOConfig></IOConfig>
<Dir>out</Dir>
<Bits>22</Bits>
<Attribute>data</Attribute>
</RtlPorts>
<RtlPorts>
<name>p_ZZ11network_topP13params_structP8ap_fixedILi22ELi17EL9ap_q_mode0EL9ap_o_mode0EL_17639_ap_vld</name>
<Object>p_ZZ11network_topP13params_structP8ap_fixedILi22ELi17EL9ap_q_mode0EL9ap_o_mode0EL_17639</Object>
<Type>pointer</Type>
<Scope>global</Scope>
<IOProtocol>ap_vld</IOProtocol>
<IOConfig></IOConfig>
<Dir>out</Dir>
<Bits>1</Bits>
<Attribute>control</Attribute>
</RtlPorts>
<RtlPorts>
<name>p_ZZ11network_topP13params_structP8ap_fixedILi22ELi17EL9ap_q_mode0EL9ap_o_mode0EL_17641</name>
<Object>p_ZZ11network_topP13params_structP8ap_fixedILi22ELi17EL9ap_q_mode0EL9ap_o_mode0EL_17641</Object>
<Type>pointer</Type>
<Scope>global</Scope>
<IOProtocol>ap_vld</IOProtocol>
<IOConfig></IOConfig>
<Dir>out</Dir>
<Bits>22</Bits>
<Attribute>data</Attribute>
</RtlPorts>
<RtlPorts>
<name>p_ZZ11network_topP13params_structP8ap_fixedILi22ELi17EL9ap_q_mode0EL9ap_o_mode0EL_17641_ap_vld</name>
<Object>p_ZZ11network_topP13params_structP8ap_fixedILi22ELi17EL9ap_q_mode0EL9ap_o_mode0EL_17641</Object>
<Type>pointer</Type>
<Scope>global</Scope>
<IOProtocol>ap_vld</IOProtocol>
<IOConfig></IOConfig>
<Dir>out</Dir>
<Bits>1</Bits>
<Attribute>control</Attribute>
</RtlPorts>
<RtlPorts>
<name>p_ZZ11network_topP13params_structP8ap_fixedILi22ELi17EL9ap_q_mode0EL9ap_o_mode0EL_17642</name>
<Object>p_ZZ11network_topP13params_structP8ap_fixedILi22ELi17EL9ap_q_mode0EL9ap_o_mode0EL_17642</Object>
<Type>pointer</Type>
<Scope>global</Scope>
<IOProtocol>ap_vld</IOProtocol>
<IOConfig></IOConfig>
<Dir>out</Dir>
<Bits>22</Bits>
<Attribute>data</Attribute>
</RtlPorts>
<RtlPorts>
<name>p_ZZ11network_topP13params_structP8ap_fixedILi22ELi17EL9ap_q_mode0EL9ap_o_mode0EL_17642_ap_vld</name>
<Object>p_ZZ11network_topP13params_structP8ap_fixedILi22ELi17EL9ap_q_mode0EL9ap_o_mode0EL_17642</Object>
<Type>pointer</Type>
<Scope>global</Scope>
<IOProtocol>ap_vld</IOProtocol>
<IOConfig></IOConfig>
<Dir>out</Dir>
<Bits>1</Bits>
<Attribute>control</Attribute>
</RtlPorts>
<RtlPorts>
<name>p_ZZ11network_topP13params_structP8ap_fixedILi22ELi17EL9ap_q_mode0EL9ap_o_mode0EL_17643</name>
<Object>p_ZZ11network_topP13params_structP8ap_fixedILi22ELi17EL9ap_q_mode0EL9ap_o_mode0EL_17643</Object>
<Type>pointer</Type>
<Scope>global</Scope>
<IOProtocol>ap_vld</IOProtocol>
<IOConfig></IOConfig>
<Dir>out</Dir>
<Bits>22</Bits>
<Attribute>data</Attribute>
</RtlPorts>
<RtlPorts>
<name>p_ZZ11network_topP13params_structP8ap_fixedILi22ELi17EL9ap_q_mode0EL9ap_o_mode0EL_17643_ap_vld</name>
<Object>p_ZZ11network_topP13params_structP8ap_fixedILi22ELi17EL9ap_q_mode0EL9ap_o_mode0EL_17643</Object>
<Type>pointer</Type>
<Scope>global</Scope>
<IOProtocol>ap_vld</IOProtocol>
<IOConfig></IOConfig>
<Dir>out</Dir>
<Bits>1</Bits>
<Attribute>control</Attribute>
</RtlPorts>
<RtlPorts>
<name>p_ZZ11network_topP13params_structP8ap_fixedILi22ELi17EL9ap_q_mode0EL9ap_o_mode0EL_17644</name>
<Object>p_ZZ11network_topP13params_structP8ap_fixedILi22ELi17EL9ap_q_mode0EL9ap_o_mode0EL_17644</Object>
<Type>pointer</Type>
<Scope>global</Scope>
<IOProtocol>ap_vld</IOProtocol>
<IOConfig></IOConfig>
<Dir>out</Dir>
<Bits>22</Bits>
<Attribute>data</Attribute>
</RtlPorts>
<RtlPorts>
<name>p_ZZ11network_topP13params_structP8ap_fixedILi22ELi17EL9ap_q_mode0EL9ap_o_mode0EL_17644_ap_vld</name>
<Object>p_ZZ11network_topP13params_structP8ap_fixedILi22ELi17EL9ap_q_mode0EL9ap_o_mode0EL_17644</Object>
<Type>pointer</Type>
<Scope>global</Scope>
<IOProtocol>ap_vld</IOProtocol>
<IOConfig></IOConfig>
<Dir>out</Dir>
<Bits>1</Bits>
<Attribute>control</Attribute>
</RtlPorts>
<RtlPorts>
<name>p_ZZ11network_topP13params_structP8ap_fixedILi22ELi17EL9ap_q_mode0EL9ap_o_mode0EL_17645</name>
<Object>p_ZZ11network_topP13params_structP8ap_fixedILi22ELi17EL9ap_q_mode0EL9ap_o_mode0EL_17645</Object>
<Type>pointer</Type>
<Scope>global</Scope>
<IOProtocol>ap_vld</IOProtocol>
<IOConfig></IOConfig>
<Dir>out</Dir>
<Bits>22</Bits>
<Attribute>data</Attribute>
</RtlPorts>
<RtlPorts>
<name>p_ZZ11network_topP13params_structP8ap_fixedILi22ELi17EL9ap_q_mode0EL9ap_o_mode0EL_17645_ap_vld</name>
<Object>p_ZZ11network_topP13params_structP8ap_fixedILi22ELi17EL9ap_q_mode0EL9ap_o_mode0EL_17645</Object>
<Type>pointer</Type>
<Scope>global</Scope>
<IOProtocol>ap_vld</IOProtocol>
<IOConfig></IOConfig>
<Dir>out</Dir>
<Bits>1</Bits>
<Attribute>control</Attribute>
</RtlPorts>
<RtlPorts>
<name>p_ZZ11network_topP13params_structP8ap_fixedILi22ELi17EL9ap_q_mode0EL9ap_o_mode0EL_17646</name>
<Object>p_ZZ11network_topP13params_structP8ap_fixedILi22ELi17EL9ap_q_mode0EL9ap_o_mode0EL_17646</Object>
<Type>pointer</Type>
<Scope>global</Scope>
<IOProtocol>ap_vld</IOProtocol>
<IOConfig></IOConfig>
<Dir>out</Dir>
<Bits>22</Bits>
<Attribute>data</Attribute>
</RtlPorts>
<RtlPorts>
<name>p_ZZ11network_topP13params_structP8ap_fixedILi22ELi17EL9ap_q_mode0EL9ap_o_mode0EL_17646_ap_vld</name>
<Object>p_ZZ11network_topP13params_structP8ap_fixedILi22ELi17EL9ap_q_mode0EL9ap_o_mode0EL_17646</Object>
<Type>pointer</Type>
<Scope>global</Scope>
<IOProtocol>ap_vld</IOProtocol>
<IOConfig></IOConfig>
<Dir>out</Dir>
<Bits>1</Bits>
<Attribute>control</Attribute>
</RtlPorts>
<RtlPorts>
<name>p_ZZ11network_topP13params_structP8ap_fixedILi22ELi17EL9ap_q_mode0EL9ap_o_mode0EL_17647</name>
<Object>p_ZZ11network_topP13params_structP8ap_fixedILi22ELi17EL9ap_q_mode0EL9ap_o_mode0EL_17647</Object>
<Type>pointer</Type>
<Scope>global</Scope>
<IOProtocol>ap_vld</IOProtocol>
<IOConfig></IOConfig>
<Dir>out</Dir>
<Bits>22</Bits>
<Attribute>data</Attribute>
</RtlPorts>
<RtlPorts>
<name>p_ZZ11network_topP13params_structP8ap_fixedILi22ELi17EL9ap_q_mode0EL9ap_o_mode0EL_17647_ap_vld</name>
<Object>p_ZZ11network_topP13params_structP8ap_fixedILi22ELi17EL9ap_q_mode0EL9ap_o_mode0EL_17647</Object>
<Type>pointer</Type>
<Scope>global</Scope>
<IOProtocol>ap_vld</IOProtocol>
<IOConfig></IOConfig>
<Dir>out</Dir>
<Bits>1</Bits>
<Attribute>control</Attribute>
</RtlPorts>
<RtlPorts>
<name>p_ZZ11network_topP13params_structP8ap_fixedILi22ELi17EL9ap_q_mode0EL9ap_o_mode0EL_17649</name>
<Object>p_ZZ11network_topP13params_structP8ap_fixedILi22ELi17EL9ap_q_mode0EL9ap_o_mode0EL_17649</Object>
<Type>pointer</Type>
<Scope>global</Scope>
<IOProtocol>ap_vld</IOProtocol>
<IOConfig></IOConfig>
<Dir>out</Dir>
<Bits>22</Bits>
<Attribute>data</Attribute>
</RtlPorts>
<RtlPorts>
<name>p_ZZ11network_topP13params_structP8ap_fixedILi22ELi17EL9ap_q_mode0EL9ap_o_mode0EL_17649_ap_vld</name>
<Object>p_ZZ11network_topP13params_structP8ap_fixedILi22ELi17EL9ap_q_mode0EL9ap_o_mode0EL_17649</Object>
<Type>pointer</Type>
<Scope>global</Scope>
<IOProtocol>ap_vld</IOProtocol>
<IOConfig></IOConfig>
<Dir>out</Dir>
<Bits>1</Bits>
<Attribute>control</Attribute>
</RtlPorts>
<RtlPorts>
<name>p_ZZ11network_topP13params_structP8ap_fixedILi22ELi17EL9ap_q_mode0EL9ap_o_mode0EL_17650</name>
<Object>p_ZZ11network_topP13params_structP8ap_fixedILi22ELi17EL9ap_q_mode0EL9ap_o_mode0EL_17650</Object>
<Type>pointer</Type>
<Scope>global</Scope>
<IOProtocol>ap_vld</IOProtocol>
<IOConfig></IOConfig>
<Dir>out</Dir>
<Bits>22</Bits>
<Attribute>data</Attribute>
</RtlPorts>
<RtlPorts>
<name>p_ZZ11network_topP13params_structP8ap_fixedILi22ELi17EL9ap_q_mode0EL9ap_o_mode0EL_17650_ap_vld</name>
<Object>p_ZZ11network_topP13params_structP8ap_fixedILi22ELi17EL9ap_q_mode0EL9ap_o_mode0EL_17650</Object>
<Type>pointer</Type>
<Scope>global</Scope>
<IOProtocol>ap_vld</IOProtocol>
<IOConfig></IOConfig>
<Dir>out</Dir>
<Bits>1</Bits>
<Attribute>control</Attribute>
</RtlPorts>
<RtlPorts>
<name>p_ZZ11network_topP13params_structP8ap_fixedILi22ELi17EL9ap_q_mode0EL9ap_o_mode0EL_17652</name>
<Object>p_ZZ11network_topP13params_structP8ap_fixedILi22ELi17EL9ap_q_mode0EL9ap_o_mode0EL_17652</Object>
<Type>pointer</Type>
<Scope>global</Scope>
<IOProtocol>ap_vld</IOProtocol>
<IOConfig></IOConfig>
<Dir>out</Dir>
<Bits>22</Bits>
<Attribute>data</Attribute>
</RtlPorts>
<RtlPorts>
<name>p_ZZ11network_topP13params_structP8ap_fixedILi22ELi17EL9ap_q_mode0EL9ap_o_mode0EL_17652_ap_vld</name>
<Object>p_ZZ11network_topP13params_structP8ap_fixedILi22ELi17EL9ap_q_mode0EL9ap_o_mode0EL_17652</Object>
<Type>pointer</Type>
<Scope>global</Scope>
<IOProtocol>ap_vld</IOProtocol>
<IOConfig></IOConfig>
<Dir>out</Dir>
<Bits>1</Bits>
<Attribute>control</Attribute>
</RtlPorts>
<RtlPorts>
<name>p_ZZ11network_topP13params_structP8ap_fixedILi22ELi17EL9ap_q_mode0EL9ap_o_mode0EL_17653</name>
<Object>p_ZZ11network_topP13params_structP8ap_fixedILi22ELi17EL9ap_q_mode0EL9ap_o_mode0EL_17653</Object>
<Type>pointer</Type>
<Scope>global</Scope>
<IOProtocol>ap_vld</IOProtocol>
<IOConfig></IOConfig>
<Dir>out</Dir>
<Bits>22</Bits>
<Attribute>data</Attribute>
</RtlPorts>
<RtlPorts>
<name>p_ZZ11network_topP13params_structP8ap_fixedILi22ELi17EL9ap_q_mode0EL9ap_o_mode0EL_17653_ap_vld</name>
<Object>p_ZZ11network_topP13params_structP8ap_fixedILi22ELi17EL9ap_q_mode0EL9ap_o_mode0EL_17653</Object>
<Type>pointer</Type>
<Scope>global</Scope>
<IOProtocol>ap_vld</IOProtocol>
<IOConfig></IOConfig>
<Dir>out</Dir>
<Bits>1</Bits>
<Attribute>control</Attribute>
</RtlPorts>
<RtlPorts>
<name>p_ZZ11network_topP13params_structP8ap_fixedILi22ELi17EL9ap_q_mode0EL9ap_o_mode0EL_17654</name>
<Object>p_ZZ11network_topP13params_structP8ap_fixedILi22ELi17EL9ap_q_mode0EL9ap_o_mode0EL_17654</Object>
<Type>pointer</Type>
<Scope>global</Scope>
<IOProtocol>ap_vld</IOProtocol>
<IOConfig></IOConfig>
<Dir>out</Dir>
<Bits>22</Bits>
<Attribute>data</Attribute>
</RtlPorts>
<RtlPorts>
<name>p_ZZ11network_topP13params_structP8ap_fixedILi22ELi17EL9ap_q_mode0EL9ap_o_mode0EL_17654_ap_vld</name>
<Object>p_ZZ11network_topP13params_structP8ap_fixedILi22ELi17EL9ap_q_mode0EL9ap_o_mode0EL_17654</Object>
<Type>pointer</Type>
<Scope>global</Scope>
<IOProtocol>ap_vld</IOProtocol>
<IOConfig></IOConfig>
<Dir>out</Dir>
<Bits>1</Bits>
<Attribute>control</Attribute>
</RtlPorts>
<RtlPorts>
<name>p_ZZ11network_topP13params_structP8ap_fixedILi22ELi17EL9ap_q_mode0EL9ap_o_mode0EL_17655</name>
<Object>p_ZZ11network_topP13params_structP8ap_fixedILi22ELi17EL9ap_q_mode0EL9ap_o_mode0EL_17655</Object>
<Type>pointer</Type>
<Scope>global</Scope>
<IOProtocol>ap_vld</IOProtocol>
<IOConfig></IOConfig>
<Dir>out</Dir>
<Bits>22</Bits>
<Attribute>data</Attribute>
</RtlPorts>
<RtlPorts>
<name>p_ZZ11network_topP13params_structP8ap_fixedILi22ELi17EL9ap_q_mode0EL9ap_o_mode0EL_17655_ap_vld</name>
<Object>p_ZZ11network_topP13params_structP8ap_fixedILi22ELi17EL9ap_q_mode0EL9ap_o_mode0EL_17655</Object>
<Type>pointer</Type>
<Scope>global</Scope>
<IOProtocol>ap_vld</IOProtocol>
<IOConfig></IOConfig>
<Dir>out</Dir>
<Bits>1</Bits>
<Attribute>control</Attribute>
</RtlPorts>
<RtlPorts>
<name>p_ZZ11network_topP13params_structP8ap_fixedILi22ELi17EL9ap_q_mode0EL9ap_o_mode0EL_17656</name>
<Object>p_ZZ11network_topP13params_structP8ap_fixedILi22ELi17EL9ap_q_mode0EL9ap_o_mode0EL_17656</Object>
<Type>pointer</Type>
<Scope>global</Scope>
<IOProtocol>ap_vld</IOProtocol>
<IOConfig></IOConfig>
<Dir>out</Dir>
<Bits>22</Bits>
<Attribute>data</Attribute>
</RtlPorts>
<RtlPorts>
<name>p_ZZ11network_topP13params_structP8ap_fixedILi22ELi17EL9ap_q_mode0EL9ap_o_mode0EL_17656_ap_vld</name>
<Object>p_ZZ11network_topP13params_structP8ap_fixedILi22ELi17EL9ap_q_mode0EL9ap_o_mode0EL_17656</Object>
<Type>pointer</Type>
<Scope>global</Scope>
<IOProtocol>ap_vld</IOProtocol>
<IOConfig></IOConfig>
<Dir>out</Dir>
<Bits>1</Bits>
<Attribute>control</Attribute>
</RtlPorts>
<RtlPorts>
<name>p_ZZ11network_topP13params_structP8ap_fixedILi22ELi17EL9ap_q_mode0EL9ap_o_mode0EL_17657</name>
<Object>p_ZZ11network_topP13params_structP8ap_fixedILi22ELi17EL9ap_q_mode0EL9ap_o_mode0EL_17657</Object>
<Type>pointer</Type>
<Scope>global</Scope>
<IOProtocol>ap_vld</IOProtocol>
<IOConfig></IOConfig>
<Dir>out</Dir>
<Bits>22</Bits>
<Attribute>data</Attribute>
</RtlPorts>
<RtlPorts>
<name>p_ZZ11network_topP13params_structP8ap_fixedILi22ELi17EL9ap_q_mode0EL9ap_o_mode0EL_17657_ap_vld</name>
<Object>p_ZZ11network_topP13params_structP8ap_fixedILi22ELi17EL9ap_q_mode0EL9ap_o_mode0EL_17657</Object>
<Type>pointer</Type>
<Scope>global</Scope>
<IOProtocol>ap_vld</IOProtocol>
<IOConfig></IOConfig>
<Dir>out</Dir>
<Bits>1</Bits>
<Attribute>control</Attribute>
</RtlPorts>
<RtlPorts>
<name>p_ZZ11network_topP13params_structP8ap_fixedILi22ELi17EL9ap_q_mode0EL9ap_o_mode0EL_17658</name>
<Object>p_ZZ11network_topP13params_structP8ap_fixedILi22ELi17EL9ap_q_mode0EL9ap_o_mode0EL_17658</Object>
<Type>pointer</Type>
<Scope>global</Scope>
<IOProtocol>ap_vld</IOProtocol>
<IOConfig></IOConfig>
<Dir>out</Dir>
<Bits>22</Bits>
<Attribute>data</Attribute>
</RtlPorts>
<RtlPorts>
<name>p_ZZ11network_topP13params_structP8ap_fixedILi22ELi17EL9ap_q_mode0EL9ap_o_mode0EL_17658_ap_vld</name>
<Object>p_ZZ11network_topP13params_structP8ap_fixedILi22ELi17EL9ap_q_mode0EL9ap_o_mode0EL_17658</Object>
<Type>pointer</Type>
<Scope>global</Scope>
<IOProtocol>ap_vld</IOProtocol>
<IOConfig></IOConfig>
<Dir>out</Dir>
<Bits>1</Bits>
<Attribute>control</Attribute>
</RtlPorts>
<RtlPorts>
<name>p_ZZ11network_topP13params_structP8ap_fixedILi22ELi17EL9ap_q_mode0EL9ap_o_mode0EL_17659</name>
<Object>p_ZZ11network_topP13params_structP8ap_fixedILi22ELi17EL9ap_q_mode0EL9ap_o_mode0EL_17659</Object>
<Type>pointer</Type>
<Scope>global</Scope>
<IOProtocol>ap_vld</IOProtocol>
<IOConfig></IOConfig>
<Dir>out</Dir>
<Bits>22</Bits>
<Attribute>data</Attribute>
</RtlPorts>
<RtlPorts>
<name>p_ZZ11network_topP13params_structP8ap_fixedILi22ELi17EL9ap_q_mode0EL9ap_o_mode0EL_17659_ap_vld</name>
<Object>p_ZZ11network_topP13params_structP8ap_fixedILi22ELi17EL9ap_q_mode0EL9ap_o_mode0EL_17659</Object>
<Type>pointer</Type>
<Scope>global</Scope>
<IOProtocol>ap_vld</IOProtocol>
<IOConfig></IOConfig>
<Dir>out</Dir>
<Bits>1</Bits>
<Attribute>control</Attribute>
</RtlPorts>
</InterfaceSummary>

</profile>
